Workbook

Sheet Cover
B2: Project Daylight - Clinuvel Pharmaceuticals (ASX: CUV / Nasdaq: CUVL)
B3: Private-equity take-private screening model | prepared 22-Sep-2026 from public information | A$ millions | FYE 30 June
B5: PROJECT | C5: Daylight
B6: Running case (MCASE) | C6: =MCASE -> 3
B7: Case label | C7: =MCASE!C8 -> Sponsor base | Base
B9: Key outputs - running case
B10: Offer price per share (A$) | C10: =LBO!D19 -> 10.75
B11: Premium to undisturbed (A$8.24) | C11: =LBO!D20 -> 0.30461165
B12: Equity purchase price (A$m) | C12: =LBO!D24 -> 544.81
B13: Implied TEV (A$m) | C13: =LBO!D29 -> 269.34096
B14: TEV / FY27E status-quo Adj. EBITDA | C14: =LBO!D33 -> 7.3798268
B15: TEV / FY28E post cost-out Adj. EBITDA | C15: =LBO!D35 -> 4.6841556
B16: Clinuvel cash applied (A$m) | C16: =LBO!D28 -> 235.46904
B17: New debt (A$m) | C17: =LBO!D74+LBO!D75 -> 75
B18: Equity invested (A$m) | C18: =LBO!D80 -> 251.39824
B19: 5-year MoIC | C19: =LBO!D255 -> 1.5929689
B20: 5-year IRR | C20: =LBO!D256 -> 0.10437355
B21: Max offer at 20% IRR (A$/sh) | C21: =ATP!C58 -> 9.2040734
B22: Model checks (0 = OK) | C22: =ROUND(ABS(LBO!D79)+SUMPRODUCT(ABS(LBO!G158:M158))+ABS(LBO!I105)+ABS(Contrib!C31)+ABS(ATP!C60),3) -> 0
B24: Tabs
B25: Hist | C25: Reported history FY20-FY26 and FY26A base-year inputs (reported vs estimated flagged)
B26: MCASE | C26: Master case driver - 23 cases (5 operating x 4 financing at the base offer + 3 variants)
B27: OPCASE | C27: Five operating cases: revenue by region, cost base, sponsor cost-out, capex, NWC
B28: FINCASE | C28: Four financing cases: base 2.0x private credit, high 3.0x + PIK, low 1.0x, no debt
B29: LBO | C29: Single-tab vertical model: S&U, PF BS, IS, BS, CF, debt, interest, credit, returns
B30: ATP | C30: Reverse LBO: max offer per share by exit multiple and hurdle IRR
B31: Contrib | C31: Value creation bridge (revenue, margin, multiple, cash generation, fees)
B32: Sensitivity | C32: Price x multiple grids; case capture table; op x fin matrices; probability-weighted view
B33: CVR | C33: Contingent value right design and valuation
B35: Colour code & mechanics
B36: Blue: hard-coded input
B37: Black: formula on same tab
B38: Green: link to another tab
B39: Iterative calculation must be ON (File > Options > Formulas; 1,000 iterations, 0.0000001). Average-balance interest (CIRC=1) and the Sensitivity capture cells are circular by design.
B40: To refresh the case tables: set MCASE to 1..23 in turn (or run model/run_cases.py), then back to the base case (3).
B42: Important
B43: Screening model built from public information only (company releases, press, third-party research summaries).
B44: Several inputs are analyst estimates, not disclosures: FY26 cost split by function, US/EU revenue split,
B45: working capital, dilutive securities, financing terms and all forward scenarios. They are flagged in the source notes.
B46: Not investment advice. Figures should be tied to the FY2026 annual report and 20-F before any use.

Sheet Hist
B2: Historical financials & FY26A base-year inputs
B3: A$m. Blue = reported or estimated input (see source column). Estimates flagged 'EST'/'ASSUMPTION'.
B5: Reported history (FY ending 30 June)
C6: FY20 | D6: FY21 | E6: FY22 | F6: FY23 | G6: FY24 | H6: FY25 | I6: FY26 | K6: Source / note
B7: Product revenue (SCENESSE) | C7: n.v. | D7: n.v. | E7: n.v. | F7: 77.9 | G7: 88 | H7: 95.018 | I7: 94.024 | K7: FY23 derived (FY24 +13% to A$88m, Morningstar); FY25 A$95.018m (Appendix 4E); FY26 A$94.024m
B8: Total revenues incl. interest & other income | C8: 32.565 | D8: 48.451 | E8: 66.987 | F8: 83 | G8: 95.31 | H8: 105.3 | I8: 101.153 | K8: As reported; FY20/FY21 'revenue' as reported (interest immaterial then)
B9: Total expenses | C9: n.v. | D9: n.v. | E9: n.v. | F9: n.v. | G9: 44.75 | H9: 53.7 | I9: 53.5 | K9: FY24 derived from FY25 +20%; FY25/FY26 as reported
B10: Profit before tax | C10: n.v. | D10: n.v. | E10: 34.321 | F10: n.v. | G10: 50.6 | H10: 51.6 | I10: 47.653 | K10: FY22 as reported (adj. PBT A$39.8m); FY24 derived (FY25 +2%); FY26 derived
B11: Net profit after tax | C11: 15.1 | D11: 24.728 | E11: 20.876 | F11: 30.605 | G11: 35.64 | H11: 36.2 | I11: 33.9 | K11: FY20 derived from FY21 +64%; FY22 as reported (non-cash items); others as reported
B12: Cash at year end | C12: n.v. | D12: n.v. | E12: 121.509 | F12: 157 | G12: 183.7 | H12: 224.1 | I12: 252.055 | K12: FY24 derived (FY25 +22%); others as reported
B13: Dividend per share (A$) | C13: n.v. | D13: n.v. | E13: 0.04 | F13: n.v. | G13: n.v. | H13: 0.05 | I13: 0.05 | K13: Fully franked where stated
B14: Product revenue growth | D14: =IFERROR(D7/C7-1,"") | E14: =IFERROR(E7/D7-1,"") | F14: =IFERROR(F7/E7-1,"") | G14: =IFERROR(G7/F7-1,"") -> 0.1296534 | H14: =IFERROR(H7/G7-1,"") -> 0.07975 | I14: =IFERROR(I7/H7-1,"") -> -0.010461176
B15: NPAT margin on total revenues | C15: =IFERROR(C11/C8,"") -> 0.46368801 | D15: =IFERROR(D11/D8,"") -> 0.5103713 | E15: =IFERROR(E11/E8,"") -> 0.31164256 | F15: =IFERROR(F11/F8,"") -> 0.36873494 | G15: =IFERROR(G11/G8,"") -> 0.37393768 | H15: =IFERROR(H11/H8,"") -> 0.34377968 | I15: =IFERROR(I11/I8,"") -> 0.33513588
B16: Half-year data: H1 FY26 sales A$36.93m (+4%), NPAT A$10.44m (-26%), cash A$233.0m; H1 interest A$5.26m (Appendix 4D, 26-Feb-2026). Implied H2 FY26 sales A$57.1m (c.-4% y/y).
B18: FY26A base-year inputs used by the LBO tab
B19: Item | C19: A$m | K19: Source / note
B20: Product revenue FY26A | C20: 94.024 | K20: Revenue from ordinary activities; FY26 results release, 27-Aug-2026 (GlobeNewswire/Nasdaq; 6-K)
B21: US share of product revenue | C21: 0.4 | K21: ASSUMPTION - US share of FY26 product revenue not in accessible disclosure; test 30-50%
B22: US SCENESSE revenue FY26A | C22: =C20*C21 -> 37.6096
B23: Europe & RoW SCENESSE revenue FY26A | C23: =C20-C22 -> 56.4144
B24: Total revenues incl. interest & other income | C24: 101.153 | K24: Total revenues incl. interest & other income; FY26 results release, 27-Aug-2026 (GlobeNewswire/Nasdaq; 6-K)
B25: Interest & other income (derived) | C25: =C24-C20 -> 7.129
B26: Total expenses (reported) | C26: 53.5 | K26: Total expenses; FY26 results release, 27-Aug-2026 (GlobeNewswire/Nasdaq; 6-K)
B27: Cost of goods / supply & distribution | C27: 7 | K27: EST: gross margin >90% (Kalkine, 2026)
B28: Core SCENESSE commercial, medical, PV & regulatory | C28: 11 | K28: EST: A$8-11m range (research stream)
B29: Corporate, listing & G&A | C29: 10.5 | K29: EST: A$8-11m range incl. ASX/SEC listing costs
B30: Communications, branding, marketing & consumer (CBM) | C30: 5 | K30: EST: CBM +100% in FY25; A$4-7m
B31: Vitiligo clinical program (CUV105/CUV107) | C31: 12 | K31: EST: A$10-15m; clinical dev. +215% in FY25
B32: Other R&D (Singapore, PRENUMBRA, NEURACTHEL, XP/VP) | C32: 6 | K32: EST: A$6-10m
B33: Depreciation & amortisation | C33: 2 | K33: EST
B34: Check: estimated split less reported expenses (should be 0) | C34: =SUM(C27:C33)-C26 -> 0
B35: Profit before tax (derived) | C35: =C24-C26 -> 47.653
B36: NPAT (reported) | C36: 33.9 | K36: NPAT (-6% y/y); FY26 results release, 27-Aug-2026 (GlobeNewswire/Nasdaq; 6-K)
B37: Income tax (derived) | C37: =C35-C36 -> 13.753
B38: Cash 30-Jun-2026 | C38: 252.055 | K38: Cash reserves (+12%); FY26 results release, 27-Aug-2026 (GlobeNewswire/Nasdaq; 6-K)
B39: Net assets 30-Jun-2026 | C39: 272.9 | K39: Net assets 30-Jun-2026; strategic reorganisation release 23-Jul-2026
B40: Net working capital & other operating items (est.) | C40: 15 | K40: ESTIMATE - net working capital & other net operating items (c.16% of sales)
B41: Operating cash flow FY26A (memo) | C41: 36.9 | K41: Operating cash inflow; FY26 results release, 27-Aug-2026 (GlobeNewswire/Nasdaq; 6-K)

Sheet MCASE
B2: Master case driver (MCASE)
B3: Change C5 to run any case. Every tab keys off the running row (row 8).
B5: MCASE | C5: 3
B7: Case # | C7: Case label | D7: Op case | E7: Fin case | F7: Offer price (A$/sh) | G7: Trans. exp. (% equity) | H7: Mgmt rollover (% equity) | I7: Exit multiple (x EBITDA) | J7: Min. cash (A$m) | K7: Comment
B8: =C5 -> 3 | C8: =OFFSET(C$9,$C$5-1,0,1,1) -> Sponsor base | Base | D8: =OFFSET(D$9,$C$5-1,0,1,1) -> 3 | E8: =OFFSET(E$9,$C$5-1,0,1,1) -> 1 | F8: =OFFSET(F$9,$C$5-1,0,1,1) -> 10.75 | G8: =OFFSET(G$9,$C$5-1,0,1,1) -> 0.0275 | H8: =OFFSET(H$9,$C$5-1,0,1,1) -> 0 | I8: =OFFSET(I$9,$C$5-1,0,1,1) -> 5.5 | J8: =OFFSET(J$9,$C$5-1,0,1,1) -> 40
B9: 1 | C9: Downside | Base | D9: 1 | E9: 1 | F9: 10.75 | G9: 0.0275 | H9: 0 | I9: 3.5 | J9: 40 | K9: Cases 1-20 = 5 operating x 4 financing cases at the base offer
B10: 2 | C10: Conservative | Base | D10: 2 | E10: 1 | F10: 10.75 | G10: 0.0275 | H10: 0 | I10: 4.5 | J10: 40
B11: 3 | C11: Sponsor base | Base | D11: 3 | E11: 1 | F11: 10.75 | G11: 0.0275 | H11: 0 | I11: 5.5 | J11: 40
B12: 4 | C12: Orals underwhelm | Base | D12: 4 | E12: 1 | F12: 10.75 | G12: 0.0275 | H12: 0 | I12: 7 | J12: 40
B13: 5 | C13: Upside (vitiligo) | Base | D13: 5 | E13: 1 | F13: 10.75 | G13: 0.0275 | H13: 0 | I13: 9 | J13: 40
B14: 6 | C14: Downside | High leverage | D14: 1 | E14: 2 | F14: 10.75 | G14: 0.0275 | H14: 0 | I14: 3.5 | J14: 40
B15: 7 | C15: Conservative | High leverage | D15: 2 | E15: 2 | F15: 10.75 | G15: 0.0275 | H15: 0 | I15: 4.5 | J15: 40
B16: 8 | C16: Sponsor base | High leverage | D16: 3 | E16: 2 | F16: 10.75 | G16: 0.0275 | H16: 0 | I16: 5.5 | J16: 40
B17: 9 | C17: Orals underwhelm | High leverage | D17: 4 | E17: 2 | F17: 10.75 | G17: 0.0275 | H17: 0 | I17: 7 | J17: 40
B18: 10 | C18: Upside (vitiligo) | High leverage | D18: 5 | E18: 2 | F18: 10.75 | G18: 0.0275 | H18: 0 | I18: 9 | J18: 40
B19: 11 | C19: Downside | Low leverage | D19: 1 | E19: 3 | F19: 10.75 | G19: 0.0275 | H19: 0 | I19: 3.5 | J19: 40
B20: 12 | C20: Conservative | Low leverage | D20: 2 | E20: 3 | F20: 10.75 | G20: 0.0275 | H20: 0 | I20: 4.5 | J20: 40
B21: 13 | C21: Sponsor base | Low leverage | D21: 3 | E21: 3 | F21: 10.75 | G21: 0.0275 | H21: 0 | I21: 5.5 | J21: 40
... B28: 20 | C28: Upside (vitiligo) | No acquisition debt | D28: 5 | E28: 4 | F28: 10.75 | G28: 0.0275 | H28: 0 | I28: 9 | J28: 40
B29: 21 | C29: Sponsor base | Base | CEO rolls 6.8% | D29: 3 | E29: 1 | F29: 10.75 | G29: 0.0275 | H29: 0.068 | I29: 5.5 | J29: 40 | K29: CEO rolls his c.6.8% stake (separate scheme class / GN19 protocol)
B30: 22 | C30: Sponsor base | Base | A$9.50 offer | D30: 3 | E30: 1 | F30: 9.5 | G30: 0.0275 | H30: 0 | I30: 5.5 | J30: 40 | K30: c.+15% premium to undisturbed
B31: 23 | C31: Sponsor base | Base | A$12.50 offer | D31: 3 | E31: 1 | F31: 12.5 | G31: 0.0275 | H31: 0 | I31: 5.5 | J31: 40 | K31: c.+52% premium; ~Mar-2026 trading levels
B32: 24 | C32: Base revenue, no cost-out | Base | D32: 6 | E32: 1 | F32: 10.75 | G32: 0.0275 | H32: 0 | I32: 5.5 | J32: 40 | K32: Tests how much of the thesis is cost-out: management plan, no savings
B35: Offer price context: undisturbed A$8.24 (1-Sep-2026); A$10.75 = c.+30% premium; cash per share at close c.A$5.4. Exit multiples scale with the durability of each operating case.

Sheet OPCASE
B2: Operating cases (OPCASE)
B3: Running block pulls the active case via OFFSET(case-1 cell, (OPCASE-1) x OpStep). FY27E = company status-quo plan (pre-close); FY28E-FY32E = sponsor plan.
B5: Running operating case (OPCASE) | C5: =MCASE!D8 -> 3
B6: OpStep (rows between case blocks) | C6: =ROW(B48)-ROW(B30) -> 18
B8: Running operating case (output - do not edit)
B9: Driver | C9: Unit | D9: Case description | H9: FY27E | I9: FY28E | J9: FY29E | K9: FY30E | L9: FY31E | M9: FY32E
B10: Case name / description | C10: =OFFSET(C$30,(OPCASE-1)*$C$6,0,1,1) -> Sponsor base | D10: =OFFSET(D$30,(OPCASE-1)*$C$6,0,1,1) -> Dersimelagon approved; APOLLO misses/delays bitopertin; SCENESSE keeps implant-preferring & severe patients
B11: US SCENESSE revenue growth | C11: % | H11: =OFFSET(H$31,(OPCASE-1)*$C$6,0,1,1) -> -0.05 | I11: =OFFSET(I$31,(OPCASE-1)*$C$6,0,1,1) -> -0.18 | J11: =OFFSET(J$31,(OPCASE-1)*$C$6,0,1,1) -> -0.15 | K11: =OFFSET(K$31,(OPCASE-1)*$C$6,0,1,1) -> -0.08 | L11: =OFFSET(L$31,(OPCASE-1)*$C$6,0,1,1) -> -0.05 | M11: =OFFSET(M$31,(OPCASE-1)*$C$6,0,1,1) -> -0.03
B12: Europe & RoW SCENESSE revenue growth | C12: % | H12: =OFFSET(H$32,(OPCASE-1)*$C$6,0,1,1) -> 0.05 | I12: =OFFSET(I$32,(OPCASE-1)*$C$6,0,1,1) -> 0.04 | J12: =OFFSET(J$32,(OPCASE-1)*$C$6,0,1,1) -> 0.02 | K12: =OFFSET(K$32,(OPCASE-1)*$C$6,0,1,1) -> -0.03 | L12: =OFFSET(L$32,(OPCASE-1)*$C$6,0,1,1) -> -0.05 | M12: =OFFSET(M$32,(OPCASE-1)*$C$6,0,1,1) -> -0.03
B13: Vitiligo revenue | C13: A$m | H13: =OFFSET(H$33,(OPCASE-1)*$C$6,0,1,1) -> 0 | I13: =OFFSET(I$33,(OPCASE-1)*$C$6,0,1,1) -> 0 | J13: =OFFSET(J$33,(OPCASE-1)*$C$6,0,1,1) -> 0 | K13: =OFFSET(K$33,(OPCASE-1)*$C$6,0,1,1) -> 0 | L13: =OFFSET(L$33,(OPCASE-1)*$C$6,0,1,1) -> 0 | M13: =OFFSET(M$33,(OPCASE-1)*$C$6,0,1,1) -> 0
B14: Other new product revenue | C14: A$m | H14: =OFFSET(H$34,(OPCASE-1)*$C$6,0,1,1) -> 0 | I14: =OFFSET(I$34,(OPCASE-1)*$C$6,0,1,1) -> 0 | J14: =OFFSET(J$34,(OPCASE-1)*$C$6,0,1,1) -> 0 | K14: =OFFSET(K$34,(OPCASE-1)*$C$6,0,1,1) -> 0 | L14: =OFFSET(L$34,(OPCASE-1)*$C$6,0,1,1) -> 0 | M14: =OFFSET(M$34,(OPCASE-1)*$C$6,0,1,1) -> 0
B15: COGS % of revenue | C15: % | H15: =OFFSET(H$35,(OPCASE-1)*$C$6,0,1,1) -> 0.075 | I15: =OFFSET(I$35,(OPCASE-1)*$C$6,0,1,1) -> 0.075 | J15: =OFFSET(J$35,(OPCASE-1)*$C$6,0,1,1) -> 0.075 | K15: =OFFSET(K$35,(OPCASE-1)*$C$6,0,1,1) -> 0.075 | L15: =OFFSET(L$35,(OPCASE-1)*$C$6,0,1,1) -> 0.075 | M15: =OFFSET(M$35,(OPCASE-1)*$C$6,0,1,1) -> 0.075
B16: Core & corporate cost inflation | C16: % | H16: =OFFSET(H$36,(OPCASE-1)*$C$6,0,1,1) -> 0.03 | I16: =OFFSET(I$36,(OPCASE-1)*$C$6,0,1,1) -> 0.03 | J16: =OFFSET(J$36,(OPCASE-1)*$C$6,0,1,1) -> 0.03 | K16: =OFFSET(K$36,(OPCASE-1)*$C$6,0,1,1) -> 0.03 | L16: =OFFSET(L$36,(OPCASE-1)*$C$6,0,1,1) -> 0.03 | M16: =OFFSET(M$36,(OPCASE-1)*$C$6,0,1,1) -> 0.03
B17: Competitive-defence spend (patient services, access) | C17: A$m | H17: =OFFSET(H$37,(OPCASE-1)*$C$6,0,1,1) -> 0 | I17: =OFFSET(I$37,(OPCASE-1)*$C$6,0,1,1) -> -1.5 | J17: =OFFSET(J$37,(OPCASE-1)*$C$6,0,1,1) -> -1.5 | K17: =OFFSET(K$37,(OPCASE-1)*$C$6,0,1,1) -> -1 | L17: =OFFSET(L$37,(OPCASE-1)*$C$6,0,1,1) -> -1 | M17: =OFFSET(M$37,(OPCASE-1)*$C$6,0,1,1) -> -1
B18: Sponsor corporate cost savings (% of status quo) | C18: % | H18: =OFFSET(H$38,(OPCASE-1)*$C$6,0,1,1) -> 0 | I18: =OFFSET(I$38,(OPCASE-1)*$C$6,0,1,1) -> 0.35 | J18: =OFFSET(J$38,(OPCASE-1)*$C$6,0,1,1) -> 0.45 | K18: =OFFSET(K$38,(OPCASE-1)*$C$6,0,1,1) -> 0.45 | L18: =OFFSET(L$38,(OPCASE-1)*$C$6,0,1,1) -> 0.45 | M18: =OFFSET(M$38,(OPCASE-1)*$C$6,0,1,1) -> 0.45
B19: CBM & consumer spend | C19: A$m | H19: =OFFSET(H$39,(OPCASE-1)*$C$6,0,1,1) -> -5.2 | I19: =OFFSET(I$39,(OPCASE-1)*$C$6,0,1,1) -> -1 | J19: =OFFSET(J$39,(OPCASE-1)*$C$6,0,1,1) -> -1 | K19: =OFFSET(K$39,(OPCASE-1)*$C$6,0,1,1) -> -1 | L19: =OFFSET(L$39,(OPCASE-1)*$C$6,0,1,1) -> -1 | M19: =OFFSET(M$39,(OPCASE-1)*$C$6,0,1,1) -> -1
B20: Vitiligo clinical spend | C20: A$m | H20: =OFFSET(H$40,(OPCASE-1)*$C$6,0,1,1) -> -15 | I20: =OFFSET(I$40,(OPCASE-1)*$C$6,0,1,1) -> -2 | J20: =OFFSET(J$40,(OPCASE-1)*$C$6,0,1,1) -> 0 | K20: =OFFSET(K$40,(OPCASE-1)*$C$6,0,1,1) -> 0 | L20: =OFFSET(L$40,(OPCASE-1)*$C$6,0,1,1) -> 0 | M20: =OFFSET(M$40,(OPCASE-1)*$C$6,0,1,1) -> 0
B21: Other R&D spend | C21: A$m | H21: =OFFSET(H$41,(OPCASE-1)*$C$6,0,1,1) -> -6.5 | I21: =OFFSET(I$41,(OPCASE-1)*$C$6,0,1,1) -> -1.5 | J21: =OFFSET(J$41,(OPCASE-1)*$C$6,0,1,1) -> -1.5 | K21: =OFFSET(K$41,(OPCASE-1)*$C$6,0,1,1) -> -1.5 | L21: =OFFSET(L$41,(OPCASE-1)*$C$6,0,1,1) -> -1.5 | M21: =OFFSET(M$41,(OPCASE-1)*$C$6,0,1,1) -> -1.5
B22: Vitiligo launch & commercial costs | C22: A$m | H22: =OFFSET(H$42,(OPCASE-1)*$C$6,0,1,1) -> 0 | I22: =OFFSET(I$42,(OPCASE-1)*$C$6,0,1,1) -> 0 | J22: =OFFSET(J$42,(OPCASE-1)*$C$6,0,1,1) -> 0 | K22: =OFFSET(K$42,(OPCASE-1)*$C$6,0,1,1) -> 0 | L22: =OFFSET(L$42,(OPCASE-1)*$C$6,0,1,1) -> 0 | M22: =OFFSET(M$42,(OPCASE-1)*$C$6,0,1,1) -> 0
B23: Non-recurring items (relocation, restructuring) | C23: A$m | H23: =OFFSET(H$43,(OPCASE-1)*$C$6,0,1,1) -> -4 | I23: =OFFSET(I$43,(OPCASE-1)*$C$6,0,1,1) -> -4 | J23: =OFFSET(J$43,(OPCASE-1)*$C$6,0,1,1) -> 0 | K23: =OFFSET(K$43,(OPCASE-1)*$C$6,0,1,1) -> 0 | L23: =OFFSET(L$43,(OPCASE-1)*$C$6,0,1,1) -> 0 | M23: =OFFSET(M$43,(OPCASE-1)*$C$6,0,1,1) -> 0
B24: Capex | C24: A$m | H24: =OFFSET(H$44,(OPCASE-1)*$C$6,0,1,1) -> -4 | I24: =OFFSET(I$44,(OPCASE-1)*$C$6,0,1,1) -> -1.5 | J24: =OFFSET(J$44,(OPCASE-1)*$C$6,0,1,1) -> -1.5 | K24: =OFFSET(K$44,(OPCASE-1)*$C$6,0,1,1) -> -1.5 | L24: =OFFSET(L$44,(OPCASE-1)*$C$6,0,1,1) -> -1.5 | M24: =OFFSET(M$44,(OPCASE-1)*$C$6,0,1,1) -> -1.5
B25: Net working capital % of revenue | C25: % | H25: =OFFSET(H$45,(OPCASE-1)*$C$6,0,1,1) -> 0.16 | I25: =OFFSET(I$45,(OPCASE-1)*$C$6,0,1,1) -> 0.16 | J25: =OFFSET(J$45,(OPCASE-1)*$C$6,0,1,1) -> 0.16 | K25: =OFFSET(K$45,(OPCASE-1)*$C$6,0,1,1) -> 0.16 | L25: =OFFSET(L$45,(OPCASE-1)*$C$6,0,1,1) -> 0.16 | M25: =OFFSET(M$45,(OPCASE-1)*$C$6,0,1,1) -> 0.16
B29: Operating case 1: Downside
B30: Case 1 | C30: Downside | D30: Both orals approved (dersimelagon ~Feb-27, bitopertin ~mid-27) and adopted fast; EU oral from FY29; price pressure
B31: US SCENESSE revenue growth | C31: % | H31: -0.08 | I31: -0.35 | J31: -0.35 | K31: -0.25 | L31: -0.2 | M31: -0.15
B32: Europe & RoW SCENESSE revenue growth | C32: % | H32: 0.04 | I32: 0.02 | J32: -0.05 | K32: -0.15 | L32: -0.2 | M32: -0.15
B33: Vitiligo revenue | C33: A$m | H33: 0 | I33: 0 | J33: 0 | K33: 0 | L33: 0 | M33: 0
B34: Other new product revenue | C34: A$m | H34: 0 | I34: 0 | J34: 0 | K34: 0 | L34: 0 | M34: 0
B35: COGS % of revenue | C35: % | H35: 0.075 | I35: 0.08 | J35: 0.085 | K35: 0.09 | L35: 0.095 | M35: 0.1
B36: Core & corporate cost inflation | C36: % | H36: 0.03 | I36: 0.03 | J36: 0.03 | K36: 0.03 | L36: 0.03 | M36: 0.03
B37: Competitive-defence spend (patient services, access) | C37: A$m | H37: 0 | I37: -2 | J37: -2 | K37: -1.5 | L37: -1 | M37: -1
B38: Sponsor corporate cost savings (% of status quo) | C38: % | H38: 0 | I38: 0.35 | J38: 0.45 | K38: 0.45 | L38: 0.45 | M38: 0.45
B39: CBM & consumer spend | C39: A$m | H39: -5.2 | I39: -1 | J39: -1 | K39: -1 | L39: -1 | M39: -1
B40: Vitiligo clinical spend | C40: A$m | H40: -15 | I40: -2 | J40: 0 | K40: 0 | L40: 0 | M40: 0
B41: Other R&D spend | C41: A$m | H41: -6.5 | I41: -1.5 | J41: -1.5 | K41: -1.5 | L41: -1.5 | M41: -1.5
B42: Vitiligo launch & commercial costs | C42: A$m | H42: 0 | I42: 0 | J42: 0 | K42: 0 | L42: 0 | M42: 0
... B45: Net working capital % of revenue | C45: % | H45: 0.16 | I45: 0.16 | J45: 0.16 | K45: 0.16 | L45: 0.16 | M45: 0.16
B47: Operating case 2: Conservative
B48: Case 2 | C48: Conservative | D48: Dersimelagon approved Feb-27 with solid uptake; bitopertin also approved; EU competition from FY30
B49: US SCENESSE revenue growth | C49: % | H49: -0.06 | I49: -0.25 | J49: -0.25 | K49: -0.15 | L49: -0.1 | M49: -0.08
B50: Europe & RoW SCENESSE revenue growth | C50: % | H50: 0.04 | I50: 0.03 | J50: 0 | K50: -0.08 | L50: -0.1 | M50: -0.08
B51: Vitiligo revenue | C51: A$m | H51: 0 | I51: 0 | J51: 0 | K51: 0 | L51: 0 | M51: 0
B52: Other new product revenue | C52: A$m | H52: 0 | I52: 0 | J52: 0 | K52: 0 | L52: 0 | M52: 0
B53: COGS % of revenue | C53: % | H53: 0.075 | I53: 0.0775 | J53: 0.08 | K53: 0.085 | L53: 0.085 | M53: 0.085
B54: Core & corporate cost inflation | C54: % | H54: 0.03 | I54: 0.03 | J54: 0.03 | K54: 0.03 | L54: 0.03 | M54: 0.03
B55: Competitive-defence spend (patient services, access) | C55: A$m | H55: 0 | I55: -2 | J55: -2 | K55: -1.5 | L55: -1 | M55: -1
B56: Sponsor corporate cost savings (% of status quo) | C56: % | H56: 0 | I56: 0.35 | J56: 0.45 | K56: 0.45 | L56: 0.45 | M56: 0.45
B57: CBM & consumer spend | C57: A$m | H57: -5.2 | I57: -1 | J57: -1 | K57: -1 | L57: -1 | M57: -1
B58: Vitiligo clinical spend | C58: A$m | H58: -15 | I58: -2 | J58: 0 | K58: 0 | L58: 0 | M58: 0
B59: Other R&D spend | C59: A$m | H59: -6.5 | I59: -1.5 | J59: -1.5 | K59: -1.5 | L59: -1.5 | M59: -1.5
B60: Vitiligo launch & commercial costs | C60: A$m | H60: 0 | I60: 0 | J60: 0 | K60: 0 | L60: 0 | M60: 0
... B63: Net working capital % of revenue | C63: % | H63: 0.16 | I63: 0.16 | J63: 0.16 | K63: 0.16 | L63: 0.16 | M63: 0.16
B65: Operating case 3: Sponsor base
B66: Case 3 | C66: Sponsor base | D66: Dersimelagon approved; APOLLO misses/delays bitopertin; SCENESSE keeps implant-preferring & severe patients
B67: US SCENESSE revenue growth | C67: % | H67: -0.05 | I67: -0.18 | J67: -0.15 | K67: -0.08 | L67: -0.05 | M67: -0.03
B68: Europe & RoW SCENESSE revenue growth | C68: % | H68: 0.05 | I68: 0.04 | J68: 0.02 | K68: -0.03 | L68: -0.05 | M68: -0.03
B69: Vitiligo revenue | C69: A$m | H69: 0 | I69: 0 | J69: 0 | K69: 0 | L69: 0 | M69: 0
B70: Other new product revenue | C70: A$m | H70: 0 | I70: 0 | J70: 0 | K70: 0 | L70: 0 | M70: 0
B71: COGS % of revenue | C71: % | H71: 0.075 | I71: 0.075 | J71: 0.075 | K71: 0.075 | L71: 0.075 | M71: 0.075
B72: Core & corporate cost inflation | C72: % | H72: 0.03 | I72: 0.03 | J72: 0.03 | K72: 0.03 | L72: 0.03 | M72: 0.03
B73: Competitive-defence spend (patient services, access) | C73: A$m | H73: 0 | I73: -1.5 | J73: -1.5 | K73: -1 | L73: -1 | M73: -1
B74: Sponsor corporate cost savings (% of status quo) | C74: % | H74: 0 | I74: 0.35 | J74: 0.45 | K74: 0.45 | L74: 0.45 | M74: 0.45
B75: CBM & consumer spend | C75: A$m | H75: -5.2 | I75: -1 | J75: -1 | K75: -1 | L75: -1 | M75: -1
B76: Vitiligo clinical spend | C76: A$m | H76: -15 | I76: -2 | J76: 0 | K76: 0 | L76: 0 | M76: 0
B77: Other R&D spend | C77: A$m | H77: -6.5 | I77: -1.5 | J77: -1.5 | K77: -1.5 | L77: -1.5 | M77: -1.5
B78: Vitiligo launch & commercial costs | C78: A$m | H78: 0 | I78: 0 | J78: 0 | K78: 0 | L78: 0 | M78: 0
... B81: Net working capital % of revenue | C81: % | H81: 0.16 | I81: 0.16 | J81: 0.16 | K81: 0.16 | L81: 0.16 | M81: 0.16
B83: Operating case 4: Orals underwhelm
B84: Case 4 | C84: Orals underwhelm | D84: Orals approved but modest efficacy; combination use; Canada, adolescents & EU year-round dosing drive growth
B85: US SCENESSE revenue growth | C85: % | H85: -0.03 | I85: -0.05 | J85: -0.03 | K85: 0 | L85: 0.02 | M85: 0.02
B86: Europe & RoW SCENESSE revenue growth | C86: % | H86: 0.05 | I86: 0.05 | J86: 0.04 | K86: 0.03 | L86: 0.02 | M86: 0.02
B87: Vitiligo revenue | C87: A$m | H87: 0 | I87: 0 | J87: 0 | K87: 0 | L87: 0 | M87: 0
B88: Other new product revenue | C88: A$m | H88: 0 | I88: 0 | J88: 0 | K88: 0 | L88: 0 | M88: 0
B89: COGS % of revenue | C89: % | H89: 0.075 | I89: 0.075 | J89: 0.075 | K89: 0.075 | L89: 0.075 | M89: 0.075
B90: Core & corporate cost inflation | C90: % | H90: 0.03 | I90: 0.03 | J90: 0.03 | K90: 0.03 | L90: 0.03 | M90: 0.03
B91: Competitive-defence spend (patient services, access) | C91: A$m | H91: 0 | I91: -1 | J91: -1 | K91: -0.5 | L91: -0.5 | M91: -0.5
B92: Sponsor corporate cost savings (% of status quo) | C92: % | H92: 0 | I92: 0.35 | J92: 0.45 | K92: 0.45 | L92: 0.45 | M92: 0.45
B93: CBM & consumer spend | C93: A$m | H93: -5.2 | I93: -1 | J93: -1 | K93: -1 | L93: -1 | M93: -1
B94: Vitiligo clinical spend | C94: A$m | H94: -15 | I94: -2 | J94: 0 | K94: 0 | L94: 0 | M94: 0
B95: Other R&D spend | C95: A$m | H95: -6.5 | I95: -2.5 | J95: -2.5 | K95: -2.5 | L95: -2.5 | M95: -2.5
B96: Vitiligo launch & commercial costs | C96: A$m | H96: 0 | I96: 0 | J96: 0 | K96: 0 | L96: 0 | M96: 0
... B99: Net working capital % of revenue | C99: % | H99: 0.16 | I99: 0.16 | J99: 0.16 | K99: 0.16 | L99: 0.16 | M99: 0.16
B101: Operating case 5: Upside (vitiligo)
B102: Case 5 | C102: Upside (vitiligo) | D102: As case 4 plus CUV105 positive: sponsor funds CUV107; vitiligo approval & launch from FY30
B103: US SCENESSE revenue growth | C103: % | H103: -0.03 | I103: -0.05 | J103: -0.03 | K103: 0 | L103: 0.02 | M103: 0.02
B104: Europe & RoW SCENESSE revenue growth | C104: % | H104: 0.05 | I104: 0.05 | J104: 0.04 | K104: 0.03 | L104: 0.02 | M104: 0.02
B105: Vitiligo revenue | C105: A$m | H105: 0 | I105: 0 | J105: 0 | K105: 5 | L105: 20 | M105: 40
B106: Other new product revenue | C106: A$m | H106: 0 | I106: 0 | J106: 0 | K106: 0 | L106: 0 | M106: 0
B107: COGS % of revenue | C107: % | H107: 0.075 | I107: 0.075 | J107: 0.075 | K107: 0.075 | L107: 0.075 | M107: 0.075
B108: Core & corporate cost inflation | C108: % | H108: 0.03 | I108: 0.03 | J108: 0.03 | K108: 0.03 | L108: 0.03 | M108: 0.03
B109: Competitive-defence spend (patient services, access) | C109: A$m | H109: 0 | I109: -1 | J109: -1 | K109: -0.5 | L109: -0.5 | M109: -0.5
B110: Sponsor corporate cost savings (% of status quo) | C110: % | H110: 0 | I110: 0.35 | J110: 0.45 | K110: 0.45 | L110: 0.45 | M110: 0.45
B111: CBM & consumer spend | C111: A$m | H111: -5.2 | I111: -1 | J111: -1 | K111: -1 | L111: -1 | M111: -1
B112: Vitiligo clinical spend | C112: A$m | H112: -15 | I112: -14 | J112: -12 | K112: -6 | L112: -3 | M112: -3
B113: Other R&D spend | C113: A$m | H113: -6.5 | I113: -2.5 | J113: -2.5 | K113: -2.5 | L113: -2.5 | M113: -2.5
B114: Vitiligo launch & commercial costs | C114: A$m | H114: 0 | I114: 0 | J114: -5 | K114: -12 | L114: -15 | M114: -16
... B117: Net working capital % of revenue | C117: % | H117: 0.16 | I117: 0.16 | J117: 0.16 | K117: 0.16 | L117: 0.16 | M117: 0.16
B119: Operating case 6: Base revenue, no cost-out
B120: Case 6 | C120: Base revenue, no cost-out | D120: Case 3 revenue, but management's plan continues: CUV107 funded, US build-out, CBM & Singapore R&D; no sponsor savings
B121: US SCENESSE revenue growth | C121: % | H121: -0.05 | I121: -0.18 | J121: -0.15 | K121: -0.08 | L121: -0.05 | M121: -0.03
...

Sheet FINCASE
B2: Financing cases (FINCASE)
B3: Running output = OFFSET(case-1 cell, (FINCASE-1) x FinStep). Terms are indicative specialist private-credit terms for a single-product orphan asset (no term sheet).
B5: Running financing case (FINCASE) | E5: =MCASE!E8 -> 1
B6: FinStep (rows between case blocks) | E6: =ROW(B54)-ROW(B34) -> 20
B8: Running financing assumptions (output - do not edit)
B9: Case name | E9: =OFFSET(E$34,(FINCASE-1)*$E$6,0,1,1) -> Base (specialist private credit)
B10: Unitranche term loan (x FY27E Adj. EBITDA) | E10: =OFFSET(E$35,(FINCASE-1)*$E$6,0,1,1) -> 2 | G10: Leverage sized on FY27E (status-quo) Adj. EBITDA, i.e. before sponsor cost-out; 5% amortisation reflects lender caution on a single product facing new entrants.
B11: Term loan margin over base rate | E11: =OFFSET(E$36,(FINCASE-1)*$E$6,0,1,1) -> 0.06
B12: Term loan base-rate floor | E12: =OFFSET(E$37,(FINCASE-1)*$E$6,0,1,1) -> 0
B13: Term loan upfront fee / OID | E13: =OFFSET(E$38,(FINCASE-1)*$E$6,0,1,1) -> 0.025
B14: Term loan mandatory amortisation (% p.a.) | E14: =OFFSET(E$39,(FINCASE-1)*$E$6,0,1,1) -> 0.05
B15: Term loan tenor (years) | E15: =OFFSET(E$40,(FINCASE-1)*$E$6,0,1,1) -> 5
B16: HoldCo PIK notes (x FY27E Adj. EBITDA) | E16: =OFFSET(E$41,(FINCASE-1)*$E$6,0,1,1) -> 0
B17: PIK coupon | E17: =OFFSET(E$42,(FINCASE-1)*$E$6,0,1,1) -> 0.12
B18: PIK upfront fee | E18: =OFFSET(E$43,(FINCASE-1)*$E$6,0,1,1) -> 0.02
B19: PIK tenor (years) | E19: =OFFSET(E$44,(FINCASE-1)*$E$6,0,1,1) -> 6
B20: Revolver commitment (A$m) | E20: =OFFSET(E$45,(FINCASE-1)*$E$6,0,1,1) -> 20
B21: Revolver margin | E21: =OFFSET(E$46,(FINCASE-1)*$E$6,0,1,1) -> 0.04
B22: Revolver commitment fee (on undrawn) | E22: =OFFSET(E$47,(FINCASE-1)*$E$6,0,1,1) -> 0.014
B23: Revolver upfront fee | E23: =OFFSET(E$48,(FINCASE-1)*$E$6,0,1,1) -> 0.01
B24: Revolver tenor (years) | E24: =OFFSET(E$49,(FINCASE-1)*$E$6,0,1,1) -> 5
B25: Covenant: max net debt / EBITDA | E25: =OFFSET(E$50,(FINCASE-1)*$E$6,0,1,1) -> 3
B26: Covenant: min EBITDA / cash interest | E26: =OFFSET(E$51,(FINCASE-1)*$E$6,0,1,1) -> 3
B33: Financing case 1: Base (specialist private credit)
B34: Case 1 | E34: Base (specialist private credit)
B35: Unitranche term loan (x FY27E Adj. EBITDA) | E35: 2
B36: Term loan margin over base rate | E36: 0.06
B37: Term loan base-rate floor | E37: 0
B38: Term loan upfront fee / OID | E38: 0.025
B39: Term loan mandatory amortisation (% p.a.) | E39: 0.05
B40: Term loan tenor (years) | E40: 5
B41: HoldCo PIK notes (x FY27E Adj. EBITDA) | E41: 0
B42: PIK coupon | E42: 0.12
B43: PIK upfront fee | E43: 0.02
B44: PIK tenor (years) | E44: 6
B45: Revolver commitment (A$m) | E45: 20
B46: Revolver margin | E46: 0.04
... B51: Covenant: min EBITDA / cash interest | E51: 3
B53: Financing case 2: High leverage (+ HoldCo PIK)
B54: Case 2 | E54: High leverage (+ HoldCo PIK)
B55: Unitranche term loan (x FY27E Adj. EBITDA) | E55: 3
B56: Term loan margin over base rate | E56: 0.0675
B57: Term loan base-rate floor | E57: 0
B58: Term loan upfront fee / OID | E58: 0.03
B59: Term loan mandatory amortisation (% p.a.) | E59: 0.05
B60: Term loan tenor (years) | E60: 5
B61: HoldCo PIK notes (x FY27E Adj. EBITDA) | E61: 0.75
B62: PIK coupon | E62: 0.12
B63: PIK upfront fee | E63: 0.02
B64: PIK tenor (years) | E64: 6
B65: Revolver commitment (A$m) | E65: 20
B66: Revolver margin | E66: 0.04
... B71: Covenant: min EBITDA / cash interest | E71: 2
B73: Financing case 3: Low leverage
B74: Case 3 | E74: Low leverage
B75: Unitranche term loan (x FY27E Adj. EBITDA) | E75: 1
B76: Term loan margin over base rate | E76: 0.055
B77: Term loan base-rate floor | E77: 0
B78: Term loan upfront fee / OID | E78: 0.0225
B79: Term loan mandatory amortisation (% p.a.) | E79: 0.05
B80: Term loan tenor (years) | E80: 5
B81: HoldCo PIK notes (x FY27E Adj. EBITDA) | E81: 0
B82: PIK coupon | E82: 0.12
B83: PIK upfront fee | E83: 0.02
B84: PIK tenor (years) | E84: 6
B85: Revolver commitment (A$m) | E85: 20
B86: Revolver margin | E86: 0.04
... B91: Covenant: min EBITDA / cash interest | E91: 4
B93: Financing case 4: No acquisition debt (cash-box)
B94: Case 4 | E94: No acquisition debt (cash-box)
B95: Unitranche term loan (x FY27E Adj. EBITDA) | E95: 0
B96: Term loan margin over base rate | E96: 0.06
B97: Term loan base-rate floor | E97: 0
B98: Term loan upfront fee / OID | E98: 0.025
B99: Term loan mandatory amortisation (% p.a.) | E99: 0.05
B100: Term loan tenor (years) | E100: 5
B101: HoldCo PIK notes (x FY27E Adj. EBITDA) | E101: 0
B102: PIK coupon | E102: 0.12
B103: PIK upfront fee | E103: 0.02
B104: PIK tenor (years) | E104: 6
B105: Revolver commitment (A$m) | E105: 20
B106: Revolver margin | E106: 0.04
... B111: Covenant: min EBITDA / cash interest | E111: 3

Sheet LBO
B2: Project Daylight - Clinuvel Pharmaceuticals take-private: screening LBO
B3: A$ millions unless stated | FYE 30 June | Close assumed 30-Jun-2027 (end FY27E) | 5-year hold to FY32E | blue = input, black = formula, green = link
B5: CIRC switch (1 = average-balance interest; iterative calc on) | D5: 1
B6: Running master case (MCASE) | D6: =MCASE -> 3
B7: Case label | D7: =MCASE!C8 -> Sponsor base | Base
B8: Operating case / financing case | D8: =MCASE!D8 -> 3 | E8: =MCASE!E8 -> 1
B9: Operating case description | D9: =OPCASE!D10 -> Dersimelagon approved; APOLLO misses/delays bitopertin; SCENESSE keeps implant-preferring & severe patients
B11: Timeline
B12: Fiscal year | G12: FY26A | H12: FY27E | I12: FY28E | J12: FY29E | K12: FY30E | L12: FY31E | M12: FY32E
B13: Period end | G13: =DATE(2026,6,30) -> 46203 | H13: =DATE(YEAR(G13)+1,6,30) -> 46568 | I13: =DATE(YEAR(H13)+1,6,30) -> 46934 | J13: =DATE(YEAR(I13)+1,6,30) -> 47299 | K13: =DATE(YEAR(J13)+1,6,30) -> 47664 | L13: =DATE(YEAR(K13)+1,6,30) -> 48029 | M13: =DATE(YEAR(L13)+1,6,30) -> 48395
B14: Period | G14: Actual | H14: Status quo | I14: Sponsor | J14: Sponsor | K14: Sponsor | L14: Sponsor | M14: Sponsor
B15: Years since close | I15: =YEAR(I13)-YEAR($H$13) -> 1 | J15: =YEAR(J13)-YEAR($H$13) -> 2 | K15: =YEAR(K13)-YEAR($H$13) -> 3 | L15: =YEAR(L13)-YEAR($H$13) -> 4 | M15: =YEAR(M13)-YEAR($H$13) -> 5
B17: Transaction assumptions
B18: Undisturbed share price (A$) | C18: ASX close 1-Sep-2026 (A$9.18 on 27-Aug results day, -12.7%); CUVL US$5.85 on 16-Sep | D18: 8.24
B19: Offer price per share (A$) | C19: MCASE running row | D19: =MCASE!F8 -> 10.75
B20: Premium to undisturbed | D20: =D19/D18-1 -> 0.30461165
B21: Basic shares outstanding (m) | C21: Derived: Vanguard 2,523,018 sh = 5.003% (Form 603, 14-Aug-2026) | D21: 50.43
B22: Dilutive securities (m) | C22: EST: performance rights; CEO holds no LTI (Jul-2026 terms) | D22: 0.25
B23: Fully diluted shares (m) | D23: =D21+D22 -> 50.68
B24: Equity purchase price | D24: =D19*D23 -> 544.81
B25: Clinuvel cash at close (pre-deal, FY27E) | C25: Status-quo FY27E closing cash (cash flow section) | D25: =H175 -> 275.46904
B26: Existing debt refinanced | C26: No borrowings (leases ignored) | D26: 0
B27: Minimum operating cash retained | C27: Named MIN_CASH | D27: =MCASE!J8 -> 40
B28: Clinuvel cash applied to the transaction | D28: =MAX(0,D25-D27) -> 235.46904
B29: Implied transaction enterprise value (TEV) | D29: =D24+D26-D25 -> 269.34096
B30: LTM Adj. EBITDA at close (FY27E, status quo) | D30: =H129 -> 36.496922
B31: FY26A Adj. EBITDA | D31: =G129 -> 42.524
B32: FY28E Adj. EBITDA (first sponsor year) | D32: =I129 -> 57.50043
B33: TEV / LTM (FY27E) Adj. EBITDA | D33: =D29/D30 -> 7.3798268
B34: TEV / FY26A Adj. EBITDA | D34: =D29/D31 -> 6.3338577
B35: TEV / FY28E Adj. EBITDA (post cost-out) | D35: =D29/D32 -> 4.6841556
B36: TEV / FY27E revenue | D36: =D29/H113 -> 2.8362357
B37: Equity purchase price / FY26A NPAT | D37: =D24/G141 -> 16.071091
B38: Cash per fully diluted share at close (A$) | D38: =D25/D23 -> 5.4354585
B39: Transaction expenses (% of equity purchase price) | D39: =MCASE!G8 -> 0.0275
B40: Transaction expenses | C40: Advisers, legal, IER, scheme, FIRB/ACCC, US counsel | D40: =D39*D24 -> 14.982275
B41: Management rollover (% of equity purchase price) | D41: =MCASE!H8 -> 0
B42: Management rollover | D42: =D41*D24 -> 0
B43: Exit multiple (x LTM Adj. EBITDA) | D43: =MCASE!I8 -> 5.5
B44: Exit costs (% of TEV) | C44: Sell-side fees at exit, % of TEV | D44: 0.015
B45: Tax rate | C45: FY25 29.8%, FY26 28.9% effective; US redomicile may lower | D45: 0.28
B46: Interest yield on cash | C46: Yield on cash (H1 FY26 interest A$5.3m on ~A$230m) | D46: 0.0325
B47: Dividend paid in FY27E (A$/sh) | C47: FY26 final dividend paid 18-Sep-2026 (fully franked) | D47: 0.05
B48: D&A run-rate | C48: D&A run-rate (EST) | D48: 2
B49: Incremental US HQ / Nasdaq run-rate cost | C49: EST: incremental US HQ / Nasdaq / SEC run-rate cost from FY27 | D49: 2.5
B50: Excess-cash distribution to equity (once debt repaid) | C50: Share of excess cash distributed to equity once debt repaid | D50: 1
B51: Debt sizing increment (A$m) | C51: Debt sizing rounding increment | D51: 5
B53: Financing assumptions (from FINCASE)
B54: Tranche | G54: Lev. (x) | H54: A$m | I54: Margin/cpn | J54: Floor | K54: Fee % | L54: Fee A$m | M54: Tenor | N54: Amort.
B55: Revolving credit facility (commitment; undrawn at close) | H55: =FINCASE!E20 -> 20 | I55: =FINCASE!E21 -> 0.04 | K55: =FINCASE!E23 -> 0.01 | L55: =H55*K55 -> 0.2 | M55: =FINCASE!E24 -> 5 | N55: 0
B56: Unitranche term loan | G56: =FINCASE!E10 -> 2 | H56: =MROUND(G56*$D$30,$D$51) -> 75 | I56: =FINCASE!E11 -> 0.06 | J56: =FINCASE!E12 -> 0 | K56: =FINCASE!E13 -> 0.025 | L56: =H56*K56 -> 1.875 | M56: =FINCASE!E15 -> 5 | N56: =FINCASE!E14 -> 0.05
B57: HoldCo PIK notes | G57: =FINCASE!E16 -> 0 | H57: =MROUND(G57*$D$30,$D$51) -> 0 | I57: =FINCASE!E17 -> 0.12 | K57: =FINCASE!E18 -> 0.02 | L57: =H57*K57 -> 0 | M57: =FINCASE!E19 -> 6 | N57: 0
B58: Total funded debt / total fees | G58: =G56+G57 -> 2 | H58: =H56+H57 -> 75 | L58: =SUM(L55:L57) -> 2.075
B59: Revolver commitment fee (on undrawn) | I59: =FINCASE!E22 -> 0.014
B60: Revolver drawn at close | H60: 0
B61: Covenant: max net debt / EBITDA | D61: =FINCASE!E25 -> 3
B62: Covenant: min EBITDA / cash interest | D62: =FINCASE!E26 -> 3
B64: Sources & uses at close (30-Jun-2027)
B65: Uses | D65: A$m | E65: %
B66: Purchase of equity (fully diluted) | D66: =D24 -> 544.81 | E66: =D66/$D$70 -> 0.96964181
B67: Refinance existing debt | D67: =D26 -> 0 | E67: =D67/$D$70 -> 0
B68: Transaction expenses | D68: =D40 -> 14.982275 | E68: =D68/$D$70 -> 0.02666515
B69: Financing fees | D69: =L58 -> 2.075 | E69: =D69/$D$70 -> 0.003693043
B70: Total uses | D70: =SUM(D66:D69) -> 561.86727 | E70: =D70/$D$70 -> 1
B71: Sources
B72: Clinuvel balance-sheet cash applied | D72: =D28 -> 235.46904 | E72: =D72/$D$78 -> 0.41908302
B73: Revolver drawn | D73: =H60 -> 0 | E73: =D73/$D$78 -> 0
B74: Unitranche term loan | D74: =H56 -> 75 | E74: =D74/$D$78 -> 0.13348348
B75: HoldCo PIK notes | D75: =H57 -> 0 | E75: =D75/$D$78 -> 0
B76: Management rollover | D76: =D42 -> 0 | E76: =D76/$D$78 -> 0
B77: Sponsor equity (plug) | D77: =D70-SUM(D72:D76) -> 251.39824 | E77: =D77/$D$78 -> 0.44743349
B78: Total sources | D78: =SUM(D72:D77) -> 561.86727 | E78: =D78/$D$78 -> 1
B79: Check: sources less uses (should be 0) | D79: =D78-D70 -> 0
B80: Total equity invested (sponsor + rollover) | D80: =D77+D76 -> 251.39824
B81: Equity / (equity + new debt) | D81: =D80/(D80+D73+D74+D75) -> 0.77021935
B82: Equity / total sources | D82: =D80/D78 -> 0.44743349
B83: PF net debt / LTM Adj. EBITDA | D83: =(D73+D74+D75-D27)/D30 -> 0.95898498
B84: Memo: equity invested excl. price-driven items (fees - cash applied - new debt) | C84: Invested(p) = p x FD shares x (1+fee%) + this | D84: =D69-D72-D73-D74-D75 -> -308.39404
B86: Purchase accounting (simplified: excess over book to goodwill & intangibles)
B87: Equity purchase price | D87: =D24 -> 544.81
B88: Less: pre-deal book equity (FY27E) | D88: =-G103 -> -298.50832
B89: Goodwill & intangibles created (plug) | D89: =D87+D88 -> 246.30168
B91: Pro forma closing balance sheet (30-Jun-2027)
G92: Pre-deal | H92: Adjust. | I92: PF close
B93: Cash | G93: =H175 -> 275.46904 | H93: =-D28+D73 -> -235.46904 | I93: =G93+H93 -> 40
B94: Net working capital & other | G94: =H147 -> 15.194278 | H94: 0 | I94: =G94+H94 -> 15.194278
B95: PP&E & other non-current | G95: =H148 -> 7.845 | H95: 0 | I95: =G95+H95 -> 7.845
B96: Goodwill & intangibles (new) | G96: 0 | H96: =D89 -> 246.30168 | I96: =G96+H96 -> 246.30168
B97: Capitalised financing fees | G97: 0 | H97: =D69 -> 2.075 | I97: =G97+H97 -> 2.075
B98: Total assets | G98: =SUM(G93:G97) -> 298.50832 | H98: =SUM(H93:H97) -> 12.907648 | I98: =SUM(I93:I97) -> 311.41596
B99: Revolver | G99: 0 | H99: =D73 -> 0 | I99: =G99+H99 -> 0
B100: Unitranche term loan | G100: 0 | H100: =D74 -> 75 | I100: =G100+H100 -> 75
B101: HoldCo PIK notes | G101: 0 | H101: =D75 -> 0 | I101: =G101+H101 -> 0
B102: Total debt | G102: =SUM(G99:G101) -> 0 | H102: =SUM(H99:H101) -> 75 | I102: =SUM(I99:I101) -> 75
B103: Shareholders' equity | G103: =G156+H141+H169 -> 298.50832 | H103: =-G103+D80-D68 -> -62.092352 | I103: =G103+H103 -> 236.41596
B104: Total liabilities & equity | G104: =G102+G103 -> 298.50832 | H104: =H102+H103 -> 12.907648 | I104: =I102+I103 -> 311.41596
B105: Check: assets less L&E (should be 0) | G105: =G98-G104 -> 0 | H105: =H98-H104 -> 0 | I105: =I98-I104 -> 0
B107: Income statement
G108: FY26A | H108: FY27E | I108: FY28E | J108: FY29E | K108: FY30E | L108: FY31E | M108: FY32E
B109: SCENESSE revenue - United States | G109: =Hist!C22 -> 37.6096 | H109: =G109*(1+OPCASE!H11) -> 35.72912 | I109: =H109*(1+OPCASE!I11) -> 29.297878 | J109: =I109*(1+OPCASE!J11) -> 24.903197 | K109: =J109*(1+OPCASE!K11) -> 22.910941 | L109: =K109*(1+OPCASE!L11) -> 21.765394 | M109: =L109*(1+OPCASE!M11) -> 21.112432
...

Sheet ATP
B2: Ability to pay (reverse LBO) - running case
B3: Max offer per share that still earns the hurdle IRR, given the running operating/financing case (Y5 exit). Cash flows include interim distributions.
B5: FY32E LTM Adj. EBITDA | C5: =LBO!M129 -> 46.359082 | K5: Max equity = NPV at the hurdle of distributions (Y1-Y4) plus Y5 distribution and exit equity. Max price = (max equity + cash applied + new debt - financing fees) / (1 + fee%) / FD shares. Debt and cash applied do not depend on price.
B6: FY32E debt | C6: =LBO!M155 -> 0
B7: FY32E cash | C7: =LBO!M146 -> 40
B8: Exit costs (% TEV) | C8: =LBO!D44 -> 0.015
B9: Interim distributions Y1-Y5 are discounted at each hurdle
B10: Clinuvel cash applied at close | C10: =LBO!D28 -> 235.46904
B11: New debt raised at close | C11: =LBO!D73+LBO!D74+LBO!D75 -> 75
B12: Financing fees | C12: =LBO!D69 -> 2.075
B13: Transaction expenses (% of equity price) | C13: =LBO!D39 -> 0.0275
B14: Fully diluted shares (m) | C14: =LBO!D23 -> 50.68
B15: Undisturbed price (A$) | C15: =LBO!D18 -> 8.24
B16: Pre-deal cash at close | C16: =LBO!D25 -> 275.46904
B17: LTM (FY27E) Adj. EBITDA | C17: =LBO!D30 -> 36.496922
B19: Max equity invested (A$m) | C19: 0.15 | D19: 0.2 | E19: 0.25
B20: Exit at 3.0x LTM EBITDA | C20: =(NPV(C$19,LBO!I245:L245)+(LBO!M245+($G20*$C$5*(1-$C$8)-$C$6+$C$7))/(1+C$19)^5) -> 151.43307 | D20: =(NPV(D$19,LBO!I245:L245)+(LBO!M245+($G20*$C$5*(1-$C$8)-$C$6+$C$7))/(1+D$19)^5) -> 125.01808 | E20: =(NPV(E$19,LBO!I245:L245)+(LBO!M245+($G20*$C$5*(1-$C$8)-$C$6+$C$7))/(1+E$19)^5) -> 104.13281 | G20: 3
B21: Exit at 4.0x LTM EBITDA | C21: =(NPV(C$19,LBO!I245:L245)+(LBO!M245+($G21*$C$5*(1-$C$8)-$C$6+$C$7))/(1+C$19)^5) -> 174.136 | D21: =(NPV(D$19,LBO!I245:L245)+(LBO!M245+($G21*$C$5*(1-$C$8)-$C$6+$C$7))/(1+D$19)^5) -> 143.3693 | E21: =(NPV(E$19,LBO!I245:L245)+(LBO!M245+($G21*$C$5*(1-$C$8)-$C$6+$C$7))/(1+E$19)^5) -> 119.09589 | G21: 4
B22: Exit at 5.0x LTM EBITDA | C22: =(NPV(C$19,LBO!I245:L245)+(LBO!M245+($G22*$C$5*(1-$C$8)-$C$6+$C$7))/(1+C$19)^5) -> 196.83893 | D22: =(NPV(D$19,LBO!I245:L245)+(LBO!M245+($G22*$C$5*(1-$C$8)-$C$6+$C$7))/(1+D$19)^5) -> 161.72051 | E22: =(NPV(E$19,LBO!I245:L245)+(LBO!M245+($G22*$C$5*(1-$C$8)-$C$6+$C$7))/(1+E$19)^5) -> 134.05897 | G22: 5
B23: Exit at 6.0x LTM EBITDA | C23: =(NPV(C$19,LBO!I245:L245)+(LBO!M245+($G23*$C$5*(1-$C$8)-$C$6+$C$7))/(1+C$19)^5) -> 219.54185 | D23: =(NPV(D$19,LBO!I245:L245)+(LBO!M245+($G23*$C$5*(1-$C$8)-$C$6+$C$7))/(1+D$19)^5) -> 180.07173 | E23: =(NPV(E$19,LBO!I245:L245)+(LBO!M245+($G23*$C$5*(1-$C$8)-$C$6+$C$7))/(1+E$19)^5) -> 149.02205 | G23: 6
B24: Exit at 7.0x LTM EBITDA | C24: =(NPV(C$19,LBO!I245:L245)+(LBO!M245+($G24*$C$5*(1-$C$8)-$C$6+$C$7))/(1+C$19)^5) -> 242.24478 | D24: =(NPV(D$19,LBO!I245:L245)+(LBO!M245+($G24*$C$5*(1-$C$8)-$C$6+$C$7))/(1+D$19)^5) -> 198.42294 | E24: =(NPV(E$19,LBO!I245:L245)+(LBO!M245+($G24*$C$5*(1-$C$8)-$C$6+$C$7))/(1+E$19)^5) -> 163.98513 | G24: 7
B25: Exit at 8.0x LTM EBITDA | C25: =(NPV(C$19,LBO!I245:L245)+(LBO!M245+($G25*$C$5*(1-$C$8)-$C$6+$C$7))/(1+C$19)^5) -> 264.94771 | D25: =(NPV(D$19,LBO!I245:L245)+(LBO!M245+($G25*$C$5*(1-$C$8)-$C$6+$C$7))/(1+D$19)^5) -> 216.77416 | E25: =(NPV(E$19,LBO!I245:L245)+(LBO!M245+($G25*$C$5*(1-$C$8)-$C$6+$C$7))/(1+E$19)^5) -> 178.94821 | G25: 8
B26: Exit at 9.0x LTM EBITDA | C26: =(NPV(C$19,LBO!I245:L245)+(LBO!M245+($G26*$C$5*(1-$C$8)-$C$6+$C$7))/(1+C$19)^5) -> 287.65063 | D26: =(NPV(D$19,LBO!I245:L245)+(LBO!M245+($G26*$C$5*(1-$C$8)-$C$6+$C$7))/(1+D$19)^5) -> 235.12537 | E26: =(NPV(E$19,LBO!I245:L245)+(LBO!M245+($G26*$C$5*(1-$C$8)-$C$6+$C$7))/(1+E$19)^5) -> 193.91129 | G26: 9
B28: Max offer price per share (A$) | C28: 0.15 | D28: 0.2 | E28: 0.25
B29: Exit at 3.0x LTM EBITDA | C29: =(C20+$C$10+$C$11-$C$12)/(1+$C$13)/$C$14 -> 8.8303137 | D29: =(D20+$C$10+$C$11-$C$12)/(1+$C$13)/$C$14 -> 8.3230521 | E29: =(E20+$C$10+$C$11-$C$12)/(1+$C$13)/$C$14 -> 7.9219807 | G29: 3
B30: Exit at 4.0x LTM EBITDA | C30: =(C21+$C$10+$C$11-$C$12)/(1+$C$13)/$C$14 -> 9.2662906 | D30: =(D21+$C$10+$C$11-$C$12)/(1+$C$13)/$C$14 -> 8.6754606 | E30: =(E21+$C$10+$C$11-$C$12)/(1+$C$13)/$C$14 -> 8.209325 | G30: 4
B31: Exit at 5.0x LTM EBITDA | C31: =(C22+$C$10+$C$11-$C$12)/(1+$C$13)/$C$14 -> 9.7022674 | D31: =(D22+$C$10+$C$11-$C$12)/(1+$C$13)/$C$14 -> 9.0278691 | E31: =(E22+$C$10+$C$11-$C$12)/(1+$C$13)/$C$14 -> 8.4966693 | G31: 5
B32: Exit at 6.0x LTM EBITDA | C32: =(C23+$C$10+$C$11-$C$12)/(1+$C$13)/$C$14 -> 10.138244 | D32: =(D23+$C$10+$C$11-$C$12)/(1+$C$13)/$C$14 -> 9.3802776 | E32: =(E23+$C$10+$C$11-$C$12)/(1+$C$13)/$C$14 -> 8.7840135 | G32: 6
B33: Exit at 7.0x LTM EBITDA | C33: =(C24+$C$10+$C$11-$C$12)/(1+$C$13)/$C$14 -> 10.574221 | D33: =(D24+$C$10+$C$11-$C$12)/(1+$C$13)/$C$14 -> 9.7326862 | E33: =(E24+$C$10+$C$11-$C$12)/(1+$C$13)/$C$14 -> 9.0713578 | G33: 7
B34: Exit at 8.0x LTM EBITDA | C34: =(C25+$C$10+$C$11-$C$12)/(1+$C$13)/$C$14 -> 11.010198 | D34: =(D25+$C$10+$C$11-$C$12)/(1+$C$13)/$C$14 -> 10.085095 | E34: =(E25+$C$10+$C$11-$C$12)/(1+$C$13)/$C$14 -> 9.3587021 | G34: 8
B35: Exit at 9.0x LTM EBITDA | C35: =(C26+$C$10+$C$11-$C$12)/(1+$C$13)/$C$14 -> 11.446175 | D35: =(D26+$C$10+$C$11-$C$12)/(1+$C$13)/$C$14 -> 10.437503 | E35: =(E26+$C$10+$C$11-$C$12)/(1+$C$13)/$C$14 -> 9.6460464 | G35: 9
B37: Implied premium to undisturbed | C37: 0.15 | D37: 0.2 | E37: 0.25
B38: Exit at 3.0x LTM EBITDA | C38: =C29/$C$15-1 -> 0.071640016 | D38: =D29/$C$15-1 -> 0.01007914 | E38: =E29/$C$15-1 -> -0.038594575 | G38: 3
B39: Exit at 4.0x LTM EBITDA | C39: =C30/$C$15-1 -> 0.12454983 | D39: =D30/$C$15-1 -> 0.052847163 | E39: =E30/$C$15-1 -> -0.0037226966 | G39: 4
B40: Exit at 5.0x LTM EBITDA | C40: =C31/$C$15-1 -> 0.17745964 | D40: =D31/$C$15-1 -> 0.095615187 | E40: =E31/$C$15-1 -> 0.031149182 | G40: 5
B41: Exit at 6.0x LTM EBITDA | C41: =C32/$C$15-1 -> 0.23036945 | D41: =D32/$C$15-1 -> 0.13838321 | E41: =E32/$C$15-1 -> 0.06602106 | G41: 6
B42: Exit at 7.0x LTM EBITDA | C42: =C33/$C$15-1 -> 0.28327926 | D42: =D33/$C$15-1 -> 0.18115123 | E42: =E33/$C$15-1 -> 0.10089294 | G42: 7
B43: Exit at 8.0x LTM EBITDA | C43: =C34/$C$15-1 -> 0.33618907 | D43: =D34/$C$15-1 -> 0.22391926 | E43: =E34/$C$15-1 -> 0.13576482 | G43: 8
B44: Exit at 9.0x LTM EBITDA | C44: =C35/$C$15-1 -> 0.38909888 | D44: =D35/$C$15-1 -> 0.26668728 | E44: =E35/$C$15-1 -> 0.17063669 | G44: 9
B46: Implied TEV / LTM Adj. EBITDA | C46: 0.15 | D46: 0.2 | E46: 0.25
B47: Exit at 3.0x LTM EBITDA | C47: =(C29*$C$14-$C$16)/$C$17 -> 4.7141308 | D47: =(D29*$C$14-$C$16)/$C$17 -> 4.0097421 | E47: =(E29*$C$14-$C$16)/$C$17 -> 3.4528102 | G47: 3
B48: Exit at 4.0x LTM EBITDA | C48: =(C30*$C$14-$C$16)/$C$17 -> 5.3195327 | D48: =(D30*$C$14-$C$16)/$C$17 -> 4.4991002 | E48: =(E30*$C$14-$C$16)/$C$17 -> 3.8518194 | G48: 4
B49: Exit at 5.0x LTM EBITDA | C49: =(C31*$C$14-$C$16)/$C$17 -> 5.9249346 | D49: =(D31*$C$14-$C$16)/$C$17 -> 4.9884582 | E49: =(E31*$C$14-$C$16)/$C$17 -> 4.2508286 | G49: 5
B50: Exit at 6.0x LTM EBITDA | C50: =(C32*$C$14-$C$16)/$C$17 -> 6.5303365 | D50: =(D32*$C$14-$C$16)/$C$17 -> 5.4778163 | E50: =(E32*$C$14-$C$16)/$C$17 -> 4.6498378 | G50: 6
B51: Exit at 7.0x LTM EBITDA | C51: =(C33*$C$14-$C$16)/$C$17 -> 7.1357384 | D51: =(D33*$C$14-$C$16)/$C$17 -> 5.9671744 | E51: =(E33*$C$14-$C$16)/$C$17 -> 5.0488471 | G51: 7
B52: Exit at 8.0x LTM EBITDA | C52: =(C34*$C$14-$C$16)/$C$17 -> 7.7411403 | D52: =(D34*$C$14-$C$16)/$C$17 -> 6.4565324 | E52: =(E34*$C$14-$C$16)/$C$17 -> 5.4478563 | G52: 8
B53: Exit at 9.0x LTM EBITDA | C53: =(C35*$C$14-$C$16)/$C$17 -> 8.3465422 | D53: =(D35*$C$14-$C$16)/$C$17 -> 6.9458905 | E53: =(E35*$C$14-$C$16)/$C$17 -> 5.8468655 | G53: 9
B55: ATP at the running exit multiple & check
B56: Running exit multiple | C56: =LBO!D43 -> 5.5
B57: Max offer price at 15% IRR (A$/sh) | C57: =((NPV(0.15,LBO!I245:L245)+(LBO!M245+($C$56*$C$5*(1-$C$8)-$C$6+$C$7))/(1+0.15)^5)+$C$10+$C$11-$C$12)/(1+$C$13)/$C$14 -> 9.9202558
B58: Max offer price at 20% IRR (A$/sh) | C58: =((NPV(0.2,LBO!I245:L245)+(LBO!M245+($C$56*$C$5*(1-$C$8)-$C$6+$C$7))/(1+0.2)^5)+$C$10+$C$11-$C$12)/(1+$C$13)/$C$14 -> 9.2040734
B59: Max offer price at 25% IRR (A$/sh) | C59: =((NPV(0.25,LBO!I245:L245)+(LBO!M245+($C$56*$C$5*(1-$C$8)-$C$6+$C$7))/(1+0.25)^5)+$C$10+$C$11-$C$12)/(1+$C$13)/$C$14 -> 8.6403414
B60: Check: price implied at the model's own IRR less running offer (should be ~0) | C60: =((NPV(LBO!D256,LBO!I245:L245)+(LBO!M245+($C$56*$C$5*(1-$C$8)-$C$6+$C$7))/(1+LBO!D256)^5)+$C$10+$C$11-$C$12)/(1+$C$13)/$C$14-LBO!D19 -> 0

Sheet Contrib
B2: Value creation bridge - running case (entry at close to Y5 exit)
B3: Decomposes (exit equity + distributions - equity invested). Entry multiple is on status-quo FY27E EBITDA, so the EBITDA bucket includes the sponsor cost-out.
B5: Entry TEV (implied by offer) | C5: =LBO!D29 -> 269.34096 | F5: Reading the bridge: a declining single-product asset should show negative revenue effect and multiple contraction, offset by cost-out (margin effect) and cash generation. If most value comes from cash generation, the deal is a 'cash-box' harvest rather than an operational growth story.
B6: Entry LTM Adj. EBITDA (FY27E) | C6: =LBO!H129 -> 36.496922
B7: Entry multiple | C7: =C5/C6 -> 7.3798268
B8: Entry revenue (FY27E) | C8: =LBO!H113 -> 94.96424
B9: Entry Adj. EBITDA margin | C9: =C6/C8 -> 0.38432279
B10: Exit LTM Adj. EBITDA (FY32E) | C10: =LBO!M129 -> 46.359082
B11: Exit multiple | C11: =LBO!D43 -> 5.5
B12: Exit TEV | C12: =LBO!M240 -> 254.97495
B13: Exit revenue (FY32E) | C13: =LBO!M113 -> 77.279255
B14: Exit Adj. EBITDA margin | C14: =C10/C13 -> 0.59989038
B15: PF net debt at close | C15: =LBO!I102-LBO!I93 -> 35
B16: Net debt at exit | C16: =LBO!M155-LBO!M146 -> -40
B17: Cumulative distributions | C17: =LBO!M246 -> 109.31924
B18: Entry fees (transaction + financing) | C18: =-(LBO!D68+LBO!D69) -> -17.057275
B19: Exit costs | C19: =LBO!M243 -> -3.8246242
B20: Equity invested | C20: =LBO!D80 -> 251.39824
B21: Exit equity value | C21: =LBO!M244 -> 291.15032
B23: Bridge | C23: A$m | D23: % of total
B24: EBITDA growth: revenue effect [(Rev1-Rev0) x margin0 x m0] | C24: =(C13-C8)*C9*C7 -> -50.158786 | D24: =C24/$C$30 -> -0.33647507
B25: EBITDA growth: margin effect [(mgn1-mgn0) x Rev1 x m0] | C25: =(C14-C9)*C13*C7 -> 122.93982 | D25: =C25/$C$30 -> 0.82470462
B26: Multiple expansion / (contraction) [(m1-m0) x EBITDA1] | C26: =(C11-C7)*C10 -> -87.147044 | D26: =C26/$C$30 -> -0.58459963
B27: Deleveraging & cash generation [ND0 - ND1 + distributions] | C27: =C15-C16+C17 -> 184.31924 | D27: =C27/$C$30 -> 1.23645
B28: Entry fees | C28: =C18 -> -17.057275 | D28: =C28/$C$30 -> -0.11442358
B29: Exit costs | C29: =C19 -> -3.8246242 | D29: =C29/$C$30 -> -0.025656337
B30: Total value created | C30: =SUM(C24:C29) -> 149.07133 | D30: =C30/$C$30 -> 1
B31: Check: exit equity + distributions - invested - bridge (should be 0) | C31: =C21+C17-C20-C30 -> 0

Sheet Sensitivity
B2: Sensitivity & case outputs
B3: Block A-B: live formulas (running case; helper cash flows in columns AL-AQ). Block C: self-referencing capture cells - run every MCASE (model/run_cases.py or cycle MCASE in Excel with iteration on). Blocks D-F read the captured values.
AL4: Block A helper: cash flows (t=0..5) per price x multiple | AS4: Block F helper: cash flows per price x op case (base financing)
B5: Block A: IRR - offer price (rows) x exit multiple (columns), running operating & financing case, exit Y5 | AL5: =-($C$7*LBO!$D$23*(1+LBO!$D$39)+LBO!$D$84) -> -160.26926 | AM5: =LBO!I$245 -> 0 | AN5: =LBO!J$245 -> 0.45470337 | AO5: =LBO!K$245 -> 39.187678 | AP5: =LBO!L$245 -> 36.005311 | AQ5: =LBO!M$245+(LBO!$M$238*E$6*(1-LBO!$D$44)-LBO!$M$155+LBO!$M$146) -> 210.66264 | AS5: =-($C$91*LBO!$D$23*(1+LBO!$D$39)+$Y$31) -> -166.01077 | AT5: =$Z$31 -> 0 | AU5: =$AA$31 -> 0 | AV5: =$AB$31 -> 12.284322 | AW5: =$AC$31 -> 15.070769 | AX5: =$AD$31+$R$31 -> 87.552596
C6: Offer (A$/sh) | premium | E6: 3 | F6: 4 | G6: 5 | H6: 6 | I6: 7 | J6: 8 | K6: 9 | AL6: =-($C$7*LBO!$D$23*(1+LBO!$D$39)+LBO!$D$84) -> -160.26926 | AM6: =LBO!I$245 -> 0 | AN6: =LBO!J$245 -> 0.45470337 | AO6: =LBO!K$245 -> 39.187678 | AP6: =LBO!L$245 -> 36.005311 | AQ6: =LBO!M$245+(LBO!$M$238*F$6*(1-LBO!$D$44)-LBO!$M$155+LBO!$M$146) -> 256.32633 | AS6: =-($C$91*LBO!$D$23*(1+LBO!$D$39)+$Y$32) -> -165.62566 | AT6: =$Z$32 -> 0 | AU6: =$AA$32 -> 0 | AV6: =$AB$32 -> 29.309743 | AW6: =$AC$32 -> 26.414201 | AX6: =$AD$32+$R$32 -> 194.29904
C7: 9 | D7: =C7/LBO!$D$18-1 -> 0.09223301 | E7: =IF(-AL5<=0,"n.m.",IFERROR(IRR(AL5:AQ5,0.15),IFERROR(IRR(AL5:AQ5,-0.2),IFERROR(IRR(AL5:AQ5,-0.6),-1)))) -> 0.13566357 | F7: =IF(-AL6<=0,"n.m.",IFERROR(IRR(AL6:AQ6,0.15),IFERROR(IRR(AL6:AQ6,-0.2),IFERROR(IRR(AL6:AQ6,-0.6),-1)))) -> 0.17104952 | G7: =IF(-AL7<=0,"n.m.",IFERROR(IRR(AL7:AQ7,0.15),IFERROR(IRR(AL7:AQ7,-0.2),IFERROR(IRR(AL7:AQ7,-0.6),-1)))) -> 0.2023509 | H7: =IF(-AL8<=0,"n.m.",IFERROR(IRR(AL8:AQ8,0.15),IFERROR(IRR(AL8:AQ8,-0.2),IFERROR(IRR(AL8:AQ8,-0.6),-1)))) -> 0.23050933 | I7: =IF(-AL9<=0,"n.m.",IFERROR(IRR(AL9:AQ9,0.15),IFERROR(IRR(AL9:AQ9,-0.2),IFERROR(IRR(AL9:AQ9,-0.6),-1)))) -> 0.25616485 | J7: =IF(-AL10<=0,"n.m.",IFERROR(IRR(AL10:AQ10,0.15),IFERROR(IRR(AL10:AQ10,-0.2),IFERROR(IRR(AL10:AQ10,-0.6),-1)))) -> 0.27977413 | K7: =IF(-AL11<=0,"n.m.",IFERROR(IRR(AL11:AQ11,0.15),IFERROR(IRR(AL11:AQ11,-0.2),IFERROR(IRR(AL11:AQ11,-0.6),-1)))) -> 0.30167535 | AL7: =-($C$7*LBO!$D$23*(1+LBO!$D$39)+LBO!$D$84) -> -160.26926 | AM7: =LBO!I$245 -> 0 | AN7: =LBO!J$245 -> 0.45470337 | AO7: =LBO!K$245 -> 39.187678 | AP7: =LBO!L$245 -> 36.005311 | AQ7: =LBO!M$245+(LBO!$M$238*G$6*(1-LBO!$D$44)-LBO!$M$155+LBO!$M$146) -> 301.99003 | AS7: =-($C$91*LBO!$D$23*(1+LBO!$D$39)+$Y$33) -> -160.26926 | AT7: =$Z$33 -> 0 | AU7: =$AA$33 -> 0.45470337 | AV7: =$AB$33 -> 39.187678 | AW7: =$AC$33 -> 36.005311 | AX7: =$AD$33+$R$33 -> 324.82188
C8: 9.5 | D8: =C8/LBO!$D$18-1 -> 0.15291262 | E8: =IF(-AL12<=0,"n.m.",IFERROR(IRR(AL12:AQ12,0.15),IFERROR(IRR(AL12:AQ12,-0.2),IFERROR(IRR(AL12:AQ12,-0.6),-1)))) -> 0.098579018 | F8: =IF(-AL13<=0,"n.m.",IFERROR(IRR(AL13:AQ13,0.15),IFERROR(IRR(AL13:AQ13,-0.2),IFERROR(IRR(AL13:AQ13,-0.6),-1)))) -> 0.13317656 | G8: =IF(-AL14<=0,"n.m.",IFERROR(IRR(AL14:AQ14,0.15),IFERROR(IRR(AL14:AQ14,-0.2),IFERROR(IRR(AL14:AQ14,-0.6),-1)))) -> 0.16375492 | H8: =IF(-AL15<=0,"n.m.",IFERROR(IRR(AL15:AQ15,0.15),IFERROR(IRR(AL15:AQ15,-0.2),IFERROR(IRR(AL15:AQ15,-0.6),-1)))) -> 0.1912453 | I8: =IF(-AL16<=0,"n.m.",IFERROR(IRR(AL16:AQ16,0.15),IFERROR(IRR(AL16:AQ16,-0.2),IFERROR(IRR(AL16:AQ16,-0.6),-1)))) -> 0.21627945 | J8: =IF(-AL17<=0,"n.m.",IFERROR(IRR(AL17:AQ17,0.15),IFERROR(IRR(AL17:AQ17,-0.2),IFERROR(IRR(AL17:AQ17,-0.6),-1)))) -> 0.23930735 | K8: =IF(-AL18<=0,"n.m.",IFERROR(IRR(AL18:AQ18,0.15),IFERROR(IRR(AL18:AQ18,-0.2),IFERROR(IRR(AL18:AQ18,-0.6),-1)))) -> 0.2606619 | AL8: =-($C$7*LBO!$D$23*(1+LBO!$D$39)+LBO!$D$84) -> -160.26926 | AM8: =LBO!I$245 -> 0 | AN8: =LBO!J$245 -> 0.45470337 | AO8: =LBO!K$245 -> 39.187678 | AP8: =LBO!L$245 -> 36.005311 | AQ8: =LBO!M$245+(LBO!$M$238*H$6*(1-LBO!$D$44)-LBO!$M$155+LBO!$M$146) -> 347.65372 | AS8: =-($C$91*LBO!$D$23*(1+LBO!$D$39)+$Y$34) -> -159.88415 | AT8: =$Z$34 -> 0 | AU8: =$AA$34 -> 9.3619617 | AV8: =$AB$34 -> 48.806138 | AW8: =$AC$34 -> 49.690811 | AX8: =$AD$34+$R$34 -> 579.07917
C9: 10 | D9: =C9/LBO!$D$18-1 -> 0.21359223 | E9: =IF(-AL19<=0,"n.m.",IFERROR(IRR(AL19:AQ19,0.15),IFERROR(IRR(AL19:AQ19,-0.2),IFERROR(IRR(AL19:AQ19,-0.6),-1)))) -> 0.06745946 | F9: =IF(-AL20<=0,"n.m.",IFERROR(IRR(AL20:AQ20,0.15),IFERROR(IRR(AL20:AQ20,-0.2),IFERROR(IRR(AL20:AQ20,-0.6),-1)))) -> 0.10137617 | G9: =IF(-AL21<=0,"n.m.",IFERROR(IRR(AL21:AQ21,0.15),IFERROR(IRR(AL21:AQ21,-0.2),IFERROR(IRR(AL21:AQ21,-0.6),-1)))) -> 0.13133186 | H9: =IF(-AL22<=0,"n.m.",IFERROR(IRR(AL22:AQ22,0.15),IFERROR(IRR(AL22:AQ22,-0.2),IFERROR(IRR(AL22:AQ22,-0.6),-1)))) -> 0.15824811 | I9: =IF(-AL23<=0,"n.m.",IFERROR(IRR(AL23:AQ23,0.15),IFERROR(IRR(AL23:AQ23,-0.2),IFERROR(IRR(AL23:AQ23,-0.6),-1)))) -> 0.18274907 | J9: =IF(-AL24<=0,"n.m.",IFERROR(IRR(AL24:AQ24,0.15),IFERROR(IRR(AL24:AQ24,-0.2),IFERROR(IRR(AL24:AQ24,-0.6),-1)))) -> 0.20527876 | K9: =IF(-AL25<=0,"n.m.",IFERROR(IRR(AL25:AQ25,0.15),IFERROR(IRR(AL25:AQ25,-0.2),IFERROR(IRR(AL25:AQ25,-0.6),-1)))) -> 0.22616529 | AL9: =-($C$7*LBO!$D$23*(1+LBO!$D$39)+LBO!$D$84) -> -160.26926 | AM9: =LBO!I$245 -> 0 | AN9: =LBO!J$245 -> 0.45470337 | AO9: =LBO!K$245 -> 39.187678 | AP9: =LBO!L$245 -> 36.005311 | AQ9: =LBO!M$245+(LBO!$M$238*I$6*(1-LBO!$D$44)-LBO!$M$155+LBO!$M$146) -> 393.31742 | AS9: =-($C$91*LBO!$D$23*(1+LBO!$D$39)+$Y$35) -> -159.88415 | AT9: =$Z$35 -> 0 | AU9: =$AA$35 -> 0 | AV9: =$AB$35 -> 25.370613 | AW9: =$AC$35 -> 47.650811 | AX9: =$AD$35+$R$35 -> 887.97669
C10: 10.5 | D10: =C10/LBO!$D$18-1 -> 0.27427184 | E10: =IF(-AL26<=0,"n.m.",IFERROR(IRR(AL26:AQ26,0.15),IFERROR(IRR(AL26:AQ26,-0.2),IFERROR(IRR(AL26:AQ26,-0.6),-1)))) -> 0.040766831 | F10: =IF(-AL27<=0,"n.m.",IFERROR(IRR(AL27:AQ27,0.15),IFERROR(IRR(AL27:AQ27,-0.2),IFERROR(IRR(AL27:AQ27,-0.6),-1)))) -> 0.074085445 | G10: =IF(-AL28<=0,"n.m.",IFERROR(IRR(AL28:AQ28,0.15),IFERROR(IRR(AL28:AQ28,-0.2),IFERROR(IRR(AL28:AQ28,-0.6),-1)))) -> 0.1034954 | H10: =IF(-AL29<=0,"n.m.",IFERROR(IRR(AL29:AQ29,0.15),IFERROR(IRR(AL29:AQ29,-0.2),IFERROR(IRR(AL29:AQ29,-0.6),-1)))) -> 0.12990929 | I10: =IF(-AL30<=0,"n.m.",IFERROR(IRR(AL30:AQ30,0.15),IFERROR(IRR(AL30:AQ30,-0.2),IFERROR(IRR(AL30:AQ30,-0.6),-1)))) -> 0.15394433 | J10: =IF(-AL31<=0,"n.m.",IFERROR(IRR(AL31:AQ31,0.15),IFERROR(IRR(AL31:AQ31,-0.2),IFERROR(IRR(AL31:AQ31,-0.6),-1)))) -> 0.17603911 | K10: =IF(-AL32<=0,"n.m.",IFERROR(IRR(AL32:AQ32,0.15),IFERROR(IRR(AL32:AQ32,-0.2),IFERROR(IRR(AL32:AQ32,-0.6),-1)))) -> 0.19651746 | AL10: =-($C$7*LBO!$D$23*(1+LBO!$D$39)+LBO!$D$84) -> -160.26926 | AM10: =LBO!I$245 -> 0 | AN10: =LBO!J$245 -> 0.45470337 | AO10: =LBO!K$245 -> 39.187678 | AP10: =LBO!L$245 -> 36.005311 | AQ10: =LBO!M$245+(LBO!$M$238*J$6*(1-LBO!$D$44)-LBO!$M$155+LBO!$M$146) -> 438.98111 | AS10: =-($C$92*LBO!$D$23*(1+LBO!$D$39)+$Y$31) -> -192.04762 | AT10: =$Z$31 -> 0 | AU10: =$AA$31 -> 0 | AV10: =$AB$31 -> 12.284322 | AW10: =$AC$31 -> 15.070769 | AX10: =$AD$31+$R$31 -> 87.552596
C11: 11 | D11: =C11/LBO!$D$18-1 -> 0.33495146 | E11: =IF(-AL33<=0,"n.m.",IFERROR(IRR(AL33:AQ33,0.15),IFERROR(IRR(AL33:AQ33,-0.2),IFERROR(IRR(AL33:AQ33,-0.6),-1)))) -> 0.017477761 | F11: =IF(-AL34<=0,"n.m.",IFERROR(IRR(AL34:AQ34,0.15),IFERROR(IRR(AL34:AQ34,-0.2),IFERROR(IRR(AL34:AQ34,-0.6),-1)))) -> 0.050263837 | G11: =IF(-AL35<=0,"n.m.",IFERROR(IRR(AL35:AQ35,0.15),IFERROR(IRR(AL35:AQ35,-0.2),IFERROR(IRR(AL35:AQ35,-0.6),-1)))) -> 0.079188802 | H11: =IF(-AL36<=0,"n.m.",IFERROR(IRR(AL36:AQ36,0.15),IFERROR(IRR(AL36:AQ36,-0.2),IFERROR(IRR(AL36:AQ36,-0.6),-1)))) -> 0.1051569 | I11: =IF(-AL37<=0,"n.m.",IFERROR(IRR(AL37:AQ37,0.15),IFERROR(IRR(AL37:AQ37,-0.2),IFERROR(IRR(AL37:AQ37,-0.6),-1)))) -> 0.12877893 | J11: =IF(-AL38<=0,"n.m.",IFERROR(IRR(AL38:AQ38,0.15),IFERROR(IRR(AL38:AQ38,-0.2),IFERROR(IRR(AL38:AQ38,-0.6),-1)))) -> 0.15048854 | K11: =IF(-AL39<=0,"n.m.",IFERROR(IRR(AL39:AQ39,0.15),IFERROR(IRR(AL39:AQ39,-0.2),IFERROR(IRR(AL39:AQ39,-0.6),-1)))) -> 0.17060564 | AL11: =-($C$7*LBO!$D$23*(1+LBO!$D$39)+LBO!$D$84) -> -160.26926 | AM11: =LBO!I$245 -> 0 | AN11: =LBO!J$245 -> 0.45470337 | AO11: =LBO!K$245 -> 39.187678 | AP11: =LBO!L$245 -> 36.005311 | AQ11: =LBO!M$245+(LBO!$M$238*K$6*(1-LBO!$D$44)-LBO!$M$155+LBO!$M$146) -> 484.64481 | AS11: =-($C$92*LBO!$D$23*(1+LBO!$D$39)+$Y$32) -> -191.66251 | AT11: =$Z$32 -> 0 | AU11: =$AA$32 -> 0 | AV11: =$AB$32 -> 29.309743 | AW11: =$AC$32 -> 26.414201 | AX11: =$AD$32+$R$32 -> 194.29904
C12: 11.5 | D12: =C12/LBO!$D$18-1 -> 0.39563107 | E12: =IF(-AL40<=0,"n.m.",IFERROR(IRR(AL40:AQ40,0.15),IFERROR(IRR(AL40:AQ40,-0.2),IFERROR(IRR(AL40:AQ40,-0.6),-1)))) -> -0.003120776 | F12: =IF(-AL41<=0,"n.m.",IFERROR(IRR(AL41:AQ41,0.15),IFERROR(IRR(AL41:AQ41,-0.2),IFERROR(IRR(AL41:AQ41,-0.6),-1)))) -> 0.029185929 | G12: =IF(-AL42<=0,"n.m.",IFERROR(IRR(AL42:AQ42,0.15),IFERROR(IRR(AL42:AQ42,-0.2),IFERROR(IRR(AL42:AQ42,-0.6),-1)))) -> 0.057675048 | H12: =IF(-AL43<=0,"n.m.",IFERROR(IRR(AL43:AQ43,0.15),IFERROR(IRR(AL43:AQ43,-0.2),IFERROR(IRR(AL43:AQ43,-0.6),-1)))) -> 0.083243012 | I12: =IF(-AL44<=0,"n.m.",IFERROR(IRR(AL44:AQ44,0.15),IFERROR(IRR(AL44:AQ44,-0.2),IFERROR(IRR(AL44:AQ44,-0.6),-1)))) -> 0.1064947 | J12: =IF(-AL45<=0,"n.m.",IFERROR(IRR(AL45:AQ45,0.15),IFERROR(IRR(AL45:AQ45,-0.2),IFERROR(IRR(AL45:AQ45,-0.6),-1)))) -> 0.12785918 | K12: =IF(-AL46<=0,"n.m.",IFERROR(IRR(AL46:AQ46,0.15),IFERROR(IRR(AL46:AQ46,-0.2),IFERROR(IRR(AL46:AQ46,-0.6),-1)))) -> 0.14765279 | AL12: =-($C$8*LBO!$D$23*(1+LBO!$D$39)+LBO!$D$84) -> -186.30611 | AM12: =LBO!I$245 -> 0 | AN12: =LBO!J$245 -> 0.45470337 | AO12: =LBO!K$245 -> 39.187678 | AP12: =LBO!L$245 -> 36.005311 | AQ12: =LBO!M$245+(LBO!$M$238*E$6*(1-LBO!$D$44)-LBO!$M$155+LBO!$M$146) -> 210.66264 | AS12: =-($C$92*LBO!$D$23*(1+LBO!$D$39)+$Y$33) -> -186.30611 | AT12: =$Z$33 -> 0 | AU12: =$AA$33 -> 0.45470337 | AV12: =$AB$33 -> 39.187678 | AW12: =$AC$33 -> 36.005311 | AX12: =$AD$33+$R$33 -> 324.82188
C13: 12 | D13: =C13/LBO!$D$18-1 -> 0.45631068 | E13: =IF(-AL47<=0,"n.m.",IFERROR(IRR(AL47:AQ47,0.15),IFERROR(IRR(AL47:AQ47,-0.2),IFERROR(IRR(AL47:AQ47,-0.6),-1)))) -> -0.021544106 | F13: =IF(-AL48<=0,"n.m.",IFERROR(IRR(AL48:AQ48,0.15),IFERROR(IRR(AL48:AQ48,-0.2),IFERROR(IRR(AL48:AQ48,-0.6),-1)))) -> 0.010327178 | G13: =IF(-AL49<=0,"n.m.",IFERROR(IRR(AL49:AQ49,0.15),IFERROR(IRR(AL49:AQ49,-0.2),IFERROR(IRR(AL49:AQ49,-0.6),-1)))) -> 0.038420984 | H13: =IF(-AL50<=0,"n.m.",IFERROR(IRR(AL50:AQ50,0.15),IFERROR(IRR(AL50:AQ50,-0.2),IFERROR(IRR(AL50:AQ50,-0.6),-1)))) -> 0.063626415 | I13: =IF(-AL51<=0,"n.m.",IFERROR(IRR(AL51:AQ51,0.15),IFERROR(IRR(AL51:AQ51,-0.2),IFERROR(IRR(AL51:AQ51,-0.6),-1)))) -> 0.086542833 | J13: =IF(-AL52<=0,"n.m.",IFERROR(IRR(AL52:AQ52,0.15),IFERROR(IRR(AL52:AQ52,-0.2),IFERROR(IRR(AL52:AQ52,-0.6),-1)))) -> 0.10759509 | K13: =IF(-AL53<=0,"n.m.",IFERROR(IRR(AL53:AQ53,0.15),IFERROR(IRR(AL53:AQ53,-0.2),IFERROR(IRR(AL53:AQ53,-0.6),-1)))) -> 0.12709622 | AL13: =-($C$8*LBO!$D$23*(1+LBO!$D$39)+LBO!$D$84) -> -186.30611 | AM13: =LBO!I$245 -> 0 | AN13: =LBO!J$245 -> 0.45470337 | AO13: =LBO!K$245 -> 39.187678 | AP13: =LBO!L$245 -> 36.005311 | AQ13: =LBO!M$245+(LBO!$M$238*F$6*(1-LBO!$D$44)-LBO!$M$155+LBO!$M$146) -> 256.32633 | AS13: =-($C$92*LBO!$D$23*(1+LBO!$D$39)+$Y$34) -> -185.921 | AT13: =$Z$34 -> 0 | AU13: =$AA$34 -> 9.3619617 | AV13: =$AB$34 -> 48.806138 | AW13: =$AC$34 -> 49.690811 | AX13: =$AD$34+$R$34 -> 579.07917
C14: 12.5 | D14: =C14/LBO!$D$18-1 -> 0.51699029 | E14: =IF(-AL54<=0,"n.m.",IFERROR(IRR(AL54:AQ54,0.15),IFERROR(IRR(AL54:AQ54,-0.2),IFERROR(IRR(AL54:AQ54,-0.6),-1)))) -> -0.038175953 | F14: =IF(-AL55<=0,"n.m.",IFERROR(IRR(AL55:AQ55,0.15),IFERROR(IRR(AL55:AQ55,-0.2),IFERROR(IRR(AL55:AQ55,-0.6),-1)))) -> -0.0067031764 | G14: =IF(-AL56<=0,"n.m.",IFERROR(IRR(AL56:AQ56,0.15),IFERROR(IRR(AL56:AQ56,-0.2),IFERROR(IRR(AL56:AQ56,-0.6),-1)))) -> 0.021029291 | H14: =IF(-AL57<=0,"n.m.",IFERROR(IRR(AL57:AQ57,0.15),IFERROR(IRR(AL57:AQ57,-0.2),IFERROR(IRR(AL57:AQ57,-0.6),-1)))) -> 0.045903663 | I14: =IF(-AL58<=0,"n.m.",IFERROR(IRR(AL58:AQ58,0.15),IFERROR(IRR(AL58:AQ58,-0.2),IFERROR(IRR(AL58:AQ58,-0.6),-1)))) -> 0.068514147 | J14: =IF(-AL59<=0,"n.m.",IFERROR(IRR(AL59:AQ59,0.15),IFERROR(IRR(AL59:AQ59,-0.2),IFERROR(IRR(AL59:AQ59,-0.6),-1)))) -> 0.089281662 | K14: =IF(-AL60<=0,"n.m.",IFERROR(IRR(AL60:AQ60,0.15),IFERROR(IRR(AL60:AQ60,-0.2),IFERROR(IRR(AL60:AQ60,-0.6),-1)))) -> 0.10851618 | AL14: =-($C$8*LBO!$D$23*(1+LBO!$D$39)+LBO!$D$84) -> -186.30611 | AM14: =LBO!I$245 -> 0 | AN14: =LBO!J$245 -> 0.45470337 | AO14: =LBO!K$245 -> 39.187678 | AP14: =LBO!L$245 -> 36.005311 | AQ14: =LBO!M$245+(LBO!$M$238*G$6*(1-LBO!$D$44)-LBO!$M$155+LBO!$M$146) -> 301.99003 | AS14: =-($C$92*LBO!$D$23*(1+LBO!$D$39)+$Y$35) -> -185.921 | AT14: =$Z$35 -> 0 | AU14: =$AA$35 -> 0 | AV14: =$AB$35 -> 25.370613 | AW14: =$AC$35 -> 47.650811 | AX14: =$AD$35+$R$35 -> 887.97669
C15: 13 | D15: =C15/LBO!$D$18-1 -> 0.5776699 | E15: =IF(-AL61<=0,"n.m.",IFERROR(IRR(AL61:AQ61,0.15),IFERROR(IRR(AL61:AQ61,-0.2),IFERROR(IRR(AL61:AQ61,-0.6),-1)))) -> -0.053309212 | F15: =IF(-AL62<=0,"n.m.",IFERROR(IRR(AL62:AQ62,0.15),IFERROR(IRR(AL62:AQ62,-0.2),IFERROR(IRR(AL62:AQ62,-0.6),-1)))) -> -0.022203522 | G15: =IF(-AL63<=0,"n.m.",IFERROR(IRR(AL63:AQ63,0.15),IFERROR(IRR(AL63:AQ63,-0.2),IFERROR(IRR(AL63:AQ63,-0.6),-1)))) -> 0.0051964775 | H15: =IF(-AL64<=0,"n.m.",IFERROR(IRR(AL64:AQ64,0.15),IFERROR(IRR(AL64:AQ64,-0.2),IFERROR(IRR(AL64:AQ64,-0.6),-1)))) -> 0.029766499 | I15: =IF(-AL65<=0,"n.m.",IFERROR(IRR(AL65:AQ65,0.15),IFERROR(IRR(AL65:AQ65,-0.2),IFERROR(IRR(AL65:AQ65,-0.6),-1)))) -> 0.052095915 | J15: =IF(-AL66<=0,"n.m.",IFERROR(IRR(AL66:AQ66,0.15),IFERROR(IRR(AL66:AQ66,-0.2),IFERROR(IRR(AL66:AQ66,-0.6),-1)))) -> 0.072601972 | K15: =IF(-AL67<=0,"n.m.",IFERROR(IRR(AL67:AQ67,0.15),IFERROR(IRR(AL67:AQ67,-0.2),IFERROR(IRR(AL67:AQ67,-0.6),-1)))) -> 0.091591789 | AL15: =-($C$8*LBO!$D$23*(1+LBO!$D$39)+LBO!$D$84) -> -186.30611 | AM15: =LBO!I$245 -> 0 | AN15: =LBO!J$245 -> 0.45470337 | AO15: =LBO!K$245 -> 39.187678 | AP15: =LBO!L$245 -> 36.005311 | AQ15: =LBO!M$245+(LBO!$M$238*H$6*(1-LBO!$D$44)-LBO!$M$155+LBO!$M$146) -> 347.65372 | AS15: =-($C$93*LBO!$D$23*(1+LBO!$D$39)+$Y$31) -> -218.08447 | AT15: =$Z$31 -> 0 | AU15: =$AA$31 -> 0 | AV15: =$AB$31 -> 12.284322 | AW15: =$AC$31 -> 15.070769 | AX15: =$AD$31+$R$31 -> 87.552596
AL16: =-($C$8*LBO!$D$23*(1+LBO!$D$39)+LBO!$D$84) -> -186.30611 | AM16: =LBO!I$245 -> 0 | AN16: =LBO!J$245 -> 0.45470337 | AO16: =LBO!K$245 -> 39.187678 | AP16: =LBO!L$245 -> 36.005311 | AQ16: =LBO!M$245+(LBO!$M$238*I$6*(1-LBO!$D$44)-LBO!$M$155+LBO!$M$146) -> 393.31742 | AS16: =-($C$93*LBO!$D$23*(1+LBO!$D$39)+$Y$32) -> -217.69936 | AT16: =$Z$32 -> 0 | AU16: =$AA$32 -> 0 | AV16: =$AB$32 -> 29.309743 | AW16: =$AC$32 -> 26.414201 | AX16: =$AD$32+$R$32 -> 194.29904
B17: Block B: MoIC - offer price x exit multiple (running case, exit Y5) | AL17: =-($C$8*LBO!$D$23*(1+LBO!$D$39)+LBO!$D$84) -> -186.30611 | AM17: =LBO!I$245 -> 0 | AN17: =LBO!J$245 -> 0.45470337 | AO17: =LBO!K$245 -> 39.187678 | AP17: =LBO!L$245 -> 36.005311 | AQ17: =LBO!M$245+(LBO!$M$238*J$6*(1-LBO!$D$44)-LBO!$M$155+LBO!$M$146) -> 438.98111 | AS17: =-($C$93*LBO!$D$23*(1+LBO!$D$39)+$Y$33) -> -212.34296 | AT17: =$Z$33 -> 0 | AU17: =$AA$33 -> 0.45470337 | AV17: =$AB$33 -> 39.187678 | AW17: =$AC$33 -> 36.005311 | AX17: =$AD$33+$R$33 -> 324.82188
E18: 3 | F18: 4 | G18: 5 | H18: 6 | I18: 7 | J18: 8 | K18: 9 | AL18: =-($C$8*LBO!$D$23*(1+LBO!$D$39)+LBO!$D$84) -> -186.30611 | AM18: =LBO!I$245 -> 0 | AN18: =LBO!J$245 -> 0.45470337 | AO18: =LBO!K$245 -> 39.187678 | AP18: =LBO!L$245 -> 36.005311 | AQ18: =LBO!M$245+(LBO!$M$238*K$6*(1-LBO!$D$44)-LBO!$M$155+LBO!$M$146) -> 484.64481 | AS18: =-($C$93*LBO!$D$23*(1+LBO!$D$39)+$Y$34) -> -211.95785 | AT18: =$Z$34 -> 0 | AU18: =$AA$34 -> 9.3619617 | AV18: =$AB$34 -> 48.806138 | AW18: =$AC$34 -> 49.690811 | AX18: =$AD$34+$R$34 -> 579.07917
C19: 9 | D19: =C19/LBO!$D$18-1 -> 0.09223301 | E19: =IF(-AL5<=0,"n.m.",(SUM(AM5:AQ5))/(-AL5)) -> 1.7864332 | F19: =IF(-AL6<=0,"n.m.",(SUM(AM6:AQ6))/(-AL6)) -> 2.0713518 | G19: =IF(-AL7<=0,"n.m.",(SUM(AM7:AQ7))/(-AL7)) -> 2.3562704 | H19: =IF(-AL8<=0,"n.m.",(SUM(AM8:AQ8))/(-AL8)) -> 2.641189 | I19: =IF(-AL9<=0,"n.m.",(SUM(AM9:AQ9))/(-AL9)) -> 2.9261076 | J19: =IF(-AL10<=0,"n.m.",(SUM(AM10:AQ10))/(-AL10)) -> 3.2110262 | K19: =IF(-AL11<=0,"n.m.",(SUM(AM11:AQ11))/(-AL11)) -> 3.4959448 | AL19: =-($C$9*LBO!$D$23*(1+LBO!$D$39)+LBO!$D$84) -> -212.34296 | AM19: =LBO!I$245 -> 0 | AN19: =LBO!J$245 -> 0.45470337 | AO19: =LBO!K$245 -> 39.187678 | AP19: =LBO!L$245 -> 36.005311 | AQ19: =LBO!M$245+(LBO!$M$238*E$6*(1-LBO!$D$44)-LBO!$M$155+LBO!$M$146) -> 210.66264 | AS19: =-($C$93*LBO!$D$23*(1+LBO!$D$39)+$Y$35) -> -211.95785 | AT19: =$Z$35 -> 0 | AU19: =$AA$35 -> 0 | AV19: =$AB$35 -> 25.370613 | AW19: =$AC$35 -> 47.650811 | AX19: =$AD$35+$R$35 -> 887.97669
C20: 9.5 | D20: =C20/LBO!$D$18-1 -> 0.15291262 | E20: =IF(-AL12<=0,"n.m.",(SUM(AM12:AQ12))/(-AL12)) -> 1.5367737 | F20: =IF(-AL13<=0,"n.m.",(SUM(AM13:AQ13))/(-AL13)) -> 1.781874 | G20: =IF(-AL14<=0,"n.m.",(SUM(AM14:AQ14))/(-AL14)) -> 2.0269744 | H20: =IF(-AL15<=0,"n.m.",(SUM(AM15:AQ15))/(-AL15)) -> 2.2720748 | I20: =IF(-AL16<=0,"n.m.",(SUM(AM16:AQ16))/(-AL16)) -> 2.5171751 | J20: =IF(-AL17<=0,"n.m.",(SUM(AM17:AQ17))/(-AL17)) -> 2.7622755 | K20: =IF(-AL18<=0,"n.m.",(SUM(AM18:AQ18))/(-AL18)) -> 3.0073758 | AL20: =-($C$9*LBO!$D$23*(1+LBO!$D$39)+LBO!$D$84) -> -212.34296 | AM20: =LBO!I$245 -> 0 | AN20: =LBO!J$245 -> 0.45470337 | AO20: =LBO!K$245 -> 39.187678 | AP20: =LBO!L$245 -> 36.005311 | AQ20: =LBO!M$245+(LBO!$M$238*F$6*(1-LBO!$D$44)-LBO!$M$155+LBO!$M$146) -> 256.32633 | AS20: =-($C$94*LBO!$D$23*(1+LBO!$D$39)+$Y$31) -> -244.12132 | AT20: =$Z$31 -> 0 | AU20: =$AA$31 -> 0 | AV20: =$AB$31 -> 12.284322 | AW20: =$AC$31 -> 15.070769 | AX20: =$AD$31+$R$31 -> 87.552596
C21: 10 | D21: =C21/LBO!$D$18-1 -> 0.21359223 | E21: =IF(-AL19<=0,"n.m.",(SUM(AM19:AQ19))/(-AL19)) -> 1.3483391 | F21: =IF(-AL20<=0,"n.m.",(SUM(AM20:AQ20))/(-AL20)) -> 1.563386 | G21: =IF(-AL21<=0,"n.m.",(SUM(AM21:AQ21))/(-AL21)) -> 1.7784329 | H21: =IF(-AL22<=0,"n.m.",(SUM(AM22:AQ22))/(-AL22)) -> 1.9934798 | I21: =IF(-AL23<=0,"n.m.",(SUM(AM23:AQ23))/(-AL23)) -> 2.2085267 | J21: =IF(-AL24<=0,"n.m.",(SUM(AM24:AQ24))/(-AL24)) -> 2.4235736 | K21: =IF(-AL25<=0,"n.m.",(SUM(AM25:AQ25))/(-AL25)) -> 2.6386205 | AL21: =-($C$9*LBO!$D$23*(1+LBO!$D$39)+LBO!$D$84) -> -212.34296 | AM21: =LBO!I$245 -> 0 | AN21: =LBO!J$245 -> 0.45470337 | AO21: =LBO!K$245 -> 39.187678 | AP21: =LBO!L$245 -> 36.005311 | AQ21: =LBO!M$245+(LBO!$M$238*G$6*(1-LBO!$D$44)-LBO!$M$155+LBO!$M$146) -> 301.99003 | AS21: =-($C$94*LBO!$D$23*(1+LBO!$D$39)+$Y$32) -> -243.73621 | AT21: =$Z$32 -> 0 | AU21: =$AA$32 -> 0 | AV21: =$AB$32 -> 29.309743 | AW21: =$AC$32 -> 26.414201 | AX21: =$AD$32+$R$32 -> 194.29904
C22: 10.5 | D22: =C22/LBO!$D$18-1 -> 0.27427184 | E22: =IF(-AL26<=0,"n.m.",(SUM(AM26:AQ26))/(-AL26)) -> 1.2010679 | F22: =IF(-AL27<=0,"n.m.",(SUM(AM27:AQ27))/(-AL27)) -> 1.3926264 | G22: =IF(-AL28<=0,"n.m.",(SUM(AM28:AQ28))/(-AL28)) -> 1.584185 | H22: =IF(-AL29<=0,"n.m.",(SUM(AM29:AQ29))/(-AL29)) -> 1.7757436 | I22: =IF(-AL30<=0,"n.m.",(SUM(AM30:AQ30))/(-AL30)) -> 1.9673021 | J22: =IF(-AL31<=0,"n.m.",(SUM(AM31:AQ31))/(-AL31)) -> 2.1588607 | K22: =IF(-AL32<=0,"n.m.",(SUM(AM32:AQ32))/(-AL32)) -> 2.3504193 | AL22: =-($C$9*LBO!$D$23*(1+LBO!$D$39)+LBO!$D$84) -> -212.34296 | AM22: =LBO!I$245 -> 0 | AN22: =LBO!J$245 -> 0.45470337 | AO22: =LBO!K$245 -> 39.187678 | AP22: =LBO!L$245 -> 36.005311 | AQ22: =LBO!M$245+(LBO!$M$238*H$6*(1-LBO!$D$44)-LBO!$M$155+LBO!$M$146) -> 347.65372 | AS22: =-($C$94*LBO!$D$23*(1+LBO!$D$39)+$Y$33) -> -238.37981 | AT22: =$Z$33 -> 0 | AU22: =$AA$33 -> 0.45470337 | AV22: =$AB$33 -> 39.187678 | AW22: =$AC$33 -> 36.005311 | AX22: =$AD$33+$R$33 -> 324.82188
C23: 11 | D23: =C23/LBO!$D$18-1 -> 0.33495146 | E23: =IF(-AL33<=0,"n.m.",(SUM(AM33:AQ33))/(-AL33)) -> 1.0827999 | F23: =IF(-AL34<=0,"n.m.",(SUM(AM34:AQ34))/(-AL34)) -> 1.2554959 | G23: =IF(-AL35<=0,"n.m.",(SUM(AM35:AQ35))/(-AL35)) -> 1.4281918 | H23: =IF(-AL36<=0,"n.m.",(SUM(AM36:AQ36))/(-AL36)) -> 1.6008878 | I23: =IF(-AL37<=0,"n.m.",(SUM(AM37:AQ37))/(-AL37)) -> 1.7735838 | J23: =IF(-AL38<=0,"n.m.",(SUM(AM38:AQ38))/(-AL38)) -> 1.9462798 | K23: =IF(-AL39<=0,"n.m.",(SUM(AM39:AQ39))/(-AL39)) -> 2.1189758 | AL23: =-($C$9*LBO!$D$23*(1+LBO!$D$39)+LBO!$D$84) -> -212.34296 | AM23: =LBO!I$245 -> 0 | AN23: =LBO!J$245 -> 0.45470337 | AO23: =LBO!K$245 -> 39.187678 | AP23: =LBO!L$245 -> 36.005311 | AQ23: =LBO!M$245+(LBO!$M$238*I$6*(1-LBO!$D$44)-LBO!$M$155+LBO!$M$146) -> 393.31742 | AS23: =-($C$94*LBO!$D$23*(1+LBO!$D$39)+$Y$34) -> -237.9947 | AT23: =$Z$34 -> 0 | AU23: =$AA$34 -> 9.3619617 | AV23: =$AB$34 -> 48.806138 | AW23: =$AC$34 -> 49.690811 | AX23: =$AD$34+$R$34 -> 579.07917
C24: 11.5 | D24: =C24/LBO!$D$18-1 -> 0.39563107 | E24: =IF(-AL40<=0,"n.m.",(SUM(AM40:AQ40))/(-AL40)) -> 0.98573547 | F24: =IF(-AL41<=0,"n.m.",(SUM(AM41:AQ41))/(-AL41)) -> 1.1429506 | G24: =IF(-AL42<=0,"n.m.",(SUM(AM42:AQ42))/(-AL42)) -> 1.3001658 | H24: =IF(-AL43<=0,"n.m.",(SUM(AM43:AQ43))/(-AL43)) -> 1.4573809 | I24: =IF(-AL44<=0,"n.m.",(SUM(AM44:AQ44))/(-AL44)) -> 1.6145961 | J24: =IF(-AL45<=0,"n.m.",(SUM(AM45:AQ45))/(-AL45)) -> 1.7718113 | K24: =IF(-AL46<=0,"n.m.",(SUM(AM46:AQ46))/(-AL46)) -> 1.9290264 | AL24: =-($C$9*LBO!$D$23*(1+LBO!$D$39)+LBO!$D$84) -> -212.34296 | AM24: =LBO!I$245 -> 0 | AN24: =LBO!J$245 -> 0.45470337 | AO24: =LBO!K$245 -> 39.187678 | AP24: =LBO!L$245 -> 36.005311 | AQ24: =LBO!M$245+(LBO!$M$238*J$6*(1-LBO!$D$44)-LBO!$M$155+LBO!$M$146) -> 438.98111 | AS24: =-($C$94*LBO!$D$23*(1+LBO!$D$39)+$Y$35) -> -237.9947 | AT24: =$Z$35 -> 0 | AU24: =$AA$35 -> 0 | AV24: =$AB$35 -> 25.370613 | AW24: =$AC$35 -> 47.650811 | AX24: =$AD$35+$R$35 -> 887.97669
C25: 12 | D25: =C25/LBO!$D$18-1 -> 0.45631068 | E25: =IF(-AL47<=0,"n.m.",(SUM(AM47:AQ47))/(-AL47)) -> 0.90464154 | F25: =IF(-AL48<=0,"n.m.",(SUM(AM48:AQ48))/(-AL48)) -> 1.048923 | G25: =IF(-AL49<=0,"n.m.",(SUM(AM49:AQ49))/(-AL49)) -> 1.1932045 | H25: =IF(-AL50<=0,"n.m.",(SUM(AM50:AQ50))/(-AL50)) -> 1.337486 | I25: =IF(-AL51<=0,"n.m.",(SUM(AM51:AQ51))/(-AL51)) -> 1.4817674 | J25: =IF(-AL52<=0,"n.m.",(SUM(AM52:AQ52))/(-AL52)) -> 1.6260489 | K25: =IF(-AL53<=0,"n.m.",(SUM(AM53:AQ53))/(-AL53)) -> 1.7703304 | AL25: =-($C$9*LBO!$D$23*(1+LBO!$D$39)+LBO!$D$84) -> -212.34296 | AM25: =LBO!I$245 -> 0 | AN25: =LBO!J$245 -> 0.45470337 | AO25: =LBO!K$245 -> 39.187678 | AP25: =LBO!L$245 -> 36.005311 | AQ25: =LBO!M$245+(LBO!$M$238*K$6*(1-LBO!$D$44)-LBO!$M$155+LBO!$M$146) -> 484.64481 | AS25: =-($C$95*LBO!$D$23*(1+LBO!$D$39)+$Y$31) -> -270.15817 | AT25: =$Z$31 -> 0 | AU25: =$AA$31 -> 0 | AV25: =$AB$31 -> 12.284322 | AW25: =$AC$31 -> 15.070769 | AX25: =$AD$31+$R$31 -> 87.552596
C26: 12.5 | D26: =C26/LBO!$D$18-1 -> 0.51699029 | E26: =IF(-AL54<=0,"n.m.",(SUM(AM54:AQ54))/(-AL54)) -> 0.83587615 | F26: =IF(-AL55<=0,"n.m.",(SUM(AM55:AQ55))/(-AL55)) -> 0.96919022 | G26: =IF(-AL56<=0,"n.m.",(SUM(AM56:AQ56))/(-AL56)) -> 1.1025043 | H26: =IF(-AL57<=0,"n.m.",(SUM(AM57:AQ57))/(-AL57)) -> 1.2358184 | I26: =IF(-AL58<=0,"n.m.",(SUM(AM58:AQ58))/(-AL58)) -> 1.3691324 | J26: =IF(-AL59<=0,"n.m.",(SUM(AM59:AQ59))/(-AL59)) -> 1.5024465 | K26: =IF(-AL60<=0,"n.m.",(SUM(AM60:AQ60))/(-AL60)) -> 1.6357605 | AL26: =-($C$10*LBO!$D$23*(1+LBO!$D$39)+LBO!$D$84) -> -238.37981 | AM26: =LBO!I$245 -> 0 | AN26: =LBO!J$245 -> 0.45470337 | AO26: =LBO!K$245 -> 39.187678 | AP26: =LBO!L$245 -> 36.005311 | AQ26: =LBO!M$245+(LBO!$M$238*E$6*(1-LBO!$D$44)-LBO!$M$155+LBO!$M$146) -> 210.66264 | AS26: =-($C$95*LBO!$D$23*(1+LBO!$D$39)+$Y$32) -> -269.77306 | AT26: =$Z$32 -> 0 | AU26: =$AA$32 -> 0 | AV26: =$AB$32 -> 29.309743 | AW26: =$AC$32 -> 26.414201 | AX26: =$AD$32+$R$32 -> 194.29904
C27: 13 | D27: =C27/LBO!$D$18-1 -> 0.5776699 | E27: =IF(-AL61<=0,"n.m.",(SUM(AM61:AQ61))/(-AL61)) -> 0.7768265 | F27: =IF(-AL62<=0,"n.m.",(SUM(AM62:AQ62))/(-AL62)) -> 0.90072272 | G27: =IF(-AL63<=0,"n.m.",(SUM(AM63:AQ63))/(-AL63)) -> 1.0246189 | H27: =IF(-AL64<=0,"n.m.",(SUM(AM64:AQ64))/(-AL64)) -> 1.1485152 | I27: =IF(-AL65<=0,"n.m.",(SUM(AM65:AQ65))/(-AL65)) -> 1.2724114 | J27: =IF(-AL66<=0,"n.m.",(SUM(AM66:AQ66))/(-AL66)) -> 1.3963076 | K27: =IF(-AL67<=0,"n.m.",(SUM(AM67:AQ67))/(-AL67)) -> 1.5202038 | AL27: =-($C$10*LBO!$D$23*(1+LBO!$D$39)+LBO!$D$84) -> -238.37981 | AM27: =LBO!I$245 -> 0 | AN27: =LBO!J$245 -> 0.45470337 | AO27: =LBO!K$245 -> 39.187678 | AP27: =LBO!L$245 -> 36.005311 | AQ27: =LBO!M$245+(LBO!$M$238*F$6*(1-LBO!$D$44)-LBO!$M$155+LBO!$M$146) -> 256.32633 | AS27: =-($C$95*LBO!$D$23*(1+LBO!$D$39)+$Y$33) -> -264.41666 | AT27: =$Z$33 -> 0 | AU27: =$AA$33 -> 0.45470337 | AV27: =$AB$33 -> 39.187678 | AW27: =$AC$33 -> 36.005311 | AX27: =$AD$33+$R$33 -> 324.82188
AL28: =-($C$10*LBO!$D$23*(1+LBO!$D$39)+LBO!$D$84) -> -238.37981 | AM28: =LBO!I$245 -> 0 | AN28: =LBO!J$245 -> 0.45470337 | AO28: =LBO!K$245 -> 39.187678 | AP28: =LBO!L$245 -> 36.005311 | AQ28: =LBO!M$245+(LBO!$M$238*G$6*(1-LBO!$D$44)-LBO!$M$155+LBO!$M$146) -> 301.99003 | AS28: =-($C$95*LBO!$D$23*(1+LBO!$D$39)+$Y$34) -> -264.03155 | AT28: =$Z$34 -> 0 | AU28: =$AA$34 -> 9.3619617 | AV28: =$AB$34 -> 48.806138 | AW28: =$AC$34 -> 49.690811 | AX28: =$AD$34+$R$34 -> 579.07917
B29: Block C: case capture table (self-referencing IF: each row snapshots the model when MCASE = its case #) | AL29: =-($C$10*LBO!$D$23*(1+LBO!$D$39)+LBO!$D$84) -> -238.37981 | AM29: =LBO!I$245 -> 0 | AN29: =LBO!J$245 -> 0.45470337 | AO29: =LBO!K$245 -> 39.187678 | AP29: =LBO!L$245 -> 36.005311 | AQ29: =LBO!M$245+(LBO!$M$238*H$6*(1-LBO!$D$44)-LBO!$M$155+LBO!$M$146) -> 347.65372 | AS29: =-($C$95*LBO!$D$23*(1+LBO!$D$39)+$Y$35) -> -264.03155 | AT29: =$Z$35 -> 0 | AU29: =$AA$35 -> 0 | AV29: =$AB$35 -> 25.370613 | AW29: =$AC$35 -> 47.650811 | AX29: =$AD$35+$R$35 -> 887.97669
B30: Case | C30: Label | D30: Offer A$/sh | E30: Premium | F30: TEV / LTM EBITDA | G30: TEV / FY28E EBITDA | H30: Equity invested | I30: Equity % (eq+new debt) | J30: New debt | K30: FY28E revenue | L30: FY29E SCENESSE revenue | M30: FY32E revenue | N30: FY27E Adj. EBITDA | O30: FY28E Adj. EBITDA | P30: FY32E Adj. EBITDA | Q30: Cum. distributions | R30: Exit equity (Y5) | S30: MoIC (Y5) | T30: IRR (Y5) | U30: Peak net lev. | V30: Min EBITDA/interest | W30: ATP @20% (A$/sh) | X30: ATP @25% (A$/sh) | Y30: Non-price inv. component | Z30: Dist Y1 | AA30: Dist Y2 | AB30: Dist Y3 | AC30: Dist Y4 | AD30: Dist Y5 | AL30: =-($C$10*LBO!$D$23*(1+LBO!$D$39)+LBO!$D$84) -> -238.37981 | AM30: =LBO!I$245 -> 0 | AN30: =LBO!J$245 -> 0.45470337 | AO30: =LBO!K$245 -> 39.187678 | AP30: =LBO!L$245 -> 36.005311 | AQ30: =LBO!M$245+(LBO!$M$238*I$6*(1-LBO!$D$44)-LBO!$M$155+LBO!$M$146) -> 393.31742 | AS30: =-($C$96*LBO!$D$23*(1+LBO!$D$39)+$Y$31) -> -296.19502 | AT30: =$Z$31 -> 0 | AU30: =$AA$31 -> 0 | AV30: =$AB$31 -> 12.284322 | AW30: =$AC$31 -> 15.070769 | AX30: =$AD$31+$R$31 -> 87.552596
B31: 1 | C31: =MCASE!C9 -> Downside | Base | D31: =IF(MCASE=$B31,LBO!$D$19,D31) -> 10.75 | E31: =IF(MCASE=$B31,LBO!$D$20,E31) -> 0.30461165 | F31: =IF(MCASE=$B31,LBO!$D$33,F31) -> 7.7353699 | G31: =IF(MCASE=$B31,LBO!$D$35,G31) -> 5.5525298 | H31: =IF(MCASE=$B31,LBO!$D$80,H31) -> 257.13975 | I31: =IF(MCASE=$B31,LBO!$D$81,I31) -> 0.78602417 | J31: =IF(MCASE=$B31,LBO!$D$74+LBO!$D$75,J31) -> 70 | K31: =IF(MCASE=$B31,LBO!$I$113,K31) -> 82.334936 | L31: =IF(MCASE=$B31,LBO!$J$109+LBO!$J$110,L31) -> 71.471027 | M31: =IF(MCASE=$B31,LBO!$M$113,M31) -> 40.316172 | N31: =IF(MCASE=$B31,LBO!$H$129,N31) -> 34.931422 | O31: =IF(MCASE=$B31,LBO!$I$129,O31) -> 48.663849 | P31: =IF(MCASE=$B31,LBO!$M$129,P31) -> 11.160326 | Q31: =IF(MCASE=$B31,LBO!$M$246,Q31) -> 36.432464 | R31: =IF(MCASE=$B31,LBO!$M$244,R31) -> 78.475222 | S31: =IF(MCASE=$B31,LBO!$D$255,S31) -> 0.44686863 | T31: =IF(MCASE=$B31,LBO!$D$256,T31) -> -0.15779358 | U31: =IF(MCASE=$B31,LBO!$D$231,U31) -> -0.00021009496 | V31: =IF(MCASE=$B31,LBO!$D$232,V31) -> 8.7532634 | W31: =IF(MCASE=$B31,ATP!$C$58,W31) -> 6.7637763 | X31: =IF(MCASE=$B31,ATP!$C$59,X31) -> 6.6022641 | Y31: =IF(MCASE=$B31,LBO!$D$84,Y31) -> -302.65253 | Z31: =IF(MCASE=$B31,LBO!$I$245,Z31) -> 0 | AA31: =IF(MCASE=$B31,LBO!$J$245,AA31) -> 0 | AB31: =IF(MCASE=$B31,LBO!$K$245,AB31) -> 12.284322 | AC31: =IF(MCASE=$B31,LBO!$L$245,AC31) -> 15.070769 | AD31: =IF(MCASE=$B31,LBO!$M$245,AD31) -> 9.0773734 | AL31: =-($C$10*LBO!$D$23*(1+LBO!$D$39)+LBO!$D$84) -> -238.37981 | AM31: =LBO!I$245 -> 0 | AN31: =LBO!J$245 -> 0.45470337 | AO31: =LBO!K$245 -> 39.187678 | AP31: =LBO!L$245 -> 36.005311 | AQ31: =LBO!M$245+(LBO!$M$238*J$6*(1-LBO!$D$44)-LBO!$M$155+LBO!$M$146) -> 438.98111 | AS31: =-($C$96*LBO!$D$23*(1+LBO!$D$39)+$Y$32) -> -295.80991 | AT31: =$Z$32 -> 0 | AU31: =$AA$32 -> 0 | AV31: =$AB$32 -> 29.309743 | AW31: =$AC$32 -> 26.414201 | AX31: =$AD$32+$R$32 -> 194.29904
B32: 2 | C32: =MCASE!C10 -> Conservative | Base | D32: =IF(MCASE=$B32,LBO!$D$19,D32) -> 10.75 | E32: =IF(MCASE=$B32,LBO!$D$20,E32) -> 0.30461165 | F32: =IF(MCASE=$B32,LBO!$D$33,F32) -> 7.5734932 | G32: =IF(MCASE=$B32,LBO!$D$35,G32) -> 5.0791739 | H32: =IF(MCASE=$B32,LBO!$D$80,H32) -> 256.75463 | I32: =IF(MCASE=$B32,LBO!$D$81,I32) -> 0.78577197 | J32: =IF(MCASE=$B32,LBO!$D$74+LBO!$D$75,J32) -> 70 | K32: =IF(MCASE=$B32,LBO!$I$113,K32) -> 86.945873 | L32: =IF(MCASE=$B32,LBO!$J$109+LBO!$J$110,L32) -> 80.317181 | M32: =IF(MCASE=$B32,LBO!$M$113,M32) -> 60.029819 | N32: =IF(MCASE=$B32,LBO!$H$129,N32) -> 35.6272 | O32: =IF(MCASE=$B32,LBO!$I$129,O32) -> 53.123276 | P32: =IF(MCASE=$B32,LBO!$M$129,P32) -> 29.803055 | Q32: =IF(MCASE=$B32,LBO!$M$246,Q32) -> 77.920941 | R32: =IF(MCASE=$B32,LBO!$M$244,R32) -> 172.10204 | S32: =IF(MCASE=$B32,LBO!$D$255,S32) -> 0.97378178 | T32: =IF(MCASE=$B32,LBO!$D$256,T32) -> -0.0056836136 | U32: =IF(MCASE=$B32,LBO!$D$231,U32) -> -0.050758315 | V32: =IF(MCASE=$B32,LBO!$D$232,V32) -> 9.7822642 | W32: =IF(MCASE=$B32,ATP!$C$58,W32) -> 7.8892427 | X32: =IF(MCASE=$B32,ATP!$C$59,X32) -> 7.5379971 | Y32: =IF(MCASE=$B32,LBO!$D$84,Y32) -> -303.03764 | Z32: =IF(MCASE=$B32,LBO!$I$245,Z32) -> 0 | AA32: =IF(MCASE=$B32,LBO!$J$245,AA32) -> 0 | AB32: =IF(MCASE=$B32,LBO!$K$245,AB32) -> 29.309743 | AC32: =IF(MCASE=$B32,LBO!$L$245,AC32) -> 26.414201 | AD32: =IF(MCASE=$B32,LBO!$M$245,AD32) -> 22.196997 | AL32: =-($C$10*LBO!$D$23*(1+LBO!$D$39)+LBO!$D$84) -> -238.37981 | AM32: =LBO!I$245 -> 0 | AN32: =LBO!J$245 -> 0.45470337 | AO32: =LBO!K$245 -> 39.187678 | AP32: =LBO!L$245 -> 36.005311 | AQ32: =LBO!M$245+(LBO!$M$238*K$6*(1-LBO!$D$44)-LBO!$M$155+LBO!$M$146) -> 484.64481 | AS32: =-($C$96*LBO!$D$23*(1+LBO!$D$39)+$Y$33) -> -290.45351 | AT32: =$Z$33 -> 0 | AU32: =$AA$33 -> 0.45470337 | AV32: =$AB$33 -> 39.187678 | AW32: =$AC$33 -> 36.005311 | AX32: =$AD$33+$R$33 -> 324.82188
B33: 3 | C33: =MCASE!C11 -> Sponsor base | Base | D33: =IF(MCASE=$B33,LBO!$D$19,D33) -> 10.75 | E33: =IF(MCASE=$B33,LBO!$D$20,E33) -> 0.30461165 | F33: =IF(MCASE=$B33,LBO!$D$33,F33) -> 7.3798268 | G33: =IF(MCASE=$B33,LBO!$D$35,G33) -> 4.6841556 | H33: =IF(MCASE=$B33,LBO!$D$80,H33) -> 251.39824 | I33: =IF(MCASE=$B33,LBO!$D$81,I33) -> 0.77021935 | J33: =IF(MCASE=$B33,LBO!$D$74+LBO!$D$75,J33) -> 75 | K33: =IF(MCASE=$B33,LBO!$I$113,K33) -> 90.902403 | L33: =IF(MCASE=$B33,LBO!$J$109+LBO!$J$110,L33) -> 87.739812 | M33: =IF(MCASE=$B33,LBO!$M$113,M33) -> 77.279255 | N33: =IF(MCASE=$B33,LBO!$H$129,N33) -> 36.496922 | O33: =IF(MCASE=$B33,LBO!$I$129,O33) -> 57.50043 | P33: =IF(MCASE=$B33,LBO!$M$129,P33) -> 46.359082 | Q33: =IF(MCASE=$B33,LBO!$M$246,Q33) -> 109.31924 | R33: =IF(MCASE=$B33,LBO!$M$244,R33) -> 291.15032 | S33: =IF(MCASE=$B33,LBO!$D$255,S33) -> 1.5929689 | T33: =IF(MCASE=$B33,LBO!$D$256,T33) -> 0.10437355 | U33: =IF(MCASE=$B33,LBO!$D$231,U33) -> -0.0019167295 | V33: =IF(MCASE=$B33,LBO!$D$232,V33) -> 9.9229181 | W33: =IF(MCASE=$B33,ATP!$C$58,W33) -> 9.2040734 | X33: =IF(MCASE=$B33,ATP!$C$59,X33) -> 8.6403414 | Y33: =IF(MCASE=$B33,LBO!$D$84,Y33) -> -308.39404 | Z33: =IF(MCASE=$B33,LBO!$I$245,Z33) -> 0 | AA33: =IF(MCASE=$B33,LBO!$J$245,AA33) -> 0.45470337 | AB33: =IF(MCASE=$B33,LBO!$K$245,AB33) -> 39.187678 | AC33: =IF(MCASE=$B33,LBO!$L$245,AC33) -> 36.005311 | AD33: =IF(MCASE=$B33,LBO!$M$245,AD33) -> 33.671552 | AL33: =-($C$11*LBO!$D$23*(1+LBO!$D$39)+LBO!$D$84) -> -264.41666 | AM33: =LBO!I$245 -> 0 | AN33: =LBO!J$245 -> 0.45470337 | AO33: =LBO!K$245 -> 39.187678 | AP33: =LBO!L$245 -> 36.005311 | AQ33: =LBO!M$245+(LBO!$M$238*E$6*(1-LBO!$D$44)-LBO!$M$155+LBO!$M$146) -> 210.66264 | AS33: =-($C$96*LBO!$D$23*(1+LBO!$D$39)+$Y$34) -> -290.0684 | AT33: =$Z$34 -> 0 | AU33: =$AA$34 -> 9.3619617 | AV33: =$AB$34 -> 48.806138 | AW33: =$AC$34 -> 49.690811 | AX33: =$AD$34+$R$34 -> 579.07917
B34: 4 | C34: =MCASE!C12 -> Orals underwhelm | Base | D34: =IF(MCASE=$B34,LBO!$D$19,D34) -> 10.75 | E34: =IF(MCASE=$B34,LBO!$D$20,E34) -> 0.30461165 | F34: =IF(MCASE=$B34,LBO!$D$33,F34) -> 7.2314151 | G34: =IF(MCASE=$B34,LBO!$D$35,G34) -> 4.3028963 | H34: =IF(MCASE=$B34,LBO!$D$80,H34) -> 251.01312 | I34: =IF(MCASE=$B34,LBO!$D$81,I34) -> 0.76994791 | J34: =IF(MCASE=$B34,LBO!$D$74+LBO!$D$75,J34) -> 75 | K34: =IF(MCASE=$B34,LBO!$I$113,K34) -> 96.854122 | L34: =IF(MCASE=$B34,LBO!$J$109+LBO!$J$110,L34) -> 98.30228 | M34: =IF(MCASE=$B34,LBO!$M$113,M34) -> 104.29263 | N34: =IF(MCASE=$B34,LBO!$H$129,N34) -> 37.1927 | O34: =IF(MCASE=$B34,LBO!$I$129,O34) -> 62.505771 | P34: =IF(MCASE=$B34,LBO!$M$129,P34) -> 70.846456 | Q34: =IF(MCASE=$B34,LBO!$M$246,Q34) -> 158.45177 | R34: =IF(MCASE=$B34,LBO!$M$244,R34) -> 528.48631 | S34: =IF(MCASE=$B34,LBO!$D$255,S34) -> 2.736662 | T34: =IF(MCASE=$B34,LBO!$D$256,T34) -> 0.23916836 | U34: =IF(MCASE=$B34,LBO!$D$231,U34) -> -0.04769736 | V34: =IF(MCASE=$B34,LBO!$D$232,V34) -> 11.049485 | W34: =IF(MCASE=$B34,ATP!$C$58,W34) -> 11.526112 | X34: =IF(MCASE=$B34,ATP!$C$59,X34) -> 10.559372 | Y34: =IF(MCASE=$B34,LBO!$D$84,Y34) -> -308.77915 | Z34: =IF(MCASE=$B34,LBO!$I$245,Z34) -> 0 | AA34: =IF(MCASE=$B34,LBO!$J$245,AA34) -> 9.3619617 | AB34: =IF(MCASE=$B34,LBO!$K$245,AB34) -> 48.806138 | AC34: =IF(MCASE=$B34,LBO!$L$245,AC34) -> 49.690811 | AD34: =IF(MCASE=$B34,LBO!$M$245,AD34) -> 50.592856 | AL34: =-($C$11*LBO!$D$23*(1+LBO!$D$39)+LBO!$D$84) -> -264.41666 | AM34: =LBO!I$245 -> 0 | AN34: =LBO!J$245 -> 0.45470337 | AO34: =LBO!K$245 -> 39.187678 | AP34: =LBO!L$245 -> 36.005311 | AQ34: =LBO!M$245+(LBO!$M$238*F$6*(1-LBO!$D$44)-LBO!$M$155+LBO!$M$146) -> 256.32633 | AS34: =-($C$96*LBO!$D$23*(1+LBO!$D$39)+$Y$35) -> -290.0684 | AT34: =$Z$35 -> 0 | AU34: =$AA$35 -> 0 | AV34: =$AB$35 -> 25.370613 | AW34: =$AC$35 -> 47.650811 | AX34: =$AD$35+$R$35 -> 887.97669
B35: 5 | C35: =MCASE!C13 -> Upside (vitiligo) | Base | D35: =IF(MCASE=$B35,LBO!$D$19,D35) -> 10.75 | E35: =IF(MCASE=$B35,LBO!$D$20,E35) -> 0.30461165 | F35: =IF(MCASE=$B35,LBO!$D$33,F35) -> 7.2314151 | G35: =IF(MCASE=$B35,LBO!$D$35,G35) -> 5.3252499 | H35: =IF(MCASE=$B35,LBO!$D$80,H35) -> 251.01312 | I35: =IF(MCASE=$B35,LBO!$D$81,I35) -> 0.76994791 | J35: =IF(MCASE=$B35,LBO!$D$74+LBO!$D$75,J35) -> 75 | K35: =IF(MCASE=$B35,LBO!$I$113,K35) -> 96.854122 | L35: =IF(MCASE=$B35,LBO!$J$109+LBO!$J$110,L35) -> 98.30228 | M35: =IF(MCASE=$B35,LBO!$M$113,M35) -> 144.29263 | N35: =IF(MCASE=$B35,LBO!$H$129,N35) -> 37.1927 | O35: =IF(MCASE=$B35,LBO!$I$129,O35) -> 50.505771 | P35: =IF(MCASE=$B35,LBO!$M$129,P35) -> 88.846456 | Q35: =IF(MCASE=$B35,LBO!$M$246,Q35) -> 133.37428 | R35: =IF(MCASE=$B35,LBO!$M$244,R35) -> 827.62383 | S35: =IF(MCASE=$B35,LBO!$D$255,S35) -> 3.8284776 | T35: =IF(MCASE=$B35,LBO!$D$256,T35) -> 0.31705213 | U35: =IF(MCASE=$B35,LBO!$D$231,U35) -> 0.11816327 | V35: =IF(MCASE=$B35,LBO!$D$232,V35) -> 8.2980528 | W35: =IF(MCASE=$B35,ATP!$C$58,W35) -> 13.505837 | X35: =IF(MCASE=$B35,ATP!$C$59,X35) -> 12.141616 | Y35: =IF(MCASE=$B35,LBO!$D$84,Y35) -> -308.77915 | Z35: =IF(MCASE=$B35,LBO!$I$245,Z35) -> 0 | AA35: =IF(MCASE=$B35,LBO!$J$245,AA35) -> 0 | AB35: =IF(MCASE=$B35,LBO!$K$245,AB35) -> 25.370613 | AC35: =IF(MCASE=$B35,LBO!$L$245,AC35) -> 47.650811 | AD35: =IF(MCASE=$B35,LBO!$M$245,AD35) -> 60.352856 | AL35: =-($C$11*LBO!$D$23*(1+LBO!$D$39)+LBO!$D$84) -> -264.41666 | AM35: =LBO!I$245 -> 0 | AN35: =LBO!J$245 -> 0.45470337 | AO35: =LBO!K$245 -> 39.187678 | AP35: =LBO!L$245 -> 36.005311 | AQ35: =LBO!M$245+(LBO!$M$238*G$6*(1-LBO!$D$44)-LBO!$M$155+LBO!$M$146) -> 301.99003 | AS35: =-($C$97*LBO!$D$23*(1+LBO!$D$39)+$Y$31) -> -322.23187 | AT35: =$Z$31 -> 0 | AU35: =$AA$31 -> 0 | AV35: =$AB$31 -> 12.284322 | AW35: =$AC$31 -> 15.070769 | AX35: =$AD$31+$R$31 -> 87.552596
B36: 6 | C36: =MCASE!C14 -> Downside | High leverage | D36: =IF(MCASE=$B36,LBO!$D$19,D36) -> 10.75 | E36: =IF(MCASE=$B36,LBO!$D$20,E36) -> 0.30461165 | F36: =IF(MCASE=$B36,LBO!$D$33,F36) -> 7.7353699 | G36: =IF(MCASE=$B36,LBO!$D$35,G36) -> 5.5525298 | H36: =IF(MCASE=$B36,LBO!$D$80,H36) -> 199.03975 | I36: =IF(MCASE=$B36,LBO!$D$81,I36) -> 0.60491095 | J36: =IF(MCASE=$B36,LBO!$D$74+LBO!$D$75,J36) -> 130 | K36: =IF(MCASE=$B36,LBO!$I$113,K36) -> 82.334936 | L36: =IF(MCASE=$B36,LBO!$J$109+LBO!$J$110,L36) -> 71.471027 | M36: =IF(MCASE=$B36,LBO!$M$113,M36) -> 40.316172 | N36: =IF(MCASE=$B36,LBO!$H$129,N36) -> 34.931422 | O36: =IF(MCASE=$B36,LBO!$I$129,O36) -> 48.663849 | P36: =IF(MCASE=$B36,LBO!$M$129,P36) -> 11.160326 | Q36: =IF(MCASE=$B36,LBO!$M$246,Q36) -> 2.9984903e-12 | R36: =IF(MCASE=$B36,LBO!$M$244,R36) -> 30.038538 | S36: =IF(MCASE=$B36,LBO!$D$255,S36) -> 0.15091728 | T36: =IF(MCASE=$B36,LBO!$D$256,T36) -> -0.31490974 | U36: =IF(MCASE=$B36,LBO!$D$231,U36) -> 1.3390844 | V36: =IF(MCASE=$B36,LBO!$D$232,V36) -> 5.0183768 | W36: =IF(MCASE=$B36,ATP!$C$58,W36) -> 7.1595516 | X36: =IF(MCASE=$B36,ATP!$C$59,X36) -> 7.116751 | Y36: =IF(MCASE=$B36,LBO!$D$84,Y36) -> -360.75253 | Z36: =IF(MCASE=$B36,LBO!$I$245,Z36) -> 0 | AA36: =IF(MCASE=$B36,LBO!$J$245,AA36) -> 0 | AB36: =IF(MCASE=$B36,LBO!$K$245,AB36) -> 0 | AC36: =IF(MCASE=$B36,LBO!$L$245,AC36) -> 0 | AD36: =IF(MCASE=$B36,LBO!$M$245,AD36) -> 2.9984903e-12 | AL36: =-($C$11*LBO!$D$23*(1+LBO!$D$39)+LBO!$D$84) -> -264.41666 | AM36: =LBO!I$245 -> 0 | AN36: =LBO!J$245 -> 0.45470337 | AO36: =LBO!K$245 -> 39.187678 | AP36: =LBO!L$245 -> 36.005311 | AQ36: =LBO!M$245+(LBO!$M$238*H$6*(1-LBO!$D$44)-LBO!$M$155+LBO!$M$146) -> 347.65372 | AS36: =-($C$97*LBO!$D$23*(1+LBO!$D$39)+$Y$32) -> -321.84676 | AT36: =$Z$32 -> 0 | AU36: =$AA$32 -> 0 | AV36: =$AB$32 -> 29.309743 | AW36: =$AC$32 -> 26.414201 | AX36: =$AD$32+$R$32 -> 194.29904
B37: 7 | C37: =MCASE!C15 -> Conservative | High leverage | D37: =IF(MCASE=$B37,LBO!$D$19,D37) -> 10.75 | E37: =IF(MCASE=$B37,LBO!$D$20,E37) -> 0.30461165 | F37: =IF(MCASE=$B37,LBO!$D$33,F37) -> 7.5734932 | G37: =IF(MCASE=$B37,LBO!$D$35,G37) -> 5.0791739 | H37: =IF(MCASE=$B37,LBO!$D$80,H37) -> 198.65463 | I37: =IF(MCASE=$B37,LBO!$D$81,I37) -> 0.60444799 | J37: =IF(MCASE=$B37,LBO!$D$74+LBO!$D$75,J37) -> 130 | K37: =IF(MCASE=$B37,LBO!$I$113,K37) -> 86.945873 | L37: =IF(MCASE=$B37,LBO!$J$109+LBO!$J$110,L37) -> 80.317181 | M37: =IF(MCASE=$B37,LBO!$M$113,M37) -> 60.029819 | N37: =IF(MCASE=$B37,LBO!$H$129,N37) -> 35.6272 | O37: =IF(MCASE=$B37,LBO!$I$129,O37) -> 53.123276 | P37: =IF(MCASE=$B37,LBO!$M$129,P37) -> 29.803055 | Q37: =IF(MCASE=$B37,LBO!$M$246,Q37) -> 4.1495696e-12 | R37: =IF(MCASE=$B37,LBO!$M$244,R37) -> 171.09977 | S37: =IF(MCASE=$B37,LBO!$D$255,S37) -> 0.86129264 | T37: =IF(MCASE=$B37,LBO!$D$256,T37) -> -0.029422661 | U37: =IF(MCASE=$B37,LBO!$D$231,U37) -> 1.1759675 | V37: =IF(MCASE=$B37,LBO!$D$232,V37) -> 5.5581493 | W37: =IF(MCASE=$B37,ATP!$C$58,W37) -> 8.255584 | X37: =IF(MCASE=$B37,ATP!$C$59,X37) -> 8.0117913 | Y37: =IF(MCASE=$B37,LBO!$D$84,Y37) -> -361.13764 | Z37: =IF(MCASE=$B37,LBO!$I$245,Z37) -> 0 | AA37: =IF(MCASE=$B37,LBO!$J$245,AA37) -> 0 | AB37: =IF(MCASE=$B37,LBO!$K$245,AB37) -> 0 | AC37: =IF(MCASE=$B37,LBO!$L$245,AC37) -> 0 | AD37: =IF(MCASE=$B37,LBO!$M$245,AD37) -> 4.1495696e-12 | AL37: =-($C$11*LBO!$D$23*(1+LBO!$D$39)+LBO!$D$84) -> -264.41666 | AM37: =LBO!I$245 -> 0 | AN37: =LBO!J$245 -> 0.45470337 | AO37: =LBO!K$245 -> 39.187678 | AP37: =LBO!L$245 -> 36.005311 | AQ37: =LBO!M$245+(LBO!$M$238*I$6*(1-LBO!$D$44)-LBO!$M$155+LBO!$M$146) -> 393.31742 | AS37: =-($C$97*LBO!$D$23*(1+LBO!$D$39)+$Y$33) -> -316.49036 | AT37: =$Z$33 -> 0 | AU37: =$AA$33 -> 0.45470337 | AV37: =$AB$33 -> 39.187678 | AW37: =$AC$33 -> 36.005311 | AX37: =$AD$33+$R$33 -> 324.82188
B38: 8 | C38: =MCASE!C16 -> Sponsor base | High leverage | D38: =IF(MCASE=$B38,LBO!$D$19,D38) -> 10.75 | E38: =IF(MCASE=$B38,LBO!$D$20,E38) -> 0.30461165 | F38: =IF(MCASE=$B38,LBO!$D$33,F38) -> 7.3798268 | G38: =IF(MCASE=$B38,LBO!$D$35,G38) -> 4.6841556 | H38: =IF(MCASE=$B38,LBO!$D$80,H38) -> 193.32324 | I38: =IF(MCASE=$B38,LBO!$D$81,I38) -> 0.58881985 | J38: =IF(MCASE=$B38,LBO!$D$74+LBO!$D$75,J38) -> 135 | K38: =IF(MCASE=$B38,LBO!$I$113,K38) -> 90.902403 | L38: =IF(MCASE=$B38,LBO!$J$109+LBO!$J$110,L38) -> 87.739812 | M38: =IF(MCASE=$B38,LBO!$M$113,M38) -> 77.279255 | N38: =IF(MCASE=$B38,LBO!$H$129,N38) -> 36.496922 | O38: =IF(MCASE=$B38,LBO!$I$129,O38) -> 57.50043 | P38: =IF(MCASE=$B38,LBO!$M$129,P38) -> 46.359082 | Q38: =IF(MCASE=$B38,LBO!$M$246,Q38) -> 33.145553 | R38: =IF(MCASE=$B38,LBO!$M$244,R38) -> 291.15032 | S38: =IF(MCASE=$B38,LBO!$D$255,S38) -> 1.6774801 | T38: =IF(MCASE=$B38,LBO!$D$256,T38) -> 0.10899981 | U38: =IF(MCASE=$B38,LBO!$D$231,U38) -> 1.1317707 | V38: =IF(MCASE=$B38,LBO!$D$232,V38) -> 5.7781591 | W38: =IF(MCASE=$B38,ATP!$C$58,W38) -> 9.5402531 | X38: =IF(MCASE=$B38,ATP!$C$59,X38) -> 9.0781778 | Y38: =IF(MCASE=$B38,LBO!$D$84,Y38) -> -366.46904 | Z38: =IF(MCASE=$B38,LBO!$I$245,Z38) -> 0 | AA38: =IF(MCASE=$B38,LBO!$J$245,AA38) -> 0 | AB38: =IF(MCASE=$B38,LBO!$K$245,AB38) -> 0 | AC38: =IF(MCASE=$B38,LBO!$L$245,AC38) -> 5.9117156e-12 | AD38: =IF(MCASE=$B38,LBO!$M$245,AD38) -> 33.145553 | AL38: =-($C$11*LBO!$D$23*(1+LBO!$D$39)+LBO!$D$84) -> -264.41666 | AM38: =LBO!I$245 -> 0 | AN38: =LBO!J$245 -> 0.45470337 | AO38: =LBO!K$245 -> 39.187678 | AP38: =LBO!L$245 -> 36.005311 | AQ38: =LBO!M$245+(LBO!$M$238*J$6*(1-LBO!$D$44)-LBO!$M$155+LBO!$M$146) -> 438.98111 | AS38: =-($C$97*LBO!$D$23*(1+LBO!$D$39)+$Y$34) -> -316.10525 | AT38: =$Z$34 -> 0 | AU38: =$AA$34 -> 9.3619617 | AV38: =$AB$34 -> 48.806138 | AW38: =$AC$34 -> 49.690811 | AX38: =$AD$34+$R$34 -> 579.07917
B39: 9 | C39: =MCASE!C17 -> Orals underwhelm | High leverage | D39: =IF(MCASE=$B39,LBO!$D$19,D39) -> 10.75 | E39: =IF(MCASE=$B39,LBO!$D$20,E39) -> 0.30461165 | F39: =IF(MCASE=$B39,LBO!$D$33,F39) -> 7.2314151 | G39: =IF(MCASE=$B39,LBO!$D$35,G39) -> 4.3028963 | H39: =IF(MCASE=$B39,LBO!$D$80,H39) -> 188.03812 | I39: =IF(MCASE=$B39,LBO!$D$81,I39) -> 0.57322034 | J39: =IF(MCASE=$B39,LBO!$D$74+LBO!$D$75,J39) -> 140 | K39: =IF(MCASE=$B39,LBO!$I$113,K39) -> 96.854122 | L39: =IF(MCASE=$B39,LBO!$J$109+LBO!$J$110,L39) -> 98.30228 | M39: =IF(MCASE=$B39,LBO!$M$113,M39) -> 104.29263 | N39: =IF(MCASE=$B39,LBO!$H$129,N39) -> 37.1927 | O39: =IF(MCASE=$B39,LBO!$I$129,O39) -> 62.505771 | P39: =IF(MCASE=$B39,LBO!$M$129,P39) -> 70.846456 | Q39: =IF(MCASE=$B39,LBO!$M$246,Q39) -> 78.030766 | R39: =IF(MCASE=$B39,LBO!$M$244,R39) -> 528.48631 | S39: =IF(MCASE=$B39,LBO!$D$255,S39) -> 3.2255006 | T39: =IF(MCASE=$B39,LBO!$D$256,T39) -> 0.26694569 | U39: =IF(MCASE=$B39,LBO!$D$231,U39) -> 1.0822347 | V39: =IF(MCASE=$B39,LBO!$D$232,V39) -> 6.383035 | W39: =IF(MCASE=$B39,ATP!$C$58,W39) -> 11.861966 | X39: =IF(MCASE=$B39,ATP!$C$59,X39) -> 10.998576 | Y39: =IF(MCASE=$B39,LBO!$D$84,Y39) -> -371.75415 | Z39: =IF(MCASE=$B39,LBO!$I$245,Z39) -> 0 | AA39: =IF(MCASE=$B39,LBO!$J$245,AA39) -> 0 | AB39: =IF(MCASE=$B39,LBO!$K$245,AB39) -> 0 | AC39: =IF(MCASE=$B39,LBO!$L$245,AC39) -> 27.33011 | AD39: =IF(MCASE=$B39,LBO!$M$245,AD39) -> 50.700656 | AL39: =-($C$11*LBO!$D$23*(1+LBO!$D$39)+LBO!$D$84) -> -264.41666 | AM39: =LBO!I$245 -> 0 | AN39: =LBO!J$245 -> 0.45470337 | AO39: =LBO!K$245 -> 39.187678 | AP39: =LBO!L$245 -> 36.005311 | AQ39: =LBO!M$245+(LBO!$M$238*K$6*(1-LBO!$D$44)-LBO!$M$155+LBO!$M$146) -> 484.64481 | AS39: =-($C$97*LBO!$D$23*(1+LBO!$D$39)+$Y$35) -> -316.10525 | AT39: =$Z$35 -> 0 | AU39: =$AA$35 -> 0 | AV39: =$AB$35 -> 25.370613 | AW39: =$AC$35 -> 47.650811 | AX39: =$AD$35+$R$35 -> 887.97669
B40: 10 | C40: =MCASE!C18 -> Upside (vitiligo) | High leverage | D40: =IF(MCASE=$B40,LBO!$D$19,D40) -> 10.75 | E40: =IF(MCASE=$B40,LBO!$D$20,E40) -> 0.30461165 | F40: =IF(MCASE=$B40,LBO!$D$33,F40) -> 7.2314151 | G40: =IF(MCASE=$B40,LBO!$D$35,G40) -> 5.3252499 | H40: =IF(MCASE=$B40,LBO!$D$80,H40) -> 188.03812 | I40: =IF(MCASE=$B40,LBO!$D$81,I40) -> 0.57322034 | J40: =IF(MCASE=$B40,LBO!$D$74+LBO!$D$75,J40) -> 140 | K40: =IF(MCASE=$B40,LBO!$I$113,K40) -> 96.854122 | L40: =IF(MCASE=$B40,LBO!$J$109+LBO!$J$110,L40) -> 98.30228 | M40: =IF(MCASE=$B40,LBO!$M$113,M40) -> 144.29263 | N40: =IF(MCASE=$B40,LBO!$H$129,N40) -> 37.1927 | O40: =IF(MCASE=$B40,LBO!$I$129,O40) -> 50.505771 | P40: =IF(MCASE=$B40,LBO!$M$129,P40) -> 88.846456 | Q40: =IF(MCASE=$B40,LBO!$M$246,Q40) -> 48.220847 | R40: =IF(MCASE=$B40,LBO!$M$244,R40) -> 827.62383 | S40: =IF(MCASE=$B40,LBO!$D$255,S40) -> 4.6578038 | T40: =IF(MCASE=$B40,LBO!$D$256,T40) -> 0.36030482 | U40: =IF(MCASE=$B40,LBO!$D$231,U40) -> 1.5170602 | V40: =IF(MCASE=$B40,LBO!$D$232,V40) -> 4.9240733 | W40: =IF(MCASE=$B40,ATP!$C$58,W40) -> 13.898311 | X40: =IF(MCASE=$B40,ATP!$C$59,X40) -> 12.650358 | Y40: =IF(MCASE=$B40,LBO!$D$84,Y40) -> -371.75415 | Z40: =IF(MCASE=$B40,LBO!$I$245,Z40) -> 0 | AA40: =IF(MCASE=$B40,LBO!$J$245,AA40) -> 0 | AB40: =IF(MCASE=$B40,LBO!$K$245,AB40) -> 0 | AC40: =IF(MCASE=$B40,LBO!$L$245,AC40) -> 0 | AD40: =IF(MCASE=$B40,LBO!$M$245,AD40) -> 48.220847 | AL40: =-($C$12*LBO!$D$23*(1+LBO!$D$39)+LBO!$D$84) -> -290.45351 | AM40: =LBO!I$245 -> 0 | AN40: =LBO!J$245 -> 0.45470337 | AO40: =LBO!K$245 -> 39.187678 | AP40: =LBO!L$245 -> 36.005311 | AQ40: =LBO!M$245+(LBO!$M$238*E$6*(1-LBO!$D$44)-LBO!$M$155+LBO!$M$146) -> 210.66264 | AS40: =-($C$98*LBO!$D$23*(1+LBO!$D$39)+$Y$31) -> -348.26872 | AT40: =$Z$31 -> 0 | AU40: =$AA$31 -> 0 | AV40: =$AB$31 -> 12.284322 | AW40: =$AC$31 -> 15.070769 | AX40: =$AD$31+$R$31 -> 87.552596
B41: 11 | C41: =MCASE!C19 -> Downside | Low leverage | D41: =IF(MCASE=$B41,LBO!$D$19,D41) -> 10.75 | E41: =IF(MCASE=$B41,LBO!$D$20,E41) -> 0.30461165 | F41: =IF(MCASE=$B41,LBO!$D$33,F41) -> 7.7353699 | G41: =IF(MCASE=$B41,LBO!$D$35,G41) -> 5.5525298 | H41: =IF(MCASE=$B41,LBO!$D$80,H41) -> 291.17725 | I41: =IF(MCASE=$B41,LBO!$D$81,I41) -> 0.89269638 | J41: =IF(MCASE=$B41,LBO!$D$74+LBO!$D$75,J41) -> 35 | K41: =IF(MCASE=$B41,LBO!$I$113,K41) -> 82.334936 | L41: =IF(MCASE=$B41,LBO!$J$109+LBO!$J$110,L41) -> 71.471027 | M41: =IF(MCASE=$B41,LBO!$M$113,M41) -> 40.316172 | N41: =IF(MCASE=$B41,LBO!$H$129,N41) -> 34.931422 | O41: =IF(MCASE=$B41,LBO!$I$129,O41) -> 48.663849 | P41: =IF(MCASE=$B41,LBO!$M$129,P41) -> 11.160326 | Q41: =IF(MCASE=$B41,LBO!$M$246,Q41) -> 75.763301 | R41: =IF(MCASE=$B41,LBO!$M$244,R41) -> 78.475222 | S41: =IF(MCASE=$B41,LBO!$D$255,S41) -> 0.52970665 | T41: =IF(MCASE=$B41,LBO!$D$256,T41) -> -0.14188944 | U41: =IF(MCASE=$B41,LBO!$D$231,U41) -> -0.77121017 | V41: =IF(MCASE=$B41,LBO!$D$232,V41) -> 24.517244 | W41: =IF(MCASE=$B41,ATP!$C$58,W41) -> 6.6111512 | X41: =IF(MCASE=$B41,ATP!$C$59,X41) -> 6.4060132 | Y41: =IF(MCASE=$B41,LBO!$D$84,Y41) -> -268.61503 | Z41: =IF(MCASE=$B41,LBO!$I$245,Z41) -> 0 | AA41: =IF(MCASE=$B41,LBO!$J$245,AA41) -> 28.63393 | AB41: =IF(MCASE=$B41,LBO!$K$245,AB41) -> 23.089028 | AC41: =IF(MCASE=$B41,LBO!$L$245,AC41) -> 15.016869 | AD41: =IF(MCASE=$B41,LBO!$M$245,AD41) -> 9.0234734 | AL41: =-($C$12*LBO!$D$23*(1+LBO!$D$39)+LBO!$D$84) -> -290.45351 | AM41: =LBO!I$245 -> 0 | AN41: =LBO!J$245 -> 0.45470337 | AO41: =LBO!K$245 -> 39.187678 | AP41: =LBO!L$245 -> 36.005311 | AQ41: =LBO!M$245+(LBO!$M$238*F$6*(1-LBO!$D$44)-LBO!$M$155+LBO!$M$146) -> 256.32633 | AS41: =-($C$98*LBO!$D$23*(1+LBO!$D$39)+$Y$32) -> -347.88361 | AT41: =$Z$32 -> 0 | AU41: =$AA$32 -> 0 | AV41: =$AB$32 -> 29.309743 | AW41: =$AC$32 -> 26.414201 | AX41: =$AD$32+$R$32 -> 194.29904
B42: 12 | C42: =MCASE!C20 -> Conservative | Low leverage | D42: =IF(MCASE=$B42,LBO!$D$19,D42) -> 10.75 | E42: =IF(MCASE=$B42,LBO!$D$20,E42) -> 0.30461165 | F42: =IF(MCASE=$B42,LBO!$D$33,F42) -> 7.5734932 | G42: =IF(MCASE=$B42,LBO!$D$35,G42) -> 5.0791739 | H42: =IF(MCASE=$B42,LBO!$D$80,H42) -> 290.79213 | I42: =IF(MCASE=$B42,LBO!$D$81,I42) -> 0.89256954 | J42: =IF(MCASE=$B42,LBO!$D$74+LBO!$D$75,J42) -> 35 | K42: =IF(MCASE=$B42,LBO!$I$113,K42) -> 86.945873 | L42: =IF(MCASE=$B42,LBO!$J$109+LBO!$J$110,L42) -> 80.317181 | M42: =IF(MCASE=$B42,LBO!$M$113,M42) -> 60.029819 | N42: =IF(MCASE=$B42,LBO!$H$129,N42) -> 35.6272 | O42: =IF(MCASE=$B42,LBO!$I$129,O42) -> 53.123276 | P42: =IF(MCASE=$B42,LBO!$M$129,P42) -> 29.803055 | Q42: =IF(MCASE=$B42,LBO!$M$246,Q42) -> 116.63955 | R42: =IF(MCASE=$B42,LBO!$M$244,R42) -> 172.10204 | S42: =IF(MCASE=$B42,LBO!$D$255,S42) -> 0.99294842 | T42: =IF(MCASE=$B42,LBO!$D$256,T42) -> -0.0016407429 | U42: =IF(MCASE=$B42,LBO!$D$231,U42) -> -0.75296562 | V42: =IF(MCASE=$B42,LBO!$D$232,V42) -> 28.370241 | W42: =IF(MCASE=$B42,ATP!$C$58,W42) -> 7.7485723 | X42: =IF(MCASE=$B42,ATP!$C$59,X42) -> 7.3564971 | Y42: =IF(MCASE=$B42,LBO!$D$84,Y42) -> -269.00014 | Z42: =IF(MCASE=$B42,LBO!$I$245,Z42) -> 0.20435871 | AA42: =IF(MCASE=$B42,LBO!$J$245,AA42) -> 36.624144 | AB42: =IF(MCASE=$B42,LBO!$K$245,AB42) -> 31.307645 | AC42: =IF(MCASE=$B42,LBO!$L$245,AC42) -> 26.360301 | AD42: =IF(MCASE=$B42,LBO!$M$245,AD42) -> 22.143097 | AL42: =-($C$12*LBO!$D$23*(1+LBO!$D$39)+LBO!$D$84) -> -290.45351 | AM42: =LBO!I$245 -> 0 | AN42: =LBO!J$245 -> 0.45470337 | AO42: =LBO!K$245 -> 39.187678 | AP42: =LBO!L$245 -> 36.005311 | AQ42: =LBO!M$245+(LBO!$M$238*G$6*(1-LBO!$D$44)-LBO!$M$155+LBO!$M$146) -> 301.99003 | AS42: =-($C$98*LBO!$D$23*(1+LBO!$D$39)+$Y$33) -> -342.52721 | AT42: =$Z$33 -> 0 | AU42: =$AA$33 -> 0.45470337 | AV42: =$AB$33 -> 39.187678 | AW42: =$AC$33 -> 36.005311 | AX42: =$AD$33+$R$33 -> 324.82188
B43: 13 | C43: =MCASE!C21 -> Sponsor base | Low leverage | D43: =IF(MCASE=$B43,LBO!$D$19,D43) -> 10.75 | E43: =IF(MCASE=$B43,LBO!$D$20,E43) -> 0.30461165 | F43: =IF(MCASE=$B43,LBO!$D$33,F43) -> 7.3798268 | G43: =IF(MCASE=$B43,LBO!$D$35,G43) -> 4.6841556 | H43: =IF(MCASE=$B43,LBO!$D$80,H43) -> 290.31074 | I43: =IF(MCASE=$B43,LBO!$D$81,I43) -> 0.89241056 | J43: =IF(MCASE=$B43,LBO!$D$74+LBO!$D$75,J43) -> 35 | K43: =IF(MCASE=$B43,LBO!$I$113,K43) -> 90.902403 | L43: =IF(MCASE=$B43,LBO!$J$109+LBO!$J$110,L43) -> 87.739812 | M43: =IF(MCASE=$B43,LBO!$M$113,M43) -> 77.279255 | N43: =IF(MCASE=$B43,LBO!$H$129,N43) -> 36.496922 | O43: =IF(MCASE=$B43,LBO!$I$129,O43) -> 57.50043 | P43: =IF(MCASE=$B43,LBO!$M$129,P43) -> 46.359082 | Q43: =IF(MCASE=$B43,LBO!$M$246,Q43) -> 153.21733 | R43: =IF(MCASE=$B43,LBO!$M$244,R43) -> 291.15032 | S43: =IF(MCASE=$B43,LBO!$D$255,S43) -> 1.5306621 | T43: =IF(MCASE=$B43,LBO!$D$256,T43) -> 0.10203566 | U43: =IF(MCASE=$B43,LBO!$D$231,U43) -> -0.69564697 | V43: =IF(MCASE=$B43,LBO!$D$232,V43) -> 30.70784 | W43: =IF(MCASE=$B43,ATP!$C$58,W43) -> 9.0506205 | X43: =IF(MCASE=$B43,ATP!$C$59,X43) -> 8.4422154 | Y43: =IF(MCASE=$B43,LBO!$D$84,Y43) -> -269.48154 | Z43: =IF(MCASE=$B43,LBO!$I$245,Z43) -> 2.8733038 | AA43: =IF(MCASE=$B43,LBO!$J$245,AA43) -> 41.662182 | AB43: =IF(MCASE=$B43,LBO!$K$245,AB43) -> 39.126778 | AC43: =IF(MCASE=$B43,LBO!$L$245,AC43) -> 35.944411 | AD43: =IF(MCASE=$B43,LBO!$M$245,AD43) -> 33.610652 | AL43: =-($C$12*LBO!$D$23*(1+LBO!$D$39)+LBO!$D$84) -> -290.45351 | AM43: =LBO!I$245 -> 0 | AN43: =LBO!J$245 -> 0.45470337 | AO43: =LBO!K$245 -> 39.187678 | AP43: =LBO!L$245 -> 36.005311 | AQ43: =LBO!M$245+(LBO!$M$238*H$6*(1-LBO!$D$44)-LBO!$M$155+LBO!$M$146) -> 347.65372 | AS43: =-($C$98*LBO!$D$23*(1+LBO!$D$39)+$Y$34) -> -342.1421 | AT43: =$Z$34 -> 0 | AU43: =$AA$34 -> 9.3619617 | AV43: =$AB$34 -> 48.806138 | AW43: =$AC$34 -> 49.690811 | AX43: =$AD$34+$R$34 -> 579.07917
B44: 14 | C44: =MCASE!C22 -> Orals underwhelm | Low leverage | D44: =IF(MCASE=$B44,LBO!$D$19,D44) -> 10.75 | E44: =IF(MCASE=$B44,LBO!$D$20,E44) -> 0.30461165 | F44: =IF(MCASE=$B44,LBO!$D$33,F44) -> 7.2314151 | G44: =IF(MCASE=$B44,LBO!$D$35,G44) -> 4.3028963 | H44: =IF(MCASE=$B44,LBO!$D$80,H44) -> 289.92562 | I44: =IF(MCASE=$B44,LBO!$D$81,I44) -> 0.89228304 | J44: =IF(MCASE=$B44,LBO!$D$74+LBO!$D$75,J44) -> 35 | K44: =IF(MCASE=$B44,LBO!$I$113,K44) -> 96.854122 | L44: =IF(MCASE=$B44,LBO!$J$109+LBO!$J$110,L44) -> 98.30228 | M44: =IF(MCASE=$B44,LBO!$M$113,M44) -> 104.29263 | N44: =IF(MCASE=$B44,LBO!$H$129,N44) -> 37.1927 | O44: =IF(MCASE=$B44,LBO!$I$129,O44) -> 62.505771 | P44: =IF(MCASE=$B44,LBO!$M$129,P44) -> 70.846456 | Q44: =IF(MCASE=$B44,LBO!$M$246,Q44) -> 202.15139 | R44: =IF(MCASE=$B44,LBO!$M$244,R44) -> 528.48631 | S44: =IF(MCASE=$B44,LBO!$D$255,S44) -> 2.5200867 | T44: =IF(MCASE=$B44,LBO!$D$256,T44) -> 0.22968055 | U44: =IF(MCASE=$B44,LBO!$D$231,U44) -> -0.56460128 | V44: =IF(MCASE=$B44,LBO!$D$232,V44) -> 33.380919 | W44: =IF(MCASE=$B44,ATP!$C$58,W44) -> 11.377405 | X44: =IF(MCASE=$B44,ATP!$C$59,X44) -> 10.367324 | Y44: =IF(MCASE=$B44,LBO!$D$84,Y44) -> -269.86665 | Z44: =IF(MCASE=$B44,LBO!$I$245,Z44) -> 5.6452245 | AA44: =IF(MCASE=$B44,LBO!$J$245,AA44) -> 47.599066 | AB44: =IF(MCASE=$B44,LBO!$K$245,AB44) -> 48.745238 | AC44: =IF(MCASE=$B44,LBO!$L$245,AC44) -> 49.629911 | AD44: =IF(MCASE=$B44,LBO!$M$245,AD44) -> 50.531956 | AL44: =-($C$12*LBO!$D$23*(1+LBO!$D$39)+LBO!$D$84) -> -290.45351 | AM44: =LBO!I$245 -> 0 | AN44: =LBO!J$245 -> 0.45470337 | AO44: =LBO!K$245 -> 39.187678 | AP44: =LBO!L$245 -> 36.005311 | AQ44: =LBO!M$245+(LBO!$M$238*I$6*(1-LBO!$D$44)-LBO!$M$155+LBO!$M$146) -> 393.31742 | AS44: =-($C$98*LBO!$D$23*(1+LBO!$D$39)+$Y$35) -> -342.1421 | AT44: =$Z$35 -> 0 | AU44: =$AA$35 -> 0 | AV44: =$AB$35 -> 25.370613 | AW44: =$AC$35 -> 47.650811 | AX44: =$AD$35+$R$35 -> 887.97669
B45: 15 | C45: =MCASE!C23 -> Upside (vitiligo) | Low leverage | D45: =IF(MCASE=$B45,LBO!$D$19,D45) -> 10.75 | E45: =IF(MCASE=$B45,LBO!$D$20,E45) -> 0.30461165 | F45: =IF(MCASE=$B45,LBO!$D$33,F45) -> 7.2314151 | G45: =IF(MCASE=$B45,LBO!$D$35,G45) -> 5.3252499 | H45: =IF(MCASE=$B45,LBO!$D$80,H45) -> 289.92562 | I45: =IF(MCASE=$B45,LBO!$D$81,I45) -> 0.89228304 | J45: =IF(MCASE=$B45,LBO!$D$74+LBO!$D$75,J45) -> 35 | K45: =IF(MCASE=$B45,LBO!$I$113,K45) -> 96.854122 | L45: =IF(MCASE=$B45,LBO!$J$109+LBO!$J$110,L45) -> 98.30228 | M45: =IF(MCASE=$B45,LBO!$M$113,M45) -> 144.29263 | N45: =IF(MCASE=$B45,LBO!$H$129,N45) -> 37.1927 | O45: =IF(MCASE=$B45,LBO!$I$129,O45) -> 50.505771 | P45: =IF(MCASE=$B45,LBO!$M$129,P45) -> 88.846456 | Q45: =IF(MCASE=$B45,LBO!$M$246,Q45) -> 178.35853 | R45: =IF(MCASE=$B45,LBO!$M$244,R45) -> 827.62383 | S45: =IF(MCASE=$B45,LBO!$D$255,S45) -> 3.4697946 | T45: =IF(MCASE=$B45,LBO!$D$256,T45) -> 0.30226854 | U45: =IF(MCASE=$B45,LBO!$D$231,U45) -> -0.45021492 | V45: =IF(MCASE=$B45,LBO!$D$232,V45) -> 25.085098 | W45: =IF(MCASE=$B45,ATP!$C$58,W45) -> 13.330299 | X45: =IF(MCASE=$B45,ATP!$C$59,X45) -> 11.916043 | Y45: =IF(MCASE=$B45,LBO!$D$84,Y45) -> -269.86665 | Z45: =IF(MCASE=$B45,LBO!$I$245,Z45) -> 0 | AA45: =IF(MCASE=$B45,LBO!$J$245,AA45) -> 32.161427 | AB45: =IF(MCASE=$B45,LBO!$K$245,AB45) -> 38.315238 | AC45: =IF(MCASE=$B45,LBO!$L$245,AC45) -> 47.589911 | AD45: =IF(MCASE=$B45,LBO!$M$245,AD45) -> 60.291956 | AL45: =-($C$12*LBO!$D$23*(1+LBO!$D$39)+LBO!$D$84) -> -290.45351 | AM45: =LBO!I$245 -> 0 | AN45: =LBO!J$245 -> 0.45470337 | AO45: =LBO!K$245 -> 39.187678 | AP45: =LBO!L$245 -> 36.005311 | AQ45: =LBO!M$245+(LBO!$M$238*J$6*(1-LBO!$D$44)-LBO!$M$155+LBO!$M$146) -> 438.98111 | AS45: =-($C$99*LBO!$D$23*(1+LBO!$D$39)+$Y$31) -> -374.30557 | AT45: =$Z$31 -> 0 | AU45: =$AA$31 -> 0 | AV45: =$AB$31 -> 12.284322 | AW45: =$AC$31 -> 15.070769 | AX45: =$AD$31+$R$31 -> 87.552596
B46: 16 | C46: =MCASE!C24 -> Downside | No acquisition debt | D46: =IF(MCASE=$B46,LBO!$D$19,D46) -> 10.75 | E46: =IF(MCASE=$B46,LBO!$D$20,E46) -> 0.30461165 | F46: =IF(MCASE=$B46,LBO!$D$33,F46) -> 7.7353699 | G46: =IF(MCASE=$B46,LBO!$D$35,G46) -> 5.5525298 | H46: =IF(MCASE=$B46,LBO!$D$80,H46) -> 325.38975 | I46: =IF(MCASE=$B46,LBO!$D$81,I46) -> 1 | J46: =IF(MCASE=$B46,LBO!$D$74+LBO!$D$75,J46) -> 0 | K46: =IF(MCASE=$B46,LBO!$I$113,K46) -> 82.334936 | L46: =IF(MCASE=$B46,LBO!$J$109+LBO!$J$110,L46) -> 71.471027 | M46: =IF(MCASE=$B46,LBO!$M$113,M46) -> 40.316172 | N46: =IF(MCASE=$B46,LBO!$H$129,N46) -> 34.931422 | O46: =IF(MCASE=$B46,LBO!$I$129,O46) -> 48.663849 | P46: =IF(MCASE=$B46,LBO!$M$129,P46) -> 11.160326 | Q46: =IF(MCASE=$B46,LBO!$M$246,Q46) -> 111.85123 | R46: =IF(MCASE=$B46,LBO!$M$244,R46) -> 78.475222 | S46: =IF(MCASE=$B46,LBO!$D$255,S46) -> 0.58491841 | T46: =IF(MCASE=$B46,LBO!$D$256,T46) -> -0.13628688 | U46: =IF(MCASE=$B46,LBO!$D$231,U46) -> -0.8219654 | V46: =IF(MCASE=$B46,LBO!$D$232,V46) -> 39.858306 | W46: =IF(MCASE=$B46,ATP!$C$58,W46) -> 6.5258558 | X46: =IF(MCASE=$B46,ATP!$C$59,X46) -> 6.2966971 | Y46: =IF(MCASE=$B46,LBO!$D$84,Y46) -> -234.40253 | Z46: =IF(MCASE=$B46,LBO!$I$245,Z46) -> 33.713471 | AA46: =IF(MCASE=$B46,LBO!$J$245,AA46) -> 31.140691 | AB46: =IF(MCASE=$B46,LBO!$K$245,AB46) -> 23.044928 | AC46: =IF(MCASE=$B46,LBO!$L$245,AC46) -> 14.972769 | AD46: =IF(MCASE=$B46,LBO!$M$245,AD46) -> 8.9793734 | AL46: =-($C$12*LBO!$D$23*(1+LBO!$D$39)+LBO!$D$84) -> -290.45351 | AM46: =LBO!I$245 -> 0 | AN46: =LBO!J$245 -> 0.45470337 | AO46: =LBO!K$245 -> 39.187678 | AP46: =LBO!L$245 -> 36.005311 | AQ46: =LBO!M$245+(LBO!$M$238*K$6*(1-LBO!$D$44)-LBO!$M$155+LBO!$M$146) -> 484.64481 | AS46: =-($C$99*LBO!$D$23*(1+LBO!$D$39)+$Y$32) -> -373.92046 | AT46: =$Z$32 -> 0 | AU46: =$AA$32 -> 0 | AV46: =$AB$32 -> 29.309743 | AW46: =$AC$32 -> 26.414201 | AX46: =$AD$32+$R$32 -> 194.29904
B47: 17 | C47: =MCASE!C25 -> Conservative | No acquisition debt | D47: =IF(MCASE=$B47,LBO!$D$19,D47) -> 10.75 | E47: =IF(MCASE=$B47,LBO!$D$20,E47) -> 0.30461165 | F47: =IF(MCASE=$B47,LBO!$D$33,F47) -> 7.5734932 | G47: =IF(MCASE=$B47,LBO!$D$35,G47) -> 5.0791739 | H47: =IF(MCASE=$B47,LBO!$D$80,H47) -> 325.00463 | I47: =IF(MCASE=$B47,LBO!$D$81,I47) -> 1 | J47: =IF(MCASE=$B47,LBO!$D$74+LBO!$D$75,J47) -> 0 | K47: =IF(MCASE=$B47,LBO!$I$113,K47) -> 86.945873 | L47: =IF(MCASE=$B47,LBO!$J$109+LBO!$J$110,L47) -> 80.317181 | M47: =IF(MCASE=$B47,LBO!$M$113,M47) -> 60.029819 | N47: =IF(MCASE=$B47,LBO!$H$129,N47) -> 35.6272 | O47: =IF(MCASE=$B47,LBO!$I$129,O47) -> 53.123276 | P47: =IF(MCASE=$B47,LBO!$M$129,P47) -> 29.803055 | Q47: =IF(MCASE=$B47,LBO!$M$246,Q47) -> 152.56565 | R47: =IF(MCASE=$B47,LBO!$M$244,R47) -> 172.10204 | S47: =IF(MCASE=$B47,LBO!$D$255,S47) -> 0.99896326 | T47: =IF(MCASE=$B47,LBO!$D$256,T47) -> -0.00026314445 | U47: =IF(MCASE=$B47,LBO!$D$231,U47) -> -0.75296562 | V47: =IF(MCASE=$B47,LBO!$D$232,V47) -> 106.43948 | W47: =IF(MCASE=$B47,ATP!$C$58,W47) -> 7.6674906 | X47: =IF(MCASE=$B47,ATP!$C$59,X47) -> 7.2525326 | Y47: =IF(MCASE=$B47,LBO!$D$84,Y47) -> -234.78764 | Z47: =IF(MCASE=$B47,LBO!$I$245,Z47) -> 36.306859 | AA47: =IF(MCASE=$B47,LBO!$J$245,AA47) -> 36.580044 | AB47: =IF(MCASE=$B47,LBO!$K$245,AB47) -> 31.263545 | AC47: =IF(MCASE=$B47,LBO!$L$245,AC47) -> 26.316201 | AD47: =IF(MCASE=$B47,LBO!$M$245,AD47) -> 22.098997 | AL47: =-($C$13*LBO!$D$23*(1+LBO!$D$39)+LBO!$D$84) -> -316.49036 | AM47: =LBO!I$245 -> 0 | AN47: =LBO!J$245 -> 0.45470337 | AO47: =LBO!K$245 -> 39.187678 | AP47: =LBO!L$245 -> 36.005311 | AQ47: =LBO!M$245+(LBO!$M$238*E$6*(1-LBO!$D$44)-LBO!$M$155+LBO!$M$146) -> 210.66264 | AS47: =-($C$99*LBO!$D$23*(1+LBO!$D$39)+$Y$33) -> -368.56406 | AT47: =$Z$33 -> 0 | AU47: =$AA$33 -> 0.45470337 | AV47: =$AB$33 -> 39.187678 | AW47: =$AC$33 -> 36.005311 | AX47: =$AD$33+$R$33 -> 324.82188
B48: 18 | C48: =MCASE!C26 -> Sponsor base | No acquisition debt | D48: =IF(MCASE=$B48,LBO!$D$19,D48) -> 10.75 | E48: =IF(MCASE=$B48,LBO!$D$20,E48) -> 0.30461165 | F48: =IF(MCASE=$B48,LBO!$D$33,F48) -> 7.3798268 | G48: =IF(MCASE=$B48,LBO!$D$35,G48) -> 4.6841556 | H48: =IF(MCASE=$B48,LBO!$D$80,H48) -> 324.52324 | I48: =IF(MCASE=$B48,LBO!$D$81,I48) -> 1 | J48: =IF(MCASE=$B48,LBO!$D$74+LBO!$D$75,J48) -> 0 | K48: =IF(MCASE=$B48,LBO!$I$113,K48) -> 90.902403 | L48: =IF(MCASE=$B48,LBO!$J$109+LBO!$J$110,L48) -> 87.739812 | M48: =IF(MCASE=$B48,LBO!$M$113,M48) -> 77.279255 | N48: =IF(MCASE=$B48,LBO!$H$129,N48) -> 36.496922 | O48: =IF(MCASE=$B48,LBO!$I$129,O48) -> 57.50043 | P48: =IF(MCASE=$B48,LBO!$M$129,P48) -> 46.359082 | Q48: =IF(MCASE=$B48,LBO!$M$246,Q48) -> 189.14343 | R48: =IF(MCASE=$B48,LBO!$M$244,R48) -> 291.15032 | S48: =IF(MCASE=$B48,LBO!$D$255,S48) -> 1.479998 | T48: =IF(MCASE=$B48,LBO!$D$256,T48) -> 0.10068892 | U48: =IF(MCASE=$B48,LBO!$D$231,U48) -> -0.69564697 | V48: =IF(MCASE=$B48,LBO!$D$232,V48) -> 165.56815 | W48: =IF(MCASE=$B48,ATP!$C$58,W48) -> 8.9695388 | X48: =IF(MCASE=$B48,ATP!$C$59,X48) -> 8.3382509 | Y48: =IF(MCASE=$B48,LBO!$D$84,Y48) -> -235.26904 | Z48: =IF(MCASE=$B48,LBO!$I$245,Z48) -> 38.975804 | AA48: =IF(MCASE=$B48,LBO!$J$245,AA48) -> 41.618082 | AB48: =IF(MCASE=$B48,LBO!$K$245,AB48) -> 39.082678 | AC48: =IF(MCASE=$B48,LBO!$L$245,AC48) -> 35.900311 | AD48: =IF(MCASE=$B48,LBO!$M$245,AD48) -> 33.566552 | AL48: =-($C$13*LBO!$D$23*(1+LBO!$D$39)+LBO!$D$84) -> -316.49036 | AM48: =LBO!I$245 -> 0 | AN48: =LBO!J$245 -> 0.45470337 | AO48: =LBO!K$245 -> 39.187678 | AP48: =LBO!L$245 -> 36.005311 | AQ48: =LBO!M$245+(LBO!$M$238*F$6*(1-LBO!$D$44)-LBO!$M$155+LBO!$M$146) -> 256.32633 | AS48: =-($C$99*LBO!$D$23*(1+LBO!$D$39)+$Y$34) -> -368.17895 | AT48: =$Z$34 -> 0 | AU48: =$AA$34 -> 9.3619617 | AV48: =$AB$34 -> 48.806138 | AW48: =$AC$34 -> 49.690811 | AX48: =$AD$34+$R$34 -> 579.07917
B49: 19 | C49: =MCASE!C27 -> Orals underwhelm | No acquisition debt | D49: =IF(MCASE=$B49,LBO!$D$19,D49) -> 10.75 | E49: =IF(MCASE=$B49,LBO!$D$20,E49) -> 0.30461165 | F49: =IF(MCASE=$B49,LBO!$D$33,F49) -> 7.2314151 | G49: =IF(MCASE=$B49,LBO!$D$35,G49) -> 4.3028963 | H49: =IF(MCASE=$B49,LBO!$D$80,H49) -> 324.13812 | I49: =IF(MCASE=$B49,LBO!$D$81,I49) -> 1 | J49: =IF(MCASE=$B49,LBO!$D$74+LBO!$D$75,J49) -> 0 | K49: =IF(MCASE=$B49,LBO!$I$113,K49) -> 96.854122 | L49: =IF(MCASE=$B49,LBO!$J$109+LBO!$J$110,L49) -> 98.30228 | M49: =IF(MCASE=$B49,LBO!$M$113,M49) -> 104.29263 | N49: =IF(MCASE=$B49,LBO!$H$129,N49) -> 37.1927 | O49: =IF(MCASE=$B49,LBO!$I$129,O49) -> 62.505771 | P49: =IF(MCASE=$B49,LBO!$M$129,P49) -> 70.846456 | Q49: =IF(MCASE=$B49,LBO!$M$246,Q49) -> 238.07749 | R49: =IF(MCASE=$B49,LBO!$M$244,R49) -> 528.48631 | S49: =IF(MCASE=$B49,LBO!$D$255,S49) -> 2.3649295 | T49: =IF(MCASE=$B49,LBO!$D$256,T49) -> 0.22502632 | U49: =IF(MCASE=$B49,LBO!$D$231,U49) -> -0.56460128 | V49: =IF(MCASE=$B49,LBO!$D$232,V49) -> 223.2349 | W49: =IF(MCASE=$B49,ATP!$C$58,W49) -> 11.296324 | X49: =IF(MCASE=$B49,ATP!$C$59,X49) -> 10.263359 | Y49: =IF(MCASE=$B49,LBO!$D$84,Y49) -> -235.65415 | Z49: =IF(MCASE=$B49,LBO!$I$245,Z49) -> 41.747724 | AA49: =IF(MCASE=$B49,LBO!$J$245,AA49) -> 47.554966 | AB49: =IF(MCASE=$B49,LBO!$K$245,AB49) -> 48.701138 | AC49: =IF(MCASE=$B49,LBO!$L$245,AC49) -> 49.585811 | AD49: =IF(MCASE=$B49,LBO!$M$245,AD49) -> 50.487856 | AL49: =-($C$13*LBO!$D$23*(1+LBO!$D$39)+LBO!$D$84) -> -316.49036 | AM49: =LBO!I$245 -> 0 | AN49: =LBO!J$245 -> 0.45470337 | AO49: =LBO!K$245 -> 39.187678 | AP49: =LBO!L$245 -> 36.005311 | AQ49: =LBO!M$245+(LBO!$M$238*G$6*(1-LBO!$D$44)-LBO!$M$155+LBO!$M$146) -> 301.99003 | AS49: =-($C$99*LBO!$D$23*(1+LBO!$D$39)+$Y$35) -> -368.17895 | AT49: =$Z$35 -> 0 | AU49: =$AA$35 -> 0 | AV49: =$AB$35 -> 25.370613 | AW49: =$AC$35 -> 47.650811 | AX49: =$AD$35+$R$35 -> 887.97669
B50: 20 | C50: =MCASE!C28 -> Upside (vitiligo) | No acquisition debt | D50: =IF(MCASE=$B50,LBO!$D$19,D50) -> 10.75 | E50: =IF(MCASE=$B50,LBO!$D$20,E50) -> 0.30461165 | F50: =IF(MCASE=$B50,LBO!$D$33,F50) -> 7.2314151 | G50: =IF(MCASE=$B50,LBO!$D$35,G50) -> 5.3252499 | H50: =IF(MCASE=$B50,LBO!$D$80,H50) -> 324.13812 | I50: =IF(MCASE=$B50,LBO!$D$81,I50) -> 1 | J50: =IF(MCASE=$B50,LBO!$D$74+LBO!$D$75,J50) -> 0 | K50: =IF(MCASE=$B50,LBO!$I$113,K50) -> 96.854122 | L50: =IF(MCASE=$B50,LBO!$J$109+LBO!$J$110,L50) -> 98.30228 | M50: =IF(MCASE=$B50,LBO!$M$113,M50) -> 144.29263 | N50: =IF(MCASE=$B50,LBO!$H$129,N50) -> 37.1927 | O50: =IF(MCASE=$B50,LBO!$I$129,O50) -> 50.505771 | P50: =IF(MCASE=$B50,LBO!$M$129,P50) -> 88.846456 | Q50: =IF(MCASE=$B50,LBO!$M$246,Q50) -> 214.48749 | R50: =IF(MCASE=$B50,LBO!$M$244,R50) -> 827.62383 | S50: =IF(MCASE=$B50,LBO!$D$255,S50) -> 3.2150224 | T50: =IF(MCASE=$B50,LBO!$D$256,T50) -> 0.29573343 | U50: =IF(MCASE=$B50,LBO!$D$231,U50) -> -0.45021492 | V50: =IF(MCASE=$B50,LBO!$D$232,V50) -> 177.28706 | W50: =IF(MCASE=$B50,ATP!$C$58,W50) -> 13.243935 | X50: =IF(MCASE=$B50,ATP!$C$59,X50) -> 11.80537 | Y50: =IF(MCASE=$B50,LBO!$D$84,Y50) -> -235.65415 | Z50: =IF(MCASE=$B50,LBO!$I$245,Z50) -> 33.107724 | AA50: =IF(MCASE=$B50,LBO!$J$245,AA50) -> 35.314966 | AB50: =IF(MCASE=$B50,LBO!$K$245,AB50) -> 38.271138 | AC50: =IF(MCASE=$B50,LBO!$L$245,AC50) -> 47.545811 | AD50: =IF(MCASE=$B50,LBO!$M$245,AD50) -> 60.247856 | AL50: =-($C$13*LBO!$D$23*(1+LBO!$D$39)+LBO!$D$84) -> -316.49036 | AM50: =LBO!I$245 -> 0 | AN50: =LBO!J$245 -> 0.45470337 | AO50: =LBO!K$245 -> 39.187678 | AP50: =LBO!L$245 -> 36.005311 | AQ50: =LBO!M$245+(LBO!$M$238*H$6*(1-LBO!$D$44)-LBO!$M$155+LBO!$M$146) -> 347.65372
B51: 21 | C51: =MCASE!C29 -> Sponsor base | Base | CEO rolls 6.8% | D51: =IF(MCASE=$B51,LBO!$D$19,D51) -> 10.75 | E51: =IF(MCASE=$B51,LBO!$D$20,E51) -> 0.30461165 | F51: =IF(MCASE=$B51,LBO!$D$33,F51) -> 7.3798268 | G51: =IF(MCASE=$B51,LBO!$D$35,G51) -> 4.6841556 | H51: =IF(MCASE=$B51,LBO!$D$80,H51) -> 251.39824 | I51: =IF(MCASE=$B51,LBO!$D$81,I51) -> 0.77021935 | J51: =IF(MCASE=$B51,LBO!$D$74+LBO!$D$75,J51) -> 75 | K51: =IF(MCASE=$B51,LBO!$I$113,K51) -> 90.902403 | L51: =IF(MCASE=$B51,LBO!$J$109+LBO!$J$110,L51) -> 87.739812 | M51: =IF(MCASE=$B51,LBO!$M$113,M51) -> 77.279255 | N51: =IF(MCASE=$B51,LBO!$H$129,N51) -> 36.496922 | O51: =IF(MCASE=$B51,LBO!$I$129,O51) -> 57.50043 | P51: =IF(MCASE=$B51,LBO!$M$129,P51) -> 46.359082 | Q51: =IF(MCASE=$B51,LBO!$M$246,Q51) -> 109.31924 | R51: =IF(MCASE=$B51,LBO!$M$244,R51) -> 291.15032 | S51: =IF(MCASE=$B51,LBO!$D$255,S51) -> 1.5929689 | T51: =IF(MCASE=$B51,LBO!$D$256,T51) -> 0.10437355 | U51: =IF(MCASE=$B51,LBO!$D$231,U51) -> -0.0019167295 | V51: =IF(MCASE=$B51,LBO!$D$232,V51) -> 9.9229181 | W51: =IF(MCASE=$B51,ATP!$C$58,W51) -> 9.2040734 | X51: =IF(MCASE=$B51,ATP!$C$59,X51) -> 8.6403414 | Y51: =IF(MCASE=$B51,LBO!$D$84,Y51) -> -308.39404 | Z51: =IF(MCASE=$B51,LBO!$I$245,Z51) -> 0 | AA51: =IF(MCASE=$B51,LBO!$J$245,AA51) -> 0.45470337 | AB51: =IF(MCASE=$B51,LBO!$K$245,AB51) -> 39.187678 | AC51: =IF(MCASE=$B51,LBO!$L$245,AC51) -> 36.005311 | AD51: =IF(MCASE=$B51,LBO!$M$245,AD51) -> 33.671552 | AL51: =-($C$13*LBO!$D$23*(1+LBO!$D$39)+LBO!$D$84) -> -316.49036 | AM51: =LBO!I$245 -> 0 | AN51: =LBO!J$245 -> 0.45470337 | AO51: =LBO!K$245 -> 39.187678 | AP51: =LBO!L$245 -> 36.005311 | AQ51: =LBO!M$245+(LBO!$M$238*I$6*(1-LBO!$D$44)-LBO!$M$155+LBO!$M$146) -> 393.31742
B52: 22 | C52: =MCASE!C30 -> Sponsor base | Base | A$9.50 offer | D52: =IF(MCASE=$B52,LBO!$D$19,D52) -> 9.5 | E52: =IF(MCASE=$B52,LBO!$D$20,E52) -> 0.15291262 | F52: =IF(MCASE=$B52,LBO!$D$33,F52) -> 5.644064 | G52: =IF(MCASE=$B52,LBO!$D$35,G52) -> 3.5824247 | H52: =IF(MCASE=$B52,LBO!$D$80,H52) -> 186.30611 | I52: =IF(MCASE=$B52,LBO!$D$81,I52) -> 0.71298031 | J52: =IF(MCASE=$B52,LBO!$D$74+LBO!$D$75,J52) -> 75 | K52: =IF(MCASE=$B52,LBO!$I$113,K52) -> 90.902403 | L52: =IF(MCASE=$B52,LBO!$J$109+LBO!$J$110,L52) -> 87.739812 | M52: =IF(MCASE=$B52,LBO!$M$113,M52) -> 77.279255 | N52: =IF(MCASE=$B52,LBO!$H$129,N52) -> 36.496922 | O52: =IF(MCASE=$B52,LBO!$I$129,O52) -> 57.50043 | P52: =IF(MCASE=$B52,LBO!$M$129,P52) -> 46.359082 | Q52: =IF(MCASE=$B52,LBO!$M$246,Q52) -> 109.31924 | R52: =IF(MCASE=$B52,LBO!$M$244,R52) -> 291.15032 | S52: =IF(MCASE=$B52,LBO!$D$255,S52) -> 2.1495246 | T52: =IF(MCASE=$B52,LBO!$D$256,T52) -> 0.17784134 | U52: =IF(MCASE=$B52,LBO!$D$231,U52) -> -0.0019167295 | V52: =IF(MCASE=$B52,LBO!$D$232,V52) -> 9.9229181 | W52: =IF(MCASE=$B52,ATP!$C$58,W52) -> 9.2040734 | X52: =IF(MCASE=$B52,ATP!$C$59,X52) -> 8.6403414 | Y52: =IF(MCASE=$B52,LBO!$D$84,Y52) -> -308.39404 | Z52: =IF(MCASE=$B52,LBO!$I$245,Z52) -> 0 | AA52: =IF(MCASE=$B52,LBO!$J$245,AA52) -> 0.45470337 | AB52: =IF(MCASE=$B52,LBO!$K$245,AB52) -> 39.187678 | AC52: =IF(MCASE=$B52,LBO!$L$245,AC52) -> 36.005311 | AD52: =IF(MCASE=$B52,LBO!$M$245,AD52) -> 33.671552 | AL52: =-($C$13*LBO!$D$23*(1+LBO!$D$39)+LBO!$D$84) -> -316.49036 | AM52: =LBO!I$245 -> 0 | AN52: =LBO!J$245 -> 0.45470337 | AO52: =LBO!K$245 -> 39.187678 | AP52: =LBO!L$245 -> 36.005311 | AQ52: =LBO!M$245+(LBO!$M$238*J$6*(1-LBO!$D$44)-LBO!$M$155+LBO!$M$146) -> 438.98111
B53: 23 | C53: =MCASE!C31 -> Sponsor base | Base | A$12.50 offer | D53: =IF(MCASE=$B53,LBO!$D$19,D53) -> 12.5 | E53: =IF(MCASE=$B53,LBO!$D$20,E53) -> 0.51699029 | F53: =IF(MCASE=$B53,LBO!$D$33,F53) -> 9.8098947 | G53: =IF(MCASE=$B53,LBO!$D$35,G53) -> 6.2265788 | H53: =IF(MCASE=$B53,LBO!$D$80,H53) -> 342.52721 | I53: =IF(MCASE=$B53,LBO!$D$81,I53) -> 0.82037099 | J53: =IF(MCASE=$B53,LBO!$D$74+LBO!$D$75,J53) -> 75 | K53: =IF(MCASE=$B53,LBO!$I$113,K53) -> 90.902403 | L53: =IF(MCASE=$B53,LBO!$J$109+LBO!$J$110,L53) -> 87.739812 | M53: =IF(MCASE=$B53,LBO!$M$113,M53) -> 77.279255 | N53: =IF(MCASE=$B53,LBO!$H$129,N53) -> 36.496922 | O53: =IF(MCASE=$B53,LBO!$I$129,O53) -> 57.50043 | P53: =IF(MCASE=$B53,LBO!$M$129,P53) -> 46.359082 | Q53: =IF(MCASE=$B53,LBO!$M$246,Q53) -> 109.31924 | R53: =IF(MCASE=$B53,LBO!$M$244,R53) -> 291.15032 | S53: =IF(MCASE=$B53,LBO!$D$255,S53) -> 1.1691613 | T53: =IF(MCASE=$B53,LBO!$D$256,T53) -> 0.033781548 | U53: =IF(MCASE=$B53,LBO!$D$231,U53) -> -0.0019167295 | V53: =IF(MCASE=$B53,LBO!$D$232,V53) -> 9.9229181 | W53: =IF(MCASE=$B53,ATP!$C$58,W53) -> 9.2040734 | X53: =IF(MCASE=$B53,ATP!$C$59,X53) -> 8.6403414 | Y53: =IF(MCASE=$B53,LBO!$D$84,Y53) -> -308.39404 | Z53: =IF(MCASE=$B53,LBO!$I$245,Z53) -> 0 | AA53: =IF(MCASE=$B53,LBO!$J$245,AA53) -> 0.45470337 | AB53: =IF(MCASE=$B53,LBO!$K$245,AB53) -> 39.187678 | AC53: =IF(MCASE=$B53,LBO!$L$245,AC53) -> 36.005311 | AD53: =IF(MCASE=$B53,LBO!$M$245,AD53) -> 33.671552 | AL53: =-($C$13*LBO!$D$23*(1+LBO!$D$39)+LBO!$D$84) -> -316.49036 | AM53: =LBO!I$245 -> 0 | AN53: =LBO!J$245 -> 0.45470337 | AO53: =LBO!K$245 -> 39.187678 | AP53: =LBO!L$245 -> 36.005311 | AQ53: =LBO!M$245+(LBO!$M$238*K$6*(1-LBO!$D$44)-LBO!$M$155+LBO!$M$146) -> 484.64481
B54: 24 | C54: =MCASE!C32 -> Base revenue, no cost-out | Base | D54: =IF(MCASE=$B54,LBO!$D$19,D54) -> 10.75 | E54: =IF(MCASE=$B54,LBO!$D$20,E54) -> 0.30461165 | F54: =IF(MCASE=$B54,LBO!$D$33,F54) -> 7.3798268 | G54: =IF(MCASE=$B54,LBO!$D$35,G54) -> 8.9480939 | H54: =IF(MCASE=$B54,LBO!$D$80,H54) -> 251.39824 | I54: =IF(MCASE=$B54,LBO!$D$81,I54) -> 0.77021935 | J54: =IF(MCASE=$B54,LBO!$D$74+LBO!$D$75,J54) -> 75 | K54: =IF(MCASE=$B54,LBO!$I$113,K54) -> 90.902403 | L54: =IF(MCASE=$B54,LBO!$J$109+LBO!$J$110,L54) -> 87.739812 | M54: =IF(MCASE=$B54,LBO!$M$113,M54) -> 77.279255 | N54: =IF(MCASE=$B54,LBO!$H$129,N54) -> 36.496922 | O54: =IF(MCASE=$B54,LBO!$I$129,O54) -> 30.100373 | P54: =IF(MCASE=$B54,LBO!$M$129,P54) -> 24.413001 | Q54: =IF(MCASE=$B54,LBO!$M$246,Q54) -> 6.4762442 | R54: =IF(MCASE=$B54,LBO!$M$244,R54) -> 172.25743 | S54: =IF(MCASE=$B54,LBO!$D$255,S54) -> 0.71095835 | T54: =IF(MCASE=$B54,LBO!$D$256,T54) -> -0.06595278 | U54: =IF(MCASE=$B54,LBO!$D$231,U54) -> 0.627721 | V54: =IF(MCASE=$B54,LBO!$D$232,V54) -> 4.4879426 | W54: =IF(MCASE=$B54,ATP!$C$58,W54) -> 7.3016339 | X54: =IF(MCASE=$B54,ATP!$C$59,X54) -> 7.046964 | Y54: =IF(MCASE=$B54,LBO!$D$84,Y54) -> -308.39404 | Z54: =IF(MCASE=$B54,LBO!$I$245,Z54) -> 0 | AA54: =IF(MCASE=$B54,LBO!$J$245,AA54) -> 0 | AB54: =IF(MCASE=$B54,LBO!$K$245,AB54) -> 0 | AC54: =IF(MCASE=$B54,LBO!$L$245,AC54) -> 0 | AD54: =IF(MCASE=$B54,LBO!$M$245,AD54) -> 6.4762442 | AL54: =-($C$14*LBO!$D$23*(1+LBO!$D$39)+LBO!$D$84) -> -342.52721 | AM54: =LBO!I$245 -> 0 | AN54: =LBO!J$245 -> 0.45470337 | AO54: =LBO!K$245 -> 39.187678 | AP54: =LBO!L$245 -> 36.005311 | AQ54: =LBO!M$245+(LBO!$M$238*E$6*(1-LBO!$D$44)-LBO!$M$155+LBO!$M$146) -> 210.66264
AL55: =-($C$14*LBO!$D$23*(1+LBO!$D$39)+LBO!$D$84) -> -342.52721 | AM55: =LBO!I$245 -> 0 | AN55: =LBO!J$245 -> 0.45470337 | AO55: =LBO!K$245 -> 39.187678 | AP55: =LBO!L$245 -> 36.005311 | AQ55: =LBO!M$245+(LBO!$M$238*F$6*(1-LBO!$D$44)-LBO!$M$155+LBO!$M$146) -> 256.32633
B56: Block D: IRR and MoIC by operating case (rows) x financing case (columns) at the base offer | AL56: =-($C$14*LBO!$D$23*(1+LBO!$D$39)+LBO!$D$84) -> -342.52721 | AM56: =LBO!I$245 -> 0 | AN56: =LBO!J$245 -> 0.45470337 | AO56: =LBO!K$245 -> 39.187678 | AP56: =LBO!L$245 -> 36.005311 | AQ56: =LBO!M$245+(LBO!$M$238*G$6*(1-LBO!$D$44)-LBO!$M$155+LBO!$M$146) -> 301.99003
C57: IRR (Y5) | D57: Base | E57: High leverage | F57: Low leverage | G57: No acquisition debt | AL57: =-($C$14*LBO!$D$23*(1+LBO!$D$39)+LBO!$D$84) -> -342.52721 | AM57: =LBO!I$245 -> 0 | AN57: =LBO!J$245 -> 0.45470337 | AO57: =LBO!K$245 -> 39.187678 | AP57: =LBO!L$245 -> 36.005311 | AQ57: =LBO!M$245+(LBO!$M$238*H$6*(1-LBO!$D$44)-LBO!$M$155+LBO!$M$146) -> 347.65372
C58: 1. Downside | D58: =T31 -> -0.15779358 | E58: =T36 -> -0.31490974 | F58: =T41 -> -0.14188944 | G58: =T46 -> -0.13628688 | AL58: =-($C$14*LBO!$D$23*(1+LBO!$D$39)+LBO!$D$84) -> -342.52721 | AM58: =LBO!I$245 -> 0 | AN58: =LBO!J$245 -> 0.45470337 | AO58: =LBO!K$245 -> 39.187678 | AP58: =LBO!L$245 -> 36.005311 | AQ58: =LBO!M$245+(LBO!$M$238*I$6*(1-LBO!$D$44)-LBO!$M$155+LBO!$M$146) -> 393.31742
C59: 2. Conservative | D59: =T32 -> -0.0056836136 | E59: =T37 -> -0.029422661 | F59: =T42 -> -0.0016407429 | G59: =T47 -> -0.00026314445 | AL59: =-($C$14*LBO!$D$23*(1+LBO!$D$39)+LBO!$D$84) -> -342.52721 | AM59: =LBO!I$245 -> 0 | AN59: =LBO!J$245 -> 0.45470337 | AO59: =LBO!K$245 -> 39.187678 | AP59: =LBO!L$245 -> 36.005311 | AQ59: =LBO!M$245+(LBO!$M$238*J$6*(1-LBO!$D$44)-LBO!$M$155+LBO!$M$146) -> 438.98111
C60: 3. Sponsor base | D60: =T33 -> 0.10437355 | E60: =T38 -> 0.10899981 | F60: =T43 -> 0.10203566 | G60: =T48 -> 0.10068892 | AL60: =-($C$14*LBO!$D$23*(1+LBO!$D$39)+LBO!$D$84) -> -342.52721 | AM60: =LBO!I$245 -> 0 | AN60: =LBO!J$245 -> 0.45470337 | AO60: =LBO!K$245 -> 39.187678 | AP60: =LBO!L$245 -> 36.005311 | AQ60: =LBO!M$245+(LBO!$M$238*K$6*(1-LBO!$D$44)-LBO!$M$155+LBO!$M$146) -> 484.64481
C61: 4. Orals underwhelm | D61: =T34 -> 0.23916836 | E61: =T39 -> 0.26694569 | F61: =T44 -> 0.22968055 | G61: =T49 -> 0.22502632 | AL61: =-($C$15*LBO!$D$23*(1+LBO!$D$39)+LBO!$D$84) -> -368.56406 | AM61: =LBO!I$245 -> 0 | AN61: =LBO!J$245 -> 0.45470337 | AO61: =LBO!K$245 -> 39.187678 | AP61: =LBO!L$245 -> 36.005311 | AQ61: =LBO!M$245+(LBO!$M$238*E$6*(1-LBO!$D$44)-LBO!$M$155+LBO!$M$146) -> 210.66264
C62: 5. Upside (vitiligo) | D62: =T35 -> 0.31705213 | E62: =T40 -> 0.36030482 | F62: =T45 -> 0.30226854 | G62: =T50 -> 0.29573343 | AL62: =-($C$15*LBO!$D$23*(1+LBO!$D$39)+LBO!$D$84) -> -368.56406 | AM62: =LBO!I$245 -> 0 | AN62: =LBO!J$245 -> 0.45470337 | AO62: =LBO!K$245 -> 39.187678 | AP62: =LBO!L$245 -> 36.005311 | AQ62: =LBO!M$245+(LBO!$M$238*F$6*(1-LBO!$D$44)-LBO!$M$155+LBO!$M$146) -> 256.32633
AL63: =-($C$15*LBO!$D$23*(1+LBO!$D$39)+LBO!$D$84) -> -368.56406 | AM63: =LBO!I$245 -> 0 | AN63: =LBO!J$245 -> 0.45470337 | AO63: =LBO!K$245 -> 39.187678 | AP63: =LBO!L$245 -> 36.005311 | AQ63: =LBO!M$245+(LBO!$M$238*G$6*(1-LBO!$D$44)-LBO!$M$155+LBO!$M$146) -> 301.99003
C64: MoIC (Y5) | D64: Base | E64: High leverage | F64: Low leverage | G64: No acquisition debt | AL64: =-($C$15*LBO!$D$23*(1+LBO!$D$39)+LBO!$D$84) -> -368.56406 | AM64: =LBO!I$245 -> 0 | AN64: =LBO!J$245 -> 0.45470337 | AO64: =LBO!K$245 -> 39.187678 | AP64: =LBO!L$245 -> 36.005311 | AQ64: =LBO!M$245+(LBO!$M$238*H$6*(1-LBO!$D$44)-LBO!$M$155+LBO!$M$146) -> 347.65372
C65: 1. Downside | D65: =S31 -> 0.44686863 | E65: =S36 -> 0.15091728 | F65: =S41 -> 0.52970665 | G65: =S46 -> 0.58491841 | AL65: =-($C$15*LBO!$D$23*(1+LBO!$D$39)+LBO!$D$84) -> -368.56406 | AM65: =LBO!I$245 -> 0 | AN65: =LBO!J$245 -> 0.45470337 | AO65: =LBO!K$245 -> 39.187678 | AP65: =LBO!L$245 -> 36.005311 | AQ65: =LBO!M$245+(LBO!$M$238*I$6*(1-LBO!$D$44)-LBO!$M$155+LBO!$M$146) -> 393.31742
C66: 2. Conservative | D66: =S32 -> 0.97378178 | E66: =S37 -> 0.86129264 | F66: =S42 -> 0.99294842 | G66: =S47 -> 0.99896326 | AL66: =-($C$15*LBO!$D$23*(1+LBO!$D$39)+LBO!$D$84) -> -368.56406 | AM66: =LBO!I$245 -> 0 | AN66: =LBO!J$245 -> 0.45470337 | AO66: =LBO!K$245 -> 39.187678 | AP66: =LBO!L$245 -> 36.005311 | AQ66: =LBO!M$245+(LBO!$M$238*J$6*(1-LBO!$D$44)-LBO!$M$155+LBO!$M$146) -> 438.98111
C67: 3. Sponsor base | D67: =S33 -> 1.5929689 | E67: =S38 -> 1.6774801 | F67: =S43 -> 1.5306621 | G67: =S48 -> 1.479998 | AL67: =-($C$15*LBO!$D$23*(1+LBO!$D$39)+LBO!$D$84) -> -368.56406 | AM67: =LBO!I$245 -> 0 | AN67: =LBO!J$245 -> 0.45470337 | AO67: =LBO!K$245 -> 39.187678 | AP67: =LBO!L$245 -> 36.005311 | AQ67: =LBO!M$245+(LBO!$M$238*K$6*(1-LBO!$D$44)-LBO!$M$155+LBO!$M$146) -> 484.64481
C68: 4. Orals underwhelm | D68: =S34 -> 2.736662 | E68: =S39 -> 3.2255006 | F68: =S44 -> 2.5200867 | G68: =S49 -> 2.3649295
C69: 5. Upside (vitiligo) | D69: =S35 -> 3.8284776 | E69: =S40 -> 4.6578038 | F69: =S45 -> 3.4697946 | G69: =S50 -> 3.2150224
C71: Equity invested (A$m) | D71: Base | E71: High leverage | F71: Low leverage | G71: No acquisition debt
C72: 1. Downside | D72: =H31 -> 257.13975 | E72: =H36 -> 199.03975 | F72: =H41 -> 291.17725 | G72: =H46 -> 325.38975
C73: 2. Conservative | D73: =H32 -> 256.75463 | E73: =H37 -> 198.65463 | F73: =H42 -> 290.79213 | G73: =H47 -> 325.00463
C74: 3. Sponsor base | D74: =H33 -> 251.39824 | E74: =H38 -> 193.32324 | F74: =H43 -> 290.31074 | G74: =H48 -> 324.52324
C75: 4. Orals underwhelm | D75: =H34 -> 251.01312 | E75: =H39 -> 188.03812 | F75: =H44 -> 289.92562 | G75: =H49 -> 324.13812
C76: 5. Upside (vitiligo) | D76: =H35 -> 251.01312 | E76: =H40 -> 188.03812 | F76: =H45 -> 289.92562 | G76: =H50 -> 324.13812
B78: Block E: probability-weighted outcome (base financing, base offer) - illustrative weights
C79: Operating case | D79: Probability | E79: IRR | F79: MoIC | G79: Exit eq.+dist. | H79: ATP @20%
C80: 1. Downside | D80: 0.2 | E80: =T31 -> -0.15779358 | F80: =S31 -> 0.44686863 | G80: =R31+Q31 -> 114.90769 | H80: =W31 -> 6.7637763
C81: 2. Conservative | D81: 0.3 | E81: =T32 -> -0.0056836136 | F81: =S32 -> 0.97378178 | G81: =R32+Q32 -> 250.02298 | H81: =W32 -> 7.8892427
C82: 3. Sponsor base | D82: 0.3 | E82: =T33 -> 0.10437355 | F82: =S33 -> 1.5929689 | G82: =R33+Q33 -> 400.46957 | H82: =W33 -> 9.2040734
C83: 4. Orals underwhelm | D83: 0.15 | E83: =T34 -> 0.23916836 | F83: =S34 -> 2.736662 | G83: =R34+Q34 -> 686.93808 | H83: =W34 -> 11.526112
C84: 5. Upside (vitiligo) | D84: 0.05 | E84: =T35 -> 0.31705213 | F84: =S35 -> 3.8284776 | G84: =R35+Q35 -> 960.99811 | H84: =W35 -> 13.505837
C85: Probability-weighted | D85: =SUM(D80:D84) -> 1 | E85: =SUMPRODUCT($D80:$D84,E80:E84) -> 0.049776124 | F85: =SUMPRODUCT($D80:$D84,F80:F84) -> 1.4613221 | G85: =SUMPRODUCT($D80:$D84,G80:G84) -> 369.21992 | H85: =SUMPRODUCT($D80:$D84,H80:H84) -> 8.8849587 | I85: (IRR/MoIC here = probability-weighted averages)
C86: Expected cash flows to equity, t = 0..5 (A$m) | D86: =-SUMPRODUCT($D$80:$D$84,H31:H35) -> -254.07644 | E86: =SUMPRODUCT($D$80:$D$84,Z31:Z35) -> 0 | F86: =SUMPRODUCT($D$80:$D$84,AA31:AA35) -> 1.5407053 | G86: =SUMPRODUCT($D$80:$D$84,AB31:AB35) -> 31.595542 | H86: =SUMPRODUCT($D$80:$D$84,AC31:AC35) -> 31.576169 | I86: =SUMPRODUCT($D$80:$D$84,AD31:AD35)+SUMPRODUCT($D$80:$D$84,R31:R35) -> 304.5075
C87: IRR / MoIC of expected cash flows | D87: =IFERROR(IRR(D86:I86,0.15),IFERROR(IRR(D86:I86,-0.2),IFERROR(IRR(D86:I86,-0.6),-1))) -> 0.082502668 | E87: =SUM(E86:I86)/-D86 -> 1.4531844
B89: Block F: IRR by offer price (rows) x operating case (columns), base financing - from captured case cash flows
C90: Offer (A$/sh) | premium | E90: 1. Downside | F90: 2. Conservative | G90: 3. Sponsor base | H90: 4. Orals underwhelm | I90: 5. Upside (vitiligo) | J90: Expected (prob.-wtd flows)
C91: 9 | D91: =C91/LBO!$D$18-1 -> 0.09223301 | E91: =IF(-AS5<=0,"n.m.",IFERROR(IRR(AS5:AX5,0.15),IFERROR(IRR(AS5:AX5,-0.2),IFERROR(IRR(AS5:AX5,-0.6),-1)))) -> -0.075732114 | F91: =IF(-AS6<=0,"n.m.",IFERROR(IRR(AS6:AX6,0.15),IFERROR(IRR(AS6:AX6,-0.2),IFERROR(IRR(AS6:AX6,-0.6),-1)))) -> 0.092837538 | G91: =IF(-AS7<=0,"n.m.",IFERROR(IRR(AS7:AX7,0.15),IFERROR(IRR(AS7:AX7,-0.2),IFERROR(IRR(AS7:AX7,-0.6),-1)))) -> 0.21677765 | H91: =IF(-AS8<=0,"n.m.",IFERROR(IRR(AS8:AX8,0.15),IFERROR(IRR(AS8:AX8,-0.2),IFERROR(IRR(AS8:AX8,-0.6),-1)))) -> 0.36657256 | I91: =IF(-AS9<=0,"n.m.",IFERROR(IRR(AS9:AX9,0.15),IFERROR(IRR(AS9:AX9,-0.2),IFERROR(IRR(AS9:AX9,-0.6),-1)))) -> 0.44575401 | J91: =IFERROR(IRR(AZ91:BE91,0.15),IFERROR(IRR(AZ91:BE91,-0.2),IFERROR(IRR(AZ91:BE91,-0.6),-1))) -> 0.19037571 | AZ91: =-($D$80*($C$91*LBO!$D$23*(1+LBO!$D$39)+$Y$31)+$D$81*($C$91*LBO!$D$23*(1+LBO!$D$39)+$Y$32)+$D$82*($C$91*LBO!$D$23*(1+LBO!$D$39)+$Y$33)+$D$83*($C$91*LBO!$D$23*(1+LBO!$D$39)+$Y$34)+$D$84*($C$91*LBO!$D$23*(1+LBO!$D$39)+$Y$35)) -> -162.94746 | BA91: =SUMPRODUCT($D$80:$D$84,$Z$31:$Z$35) -> 0 | BB91: =SUMPRODUCT($D$80:$D$84,$AA$31:$AA$35) -> 1.5407053 | BC91: =SUMPRODUCT($D$80:$D$84,$AB$31:$AB$35) -> 31.595542 | BD91: =SUMPRODUCT($D$80:$D$84,$AC$31:$AC$35) -> 31.576169 | BE91: =SUMPRODUCT($D$80:$D$84,$AD$31:$AD$35)+SUMPRODUCT($D$80:$D$84,$R$31:$R$35) -> 304.5075
C92: 9.5 | D92: =C92/LBO!$D$18-1 -> 0.15291262 | E92: =IF(-AS10<=0,"n.m.",IFERROR(IRR(AS10:AX10,0.15),IFERROR(IRR(AS10:AX10,-0.2),IFERROR(IRR(AS10:AX10,-0.6),-1)))) -> -0.10397662 | F92: =IF(-AS11<=0,"n.m.",IFERROR(IRR(AS11:AX11,0.15),IFERROR(IRR(AS11:AX11,-0.2),IFERROR(IRR(AS11:AX11,-0.6),-1)))) -> 0.058876309 | G92: =IF(-AS12<=0,"n.m.",IFERROR(IRR(AS12:AX12,0.15),IFERROR(IRR(AS12:AX12,-0.2),IFERROR(IRR(AS12:AX12,-0.6),-1)))) -> 0.17784134 | H92: =IF(-AS13<=0,"n.m.",IFERROR(IRR(AS13:AX13,0.15),IFERROR(IRR(AS13:AX13,-0.2),IFERROR(IRR(AS13:AX13,-0.6),-1)))) -> 0.32236929 | I92: =IF(-AS14<=0,"n.m.",IFERROR(IRR(AS14:AX14,0.15),IFERROR(IRR(AS14:AX14,-0.2),IFERROR(IRR(AS14:AX14,-0.6),-1)))) -> 0.40129702 | J92: =IFERROR(IRR(AZ92:BE92,0.15),IFERROR(IRR(AZ92:BE92,-0.2),IFERROR(IRR(AZ92:BE92,-0.6),-1))) -> 0.153116 | AZ92: =-($D$80*($C$92*LBO!$D$23*(1+LBO!$D$39)+$Y$31)+$D$81*($C$92*LBO!$D$23*(1+LBO!$D$39)+$Y$32)+$D$82*($C$92*LBO!$D$23*(1+LBO!$D$39)+$Y$33)+$D$83*($C$92*LBO!$D$23*(1+LBO!$D$39)+$Y$34)+$D$84*($C$92*LBO!$D$23*(1+LBO!$D$39)+$Y$35)) -> -188.98431 | BA92: =SUMPRODUCT($D$80:$D$84,$Z$31:$Z$35) -> 0 | BB92: =SUMPRODUCT($D$80:$D$84,$AA$31:$AA$35) -> 1.5407053 | BC92: =SUMPRODUCT($D$80:$D$84,$AB$31:$AB$35) -> 31.595542 | BD92: =SUMPRODUCT($D$80:$D$84,$AC$31:$AC$35) -> 31.576169 | BE92: =SUMPRODUCT($D$80:$D$84,$AD$31:$AD$35)+SUMPRODUCT($D$80:$D$84,$R$31:$R$35) -> 304.5075
C93: 10 | D93: =C93/LBO!$D$18-1 -> 0.21359223 | E93: =IF(-AS15<=0,"n.m.",IFERROR(IRR(AS15:AX15,0.15),IFERROR(IRR(AS15:AX15,-0.2),IFERROR(IRR(AS15:AX15,-0.6),-1)))) -> -0.12786185 | F93: =IF(-AS16<=0,"n.m.",IFERROR(IRR(AS16:AX16,0.15),IFERROR(IRR(AS16:AX16,-0.2),IFERROR(IRR(AS16:AX16,-0.6),-1)))) -> 0.030199468 | G93: =IF(-AS17<=0,"n.m.",IFERROR(IRR(AS17:AX17,0.15),IFERROR(IRR(AS17:AX17,-0.2),IFERROR(IRR(AS17:AX17,-0.6),-1)))) -> 0.14512567 | H93: =IF(-AS18<=0,"n.m.",IFERROR(IRR(AS18:AX18,0.15),IFERROR(IRR(AS18:AX18,-0.2),IFERROR(IRR(AS18:AX18,-0.6),-1)))) -> 0.285288 | I93: =IF(-AS19<=0,"n.m.",IFERROR(IRR(AS19:AX19,0.15),IFERROR(IRR(AS19:AX19,-0.2),IFERROR(IRR(AS19:AX19,-0.6),-1)))) -> 0.36384062 | J93: =IFERROR(IRR(AZ93:BE93,0.15),IFERROR(IRR(AZ93:BE93,-0.2),IFERROR(IRR(AZ93:BE93,-0.6),-1))) -> 0.12171845 | AZ93: =-($D$80*($C$93*LBO!$D$23*(1+LBO!$D$39)+$Y$31)+$D$81*($C$93*LBO!$D$23*(1+LBO!$D$39)+$Y$32)+$D$82*($C$93*LBO!$D$23*(1+LBO!$D$39)+$Y$33)+$D$83*($C$93*LBO!$D$23*(1+LBO!$D$39)+$Y$34)+$D$84*($C$93*LBO!$D$23*(1+LBO!$D$39)+$Y$35)) -> -215.02116 | BA93: =SUMPRODUCT($D$80:$D$84,$Z$31:$Z$35) -> 0 | BB93: =SUMPRODUCT($D$80:$D$84,$AA$31:$AA$35) -> 1.5407053 | BC93: =SUMPRODUCT($D$80:$D$84,$AB$31:$AB$35) -> 31.595542 | BD93: =SUMPRODUCT($D$80:$D$84,$AC$31:$AC$35) -> 31.576169 | BE93: =SUMPRODUCT($D$80:$D$84,$AD$31:$AD$35)+SUMPRODUCT($D$80:$D$84,$R$31:$R$35) -> 304.5075
C94: 10.5 | D94: =C94/LBO!$D$18-1 -> 0.27427184 | E94: =IF(-AS20<=0,"n.m.",IFERROR(IRR(AS20:AX20,0.15),IFERROR(IRR(AS20:AX20,-0.2),IFERROR(IRR(AS20:AX20,-0.6),-1)))) -> -0.14847511 | F94: =IF(-AS21<=0,"n.m.",IFERROR(IRR(AS21:AX21,0.15),IFERROR(IRR(AS21:AX21,-0.2),IFERROR(IRR(AS21:AX21,-0.6),-1)))) -> 0.0054814413 | G94: =IF(-AS22<=0,"n.m.",IFERROR(IRR(AS22:AX22,0.15),IFERROR(IRR(AS22:AX22,-0.2),IFERROR(IRR(AS22:AX22,-0.6),-1)))) -> 0.11703308 | H94: =IF(-AS23<=0,"n.m.",IFERROR(IRR(AS23:AX23,0.15),IFERROR(IRR(AS23:AX23,-0.2),IFERROR(IRR(AS23:AX23,-0.6),-1)))) -> 0.2534873 | I94: =IF(-AS24<=0,"n.m.",IFERROR(IRR(AS24:AX24,0.15),IFERROR(IRR(AS24:AX24,-0.2),IFERROR(IRR(AS24:AX24,-0.6),-1)))) -> 0.33160245 | J94: =IFERROR(IRR(AZ94:BE94,0.15),IFERROR(IRR(AZ94:BE94,-0.2),IFERROR(IRR(AZ94:BE94,-0.6),-1))) -> 0.094696862 | AZ94: =-($D$80*($C$94*LBO!$D$23*(1+LBO!$D$39)+$Y$31)+$D$81*($C$94*LBO!$D$23*(1+LBO!$D$39)+$Y$32)+$D$82*($C$94*LBO!$D$23*(1+LBO!$D$39)+$Y$33)+$D$83*($C$94*LBO!$D$23*(1+LBO!$D$39)+$Y$34)+$D$84*($C$94*LBO!$D$23*(1+LBO!$D$39)+$Y$35)) -> -241.05801 | BA94: =SUMPRODUCT($D$80:$D$84,$Z$31:$Z$35) -> 0 | BB94: =SUMPRODUCT($D$80:$D$84,$AA$31:$AA$35) -> 1.5407053 | BC94: =SUMPRODUCT($D$80:$D$84,$AB$31:$AB$35) -> 31.595542 | BD94: =SUMPRODUCT($D$80:$D$84,$AC$31:$AC$35) -> 31.576169 | BE94: =SUMPRODUCT($D$80:$D$84,$AD$31:$AD$35)+SUMPRODUCT($D$80:$D$84,$R$31:$R$35) -> 304.5075
C95: 11 | D95: =C95/LBO!$D$18-1 -> 0.33495146 | E95: =IF(-AS25<=0,"n.m.",IFERROR(IRR(AS25:AX25,0.15),IFERROR(IRR(AS25:AX25,-0.2),IFERROR(IRR(AS25:AX25,-0.6),-1)))) -> -0.16655006 | F95: =IF(-AS26<=0,"n.m.",IFERROR(IRR(AS26:AX26,0.15),IFERROR(IRR(AS26:AX26,-0.2),IFERROR(IRR(AS26:AX26,-0.6),-1)))) -> -0.016170264 | G95: =IF(-AS27<=0,"n.m.",IFERROR(IRR(AS27:AX27,0.15),IFERROR(IRR(AS27:AX27,-0.2),IFERROR(IRR(AS27:AX27,-0.6),-1)))) -> 0.092499123 | H95: =IF(-AS28<=0,"n.m.",IFERROR(IRR(AS28:AX28,0.15),IFERROR(IRR(AS28:AX28,-0.2),IFERROR(IRR(AS28:AX28,-0.6),-1)))) -> 0.22574372 | I95: =IF(-AS29<=0,"n.m.",IFERROR(IRR(AS29:AX29,0.15),IFERROR(IRR(AS29:AX29,-0.2),IFERROR(IRR(AS29:AX29,-0.6),-1)))) -> 0.30339136 | J95: =IFERROR(IRR(AZ95:BE95,0.15),IFERROR(IRR(AZ95:BE95,-0.2),IFERROR(IRR(AZ95:BE95,-0.6),-1))) -> 0.071055377 | AZ95: =-($D$80*($C$95*LBO!$D$23*(1+LBO!$D$39)+$Y$31)+$D$81*($C$95*LBO!$D$23*(1+LBO!$D$39)+$Y$32)+$D$82*($C$95*LBO!$D$23*(1+LBO!$D$39)+$Y$33)+$D$83*($C$95*LBO!$D$23*(1+LBO!$D$39)+$Y$34)+$D$84*($C$95*LBO!$D$23*(1+LBO!$D$39)+$Y$35)) -> -267.09486 | BA95: =SUMPRODUCT($D$80:$D$84,$Z$31:$Z$35) -> 0 | BB95: =SUMPRODUCT($D$80:$D$84,$AA$31:$AA$35) -> 1.5407053 | BC95: =SUMPRODUCT($D$80:$D$84,$AB$31:$AB$35) -> 31.595542 | BD95: =SUMPRODUCT($D$80:$D$84,$AC$31:$AC$35) -> 31.576169 | BE95: =SUMPRODUCT($D$80:$D$84,$AD$31:$AD$35)+SUMPRODUCT($D$80:$D$84,$R$31:$R$35) -> 304.5075
C96: 11.5 | D96: =C96/LBO!$D$18-1 -> 0.39563107 | E96: =IF(-AS30<=0,"n.m.",IFERROR(IRR(AS30:AX30,0.15),IFERROR(IRR(AS30:AX30,-0.2),IFERROR(IRR(AS30:AX30,-0.6),-1)))) -> -0.18260362 | F96: =IF(-AS31<=0,"n.m.",IFERROR(IRR(AS31:AX31,0.15),IFERROR(IRR(AS31:AX31,-0.2),IFERROR(IRR(AS31:AX31,-0.6),-1)))) -> -0.035383369 | G96: =IF(-AS32<=0,"n.m.",IFERROR(IRR(AS32:AX32,0.15),IFERROR(IRR(AS32:AX32,-0.2),IFERROR(IRR(AS32:AX32,-0.6),-1)))) -> 0.070781247 | H96: =IF(-AS33<=0,"n.m.",IFERROR(IRR(AS33:AX33,0.15),IFERROR(IRR(AS33:AX33,-0.2),IFERROR(IRR(AS33:AX33,-0.6),-1)))) -> 0.20120575 | I96: =IF(-AS34<=0,"n.m.",IFERROR(IRR(AS34:AX34,0.15),IFERROR(IRR(AS34:AX34,-0.2),IFERROR(IRR(AS34:AX34,-0.6),-1)))) -> 0.27837422 | J96: =IFERROR(IRR(AZ96:BE96,0.15),IFERROR(IRR(AZ96:BE96,-0.2),IFERROR(IRR(AZ96:BE96,-0.6),-1))) -> 0.050096216 | AZ96: =-($D$80*($C$96*LBO!$D$23*(1+LBO!$D$39)+$Y$31)+$D$81*($C$96*LBO!$D$23*(1+LBO!$D$39)+$Y$32)+$D$82*($C$96*LBO!$D$23*(1+LBO!$D$39)+$Y$33)+$D$83*($C$96*LBO!$D$23*(1+LBO!$D$39)+$Y$34)+$D$84*($C$96*LBO!$D$23*(1+LBO!$D$39)+$Y$35)) -> -293.13171 | BA96: =SUMPRODUCT($D$80:$D$84,$Z$31:$Z$35) -> 0 | BB96: =SUMPRODUCT($D$80:$D$84,$AA$31:$AA$35) -> 1.5407053 | BC96: =SUMPRODUCT($D$80:$D$84,$AB$31:$AB$35) -> 31.595542 | BD96: =SUMPRODUCT($D$80:$D$84,$AC$31:$AC$35) -> 31.576169 | BE96: =SUMPRODUCT($D$80:$D$84,$AD$31:$AD$35)+SUMPRODUCT($D$80:$D$84,$R$31:$R$35) -> 304.5075
C97: 12 | D97: =C97/LBO!$D$18-1 -> 0.45631068 | E97: =IF(-AS35<=0,"n.m.",IFERROR(IRR(AS35:AX35,0.15),IFERROR(IRR(AS35:AX35,-0.2),IFERROR(IRR(AS35:AX35,-0.6),-1)))) -> -0.19701287 | F97: =IF(-AS36<=0,"n.m.",IFERROR(IRR(AS36:AX36,0.15),IFERROR(IRR(AS36:AX36,-0.2),IFERROR(IRR(AS36:AX36,-0.6),-1)))) -> -0.052615054 | G97: =IF(-AS37<=0,"n.m.",IFERROR(IRR(AS37:AX37,0.15),IFERROR(IRR(AS37:AX37,-0.2),IFERROR(IRR(AS37:AX37,-0.6),-1)))) -> 0.051342199 | H97: =IF(-AS38<=0,"n.m.",IFERROR(IRR(AS38:AX38,0.15),IFERROR(IRR(AS38:AX38,-0.2),IFERROR(IRR(AS38:AX38,-0.6),-1)))) -> 0.17925846 | I97: =IF(-AS39<=0,"n.m.",IFERROR(IRR(AS39:AX39,0.15),IFERROR(IRR(AS39:AX39,-0.2),IFERROR(IRR(AS39:AX39,-0.6),-1)))) -> 0.25594686 | J97: =IFERROR(IRR(AZ97:BE97,0.15),IFERROR(IRR(AZ97:BE97,-0.2),IFERROR(IRR(AZ97:BE97,-0.6),-1))) -> 0.031312692 | AZ97: =-($D$80*($C$97*LBO!$D$23*(1+LBO!$D$39)+$Y$31)+$D$81*($C$97*LBO!$D$23*(1+LBO!$D$39)+$Y$32)+$D$82*($C$97*LBO!$D$23*(1+LBO!$D$39)+$Y$33)+$D$83*($C$97*LBO!$D$23*(1+LBO!$D$39)+$Y$34)+$D$84*($C$97*LBO!$D$23*(1+LBO!$D$39)+$Y$35)) -> -319.16856 | BA97: =SUMPRODUCT($D$80:$D$84,$Z$31:$Z$35) -> 0 | BB97: =SUMPRODUCT($D$80:$D$84,$AA$31:$AA$35) -> 1.5407053 | BC97: =SUMPRODUCT($D$80:$D$84,$AB$31:$AB$35) -> 31.595542 | BD97: =SUMPRODUCT($D$80:$D$84,$AC$31:$AC$35) -> 31.576169 | BE97: =SUMPRODUCT($D$80:$D$84,$AD$31:$AD$35)+SUMPRODUCT($D$80:$D$84,$R$31:$R$35) -> 304.5075
C98: 12.5 | D98: =C98/LBO!$D$18-1 -> 0.51699029 | E98: =IF(-AS40<=0,"n.m.",IFERROR(IRR(AS40:AX40,0.15),IFERROR(IRR(AS40:AX40,-0.2),IFERROR(IRR(AS40:AX40,-0.6),-1)))) -> -0.21006075 | F98: =IF(-AS41<=0,"n.m.",IFERROR(IRR(AS41:AX41,0.15),IFERROR(IRR(AS41:AX41,-0.2),IFERROR(IRR(AS41:AX41,-0.6),-1)))) -> -0.068207938 | G98: =IF(-AS42<=0,"n.m.",IFERROR(IRR(AS42:AX42,0.15),IFERROR(IRR(AS42:AX42,-0.2),IFERROR(IRR(AS42:AX42,-0.6),-1)))) -> 0.033781548 | H98: =IF(-AS43<=0,"n.m.",IFERROR(IRR(AS43:AX43,0.15),IFERROR(IRR(AS43:AX43,-0.2),IFERROR(IRR(AS43:AX43,-0.6),-1)))) -> 0.15944427 | I98: =IF(-AS44<=0,"n.m.",IFERROR(IRR(AS44:AX44,0.15),IFERROR(IRR(AS44:AX44,-0.2),IFERROR(IRR(AS44:AX44,-0.6),-1)))) -> 0.23565805 | J98: =IFERROR(IRR(AZ98:BE98,0.15),IFERROR(IRR(AZ98:BE98,-0.2),IFERROR(IRR(AZ98:BE98,-0.6),-1))) -> 0.01432602 | AZ98: =-($D$80*($C$98*LBO!$D$23*(1+LBO!$D$39)+$Y$31)+$D$81*($C$98*LBO!$D$23*(1+LBO!$D$39)+$Y$32)+$D$82*($C$98*LBO!$D$23*(1+LBO!$D$39)+$Y$33)+$D$83*($C$98*LBO!$D$23*(1+LBO!$D$39)+$Y$34)+$D$84*($C$98*LBO!$D$23*(1+LBO!$D$39)+$Y$35)) -> -345.20541 | BA98: =SUMPRODUCT($D$80:$D$84,$Z$31:$Z$35) -> 0 | BB98: =SUMPRODUCT($D$80:$D$84,$AA$31:$AA$35) -> 1.5407053 | BC98: =SUMPRODUCT($D$80:$D$84,$AB$31:$AB$35) -> 31.595542 | BD98: =SUMPRODUCT($D$80:$D$84,$AC$31:$AC$35) -> 31.576169 | BE98: =SUMPRODUCT($D$80:$D$84,$AD$31:$AD$35)+SUMPRODUCT($D$80:$D$84,$R$31:$R$35) -> 304.5075
C99: 13 | D99: =C99/LBO!$D$18-1 -> 0.5776699 | E99: =IF(-AS45<=0,"n.m.",IFERROR(IRR(AS45:AX45,0.15),IFERROR(IRR(AS45:AX45,-0.2),IFERROR(IRR(AS45:AX45,-0.6),-1)))) -> -0.22196467 | F99: =IF(-AS46<=0,"n.m.",IFERROR(IRR(AS46:AX46,0.15),IFERROR(IRR(AS46:AX46,-0.2),IFERROR(IRR(AS46:AX46,-0.6),-1)))) -> -0.082424968 | G99: =IF(-AS47<=0,"n.m.",IFERROR(IRR(AS47:AX47,0.15),IFERROR(IRR(AS47:AX47,-0.2),IFERROR(IRR(AS47:AX47,-0.6),-1)))) -> 0.017793378 | H99: =IF(-AS48<=0,"n.m.",IFERROR(IRR(AS48:AX48,0.15),IFERROR(IRR(AS48:AX48,-0.2),IFERROR(IRR(AS48:AX48,-0.6),-1)))) -> 0.14141409 | I99: =IF(-AS49<=0,"n.m.",IFERROR(IRR(AS49:AX49,0.15),IFERROR(IRR(AS49:AX49,-0.2),IFERROR(IRR(AS49:AX49,-0.6),-1)))) -> 0.21716239 | J99: =IFERROR(IRR(AZ99:BE99,0.15),IFERROR(IRR(AZ99:BE99,-0.2),IFERROR(IRR(AZ99:BE99,-0.6),-1))) -> -0.0011539182 | AZ99: =-($D$80*($C$99*LBO!$D$23*(1+LBO!$D$39)+$Y$31)+$D$81*($C$99*LBO!$D$23*(1+LBO!$D$39)+$Y$32)+$D$82*($C$99*LBO!$D$23*(1+LBO!$D$39)+$Y$33)+$D$83*($C$99*LBO!$D$23*(1+LBO!$D$39)+$Y$34)+$D$84*($C$99*LBO!$D$23*(1+LBO!$D$39)+$Y$35)) -> -371.24226 | BA99: =SUMPRODUCT($D$80:$D$84,$Z$31:$Z$35) -> 0 | BB99: =SUMPRODUCT($D$80:$D$84,$AA$31:$AA$35) -> 1.5407053 | BC99: =SUMPRODUCT($D$80:$D$84,$AB$31:$AB$35) -> 31.595542 | BD99: =SUMPRODUCT($D$80:$D$84,$AC$31:$AC$35) -> 31.576169 | BE99: =SUMPRODUCT($D$80:$D$84,$AD$31:$AD$35)+SUMPRODUCT($D$80:$D$84,$R$31:$R$35) -> 304.5075
C101: Note: IRRs include interim distributions (cash above minimum cash once debt is repaid). Case exit multiples: Downside 3.5x, Conservative 4.5x, Sponsor base 5.5x, Orals underwhelm 7.0x, Upside (vitiligo) 9.0x.

Sheet CVR
B2: Contingent value rights (CVR) - bridging the bid-ask on competition and vitiligo
B3: Illustrative. CVR 1 pays if SCENESSE holds up (FY29 EPP revenue threshold); CVR 2 pays on vitiligo approval.
B5: Inputs
B6: Fully diluted shares (m) | C6: =LBO!D23 -> 50.68 | H6: Design logic: CVR 1 transfers the dersimelagon/bitopertin outcome risk back to sellers - it only pays in the cases where SCENESSE revenue holds up, i.e. when the sponsor can afford it. CVR 2 lets holders keep the vitiligo option without the sponsor funding CUV107 on spec. CVRs are uncommon in ASX schemes (need IER valuation and disclosure) but standard in US biotech M&A; non-transferable CVRs avoid US registration.
B7: Cash offer per share (A$) | C7: =LBO!D19 -> 10.75
B8: CVR 1: payment per share (A$) if FY29E SCENESSE revenue >= threshold | C8: 1
B9: CVR 1: FY29E SCENESSE revenue threshold (A$m) | C9: 90
B10: CVR 1: years from close to payment | C10: 2.25
B11: CVR 2: payment per share (A$) on FDA/EC vitiligo approval by 30-Jun-2030 | C11: 1
B12: CVR 2: probability of approval by 30-Jun-2030 (unconditional, incl. CUV105 risk) | C12: 0.3
B13: CVR 2: years from close to payment | C13: 3
B14: Discount rate for CVR valuation | C14: 0.12
B16: CVR 1 trigger by operating case (captured FY29E SCENESSE revenue)
B17: Operating case | C17: Prob. | D17: FY29E SCEN. | E17: Triggers?
B18: 1. Downside | C18: =Sensitivity!D80 -> 0.2 | D18: =Sensitivity!L31 -> 71.471027 | E18: =IF(D18>=$C$9,1,0) -> 0
B19: 2. Conservative | C19: =Sensitivity!D81 -> 0.3 | D19: =Sensitivity!L32 -> 80.317181 | E19: =IF(D19>=$C$9,1,0) -> 0
B20: 3. Sponsor base | C20: =Sensitivity!D82 -> 0.3 | D20: =Sensitivity!L33 -> 87.739812 | E20: =IF(D20>=$C$9,1,0) -> 0
B21: 4. Orals underwhelm | C21: =Sensitivity!D83 -> 0.15 | D21: =Sensitivity!L34 -> 98.30228 | E21: =IF(D21>=$C$9,1,0) -> 1
B22: 5. Upside (vitiligo) | C22: =Sensitivity!D84 -> 0.05 | D22: =Sensitivity!L35 -> 98.30228 | E22: =IF(D22>=$C$9,1,0) -> 1
B24: Valuation
B25: CVR 1 probability (sum of triggering case weights) | C25: =SUMPRODUCT(C18:C22,E18:E22) -> 0.2
B26: CVR 1 expected PV per share (A$) | C26: =C8*C25/(1+C14)^C10 -> 0.15498492
B27: CVR 2 expected PV per share (A$) | C27: =C11*C12/(1+C14)^C13 -> 0.21353407
B28: Headline value per share: cash + CVR face (A$) | C28: =C7+C8+C11 -> 12.75
B29: Risk-adjusted value per share: cash + expected PV of CVRs (A$) | C29: =C7+C26+C27 -> 11.118519
B30: Expected PV cost to sponsor (A$m) | C30: =(C26+C27)*C6 -> 18.676543
B31: Maximum CVR payout (A$m, undiscounted) | C31: =(C8+C11)*C6 -> 101.36
